Workbook
Name AC_DEPOSITS: #REF!
Name ACRegion: #REF!
Name ACT1_LF: #REF!
Name ACT2_LF: #REF!
Name AMZ_OTHER: #REF!
Name AMZ_OTHER_CC: #REF!
Name AMZ_STATIONS: #REF!
Name AMZ_TO: #REF!
Name AMZ_WAGES: #REF!
Name AMZ_WAGES_CC: #REF!
Name amzAOs: #REF!
Name ANC_INCREASE_All_Markets: #REF!
Name AO_GA: #REF!
Name ATR72_LF: #REF!
Name AVG_BH_CAR_PIL: #REF!
Name AVG_BH_PIL: #REF!
Name BB_DEPR: #REF!
Name BB_GA_Salaries: #REF!
Name BB_OTHER: #REF!
Name BB_SALARIES: #REF!
Name BB_Wages: #REF!
Name CA_Rate: #REF!
Name CARGO_Pilots: #REF!
Name ColumnsIntoTable: CHOOSE({1,2},#REF!,#REF!)
Name ColumnsIntoTable: CHOOSE({1,2},#REF!,#REF!)
Name ColumnsIntoTable: CHOOSE({1,2},#REF!,#REF!)
Name ColumnsIntoTable: CHOOSE({1,2},#REF!,#REF!)
Name ColumnsIntoTable: CHOOSE({1,2},#REF!,#REF!)
Name COMM_BB_Incr: #REF!
Name COMM_BB_TOTAL: #REF!
Name COMM_Sil_Incr: #REF!
Name COMM_Silver_TOTAL: #REF!
Name Delivery_Month_OPLEASE: #REF!
Name Fare_change: #REF!
Name Flying_Attrition: #REF!
Name FO_Rate: #REF!
Name FUELTREND: #REF!
Name GA_Salaries: #REF!
Name GOODWILL: #REF!
Name HVYCHK_REIMB_RESERVES: #REF!
Name INTANGIBLE_ACC_AMORT: #REF!
Name IQ_CH: 110000
Name IQ_CQ: 5000
Name IQ_CY: 10000
Name IQ_DAILY: 500000
Name IQ_FH: 100000
Name IQ_FQ: 500
Name IQ_FY: 1000
Name IQ_LTM: 2000
Name IQ_MONTH: 15000
Name IQ_NTM: 6000
Name IQ_WEEK: 50000
Name IQ_YTD: 3000
Name IS_Seaborne_YR: #REF!
Name IS_Silver_YR: #REF!
Name LESS_ACC_DEPR: #REF!
Name LOAD_FACTOR_ADJUSTMENTS: #REF!
Name MAINT_BB_TOTAL: #REF!
Name MAINT_SIL_TOTAL: #REF!
Name MONTHLY_BAL: #REF!

Sheet basic
D1: avion 1 | G1: avion 2 | L1: avion 1 | O1: avion 2 | T1: avion 1 | W1: avion 2 | Z1: avion 3 | AC1: avion 4
B2: vuelo | C2: ruta | D2: horas | E2: kg | F2: ruta | G2: horas | H2: kg | J2: vuelo | K2: ruta | L2: horas | M2: kg | N2: ruta | O2: horas | P2: kg | R2: vuelo | S2: ruta | T2: horas | U2: kg | V2: ruta | W2: horas | X2: kg | Y2: ruta | Z2: horas | AA2: kg | AB2: ruta | AC2: horas | AD2: kg
B3: 1 | C3: mde-kin | D3: 2.5 | E3: 24000 | F3: mia kin | G3: 2.5 | H3: 24000 | J3: 1 | K3: mde-kin | L3: 2.5 | M3: 24000 | N3: mia kin | O3: 2.5 | P3: 24000 | R3: 1 | S3: mde-kin | T3: 2.5 | U3: 24000 | V3: mia kin | W3: 2.5 | X3: 24000 | Y3: mia kin | Z3: 2.5 | AA3: 24000 | AB3: gso eur | AC3: 12 | AD3: 102000
B4: 2 | C4: kin-mde | D4: 2.5 | F4: kin-mia | G4: 2.5 | J4: 2 | K4: kin-mde | L4: 2.5 | N4: kin-mia | O4: 2.5 | R4: 2 | S4: kin-mde | T4: 2.5 | V4: kin-mia | W4: 2.5 | Y4: kin-mia | Z4: 2.5 | AB4: eur gso | AC4: 12 | AD4: 102000
B5: 3 | C5: mde- mia | D5: 3 | E5: 24000 | J5: 3 | K5: mde- mia | L5: 3 | M5: 24000 | R5: 3 | S5: mde- mia | T5: 3 | U5: 24000
B6: 4 | C6: mia mde | D6: 3 | E6: 12000 | J6: 4 | K6: mia mde | L6: 3 | M6: 12000 | R6: 4 | S6: mia mde | T6: 3 | U6: 12000
B9: total | D9: =SUM(D3:D8) -> 11 | E9: =SUM(E3:E8) -> 60000 | G9: =SUM(G3:G8) -> 5 | H9: =SUM(H3:H8) -> 24000 | J9: total | L9: =SUM(L3:L8) -> 11 | M9: =SUM(M3:M8) -> 60000 | O9: =SUM(O3:O8) -> 5 | P9: =SUM(P3:P8) -> 24000 | R9: total | T9: =SUM(T3:T8) -> 11 | U9: =SUM(U3:U8) -> 60000 | W9: =SUM(W3:W8) -> 5 | X9: =SUM(X3:X8) -> 24000 | Z9: =SUM(Z3:Z8) -> 5 | AA9: =SUM(AA3:AA8) -> 24000 | AC9: =SUM(AC3:AC8) -> 24 | AD9: =SUM(AD3:AD8) -> 204000
E10: dia | F10: 1 | G10: =D9+G9 -> 16 | H10: =E9+H9 -> 84000 | M10: dia | N10: 1 | O10: =L9+O9 -> 16 | P10: =M9+P9 -> 84000 | X10: dia | Y10: 1 | Z10: =T9+W9+Z9 -> 21 | AA10: =U9+X9+AA9 -> 108000 | AB10: 1 | AC10: =AC9*Y10 -> 24 | AD10: =AD9*AB10 -> 204000
E11: semana | F11: 6 | G11: =G10*F11 -> 96 | H11: =H10*F11 -> 504000 | M11: semana | N11: 7 | O11: =O10*N11 -> 112 | P11: =P10*N11 -> 588000 | X11: semana | Y11: 7 | Z11: =Z10*Y11 -> 147 | AA11: =AA10*Y11 -> 756000 | AB11: 2 | AC11: =AC10*AB11 -> 48 | AD11: =AD10*AB11 -> 408000
E12: mes | F12: 4 | G12: =G11*F12 -> 384 | H12: =H11*F12 -> 2016000 | M12: mes | N12: 4 | O12: =O11*N12 -> 448 | P12: =P11*N12 -> 2352000 | X12: mes | Y12: 4 | Z12: =Z11*Y12 -> 588 | AA12: =AA11*Y12 -> 3024000 | AB12: 4 | AC12: =AC11*AB12 -> 192 | AD12: =AD11*AB12 -> 1632000
E13: ano | F13: 12 | G13: =G12*F13 -> 4608 | H13: =H12*F13 -> 24192000 | M13: ano | N13: 12 | O13: =O12*N13 -> 5376 | P13: =P12*N13 -> 28224000 | X13: ano | Y13: 12 | Z13: =Z12*Y13 -> 7056 | AA13: =AA12*Y13 -> 36288000 | AB13: 12 | AC13: =AC12*AB13 -> 2304 | AD13: =AD12*AB13 -> 19584000
E14: total costoS | G14: =G13*variables!$C$3 -> 41472000 | H14: =H13*variables!$C$5 -> 72576000 | M14: total costoS | O14: =O13*variables!$C$3 -> 48384000 | P14: =P13*variables!$C$5 -> 84672000 | X14: total costoS | Z14: =Z13*variables!$C$3 -> 63504000 | AA14: =AA13*variables!$C$5 -> 108864000 | AC14: =AC13*variables!$D$3 -> 41472000 | AD14: =AD13*variables!$C$5 -> 58752000
E15: utilidad | G15: =G14/H13 -> 1.7142857 | H15: =H13*variables!$C$6 -> 48384000 | M15: utilidad | O15: =O14/P13 -> 1.7142857 | P15: =P13*variables!$C$6 -> 56448000 | X15: utilidad | Z15: =Z14/AA13 -> 1.75 | AA15: =AA13*variables!$C$6 -> 72576000 | AC15: =AC14/AD13 -> 2.1176471 | AD15: =AD13*variables!$D$6 -> 34272000
E16: total | H16: =G14+H14+H15 -> 162432000 | M16: total | P16: =O14+P14+P15 -> 189504000 | X16: total | AA16: =Z14+AA14+AA15 -> 244944000 | AD16: =AC14+AD14+AD15 -> 134496000
B18: vuelo | C18: ruta | D18: horas | E18: kg | F18: ruta | G18: horas | H18: kg | J18: vuelo | K18: ruta | L18: horas | M18: kg | N18: ruta | O18: horas | P18: kg | R18: vuelo | S18: ruta | T18: horas | U18: kg | V18: ruta | W18: horas | X18: kg | Y18: ruta | Z18: horas | AA18: kg
B19: 5 | F19: mde- mia | G19: 3 | H19: 24000 | J19: 5 | K19: mde- mia | L19: 3 | M19: 24000 | N19: mde- mia | O19: 3 | P19: 24000 | R19: 5 | S19: mde- mia | T19: 3 | U19: 24000 | Y19: mde- mia | Z19: 3 | AA19: 24000
B20: 6 | F20: mia mde | G20: 3 | H20: 12000 | J20: 6 | K20: mia mde | L20: 3 | M20: 12000 | R20: 6 | S20: mia mde | T20: 3 | U20: 12000 | Y20: mia mde | Z20: 3 | AA20: 12000
B22: total | D22: =SUM(D19:D21) -> 0 | E22: =SUM(E19:E21) -> 0 | F22: =SUM(F19:F21) -> 0 | G22: =SUM(G19:G21) -> 6 | H22: =SUM(H19:H21) -> 36000 | J22: total | L22: =SUM(L19:L21) -> 6 | M22: =SUM(M19:M21) -> 36000 | N22: =SUM(N19:N21) -> 0 | O22: =SUM(O19:O21) -> 3 | P22: =SUM(P19:P21) -> 24000 | R22: total | T22: =SUM(T19:T21) -> 6 | U22: =SUM(U19:U21) -> 36000 | V22: =SUM(V19:V21) -> 0 | W22: =SUM(W19:W21) -> 0 | X22: =SUM(X19:X21) -> 0 | Z22: =SUM(Z19:Z21) -> 6 | AA22: =SUM(AA19:AA21) -> 36000
E23: dia | F23: 1 | G23: =D22+G22 -> 6 | H23: =E22+H22 -> 36000 | M23: dia | N23: 1 | O23: =L22+O22 -> 9 | P23: =M22+P22 -> 60000 | X23: dia | Y23: 1 | Z23: =T22+W22+Z22 -> 12 | AA23: =U22+X22+AA22 -> 72000
E24: semana | F24: 7 | G24: =G23*F24 -> 42 | H24: =H23*F24 -> 252000 | M24: semana | N24: 7 | O24: =O23*N24 -> 63 | P24: =P23*N24 -> 420000 | T24: =T9+W9+Z9+Z22+W22+T22 -> 33 | X24: semana | Y24: 7 | Z24: =Z23*Y24 -> 84 | AA24: =AA23*Y24 -> 504000
E25: mes | F25: 4 | G25: =G24*F25 -> 168 | H25: =H24*F25 -> 1008000 | M25: mes | N25: 4 | O25: =O24*N25 -> 252 | P25: =P24*N25 -> 1680000 | X25: mes | Y25: 4 | Z25: =Z24*Y25 -> 336 | AA25: =AA24*Y25 -> 2016000
E26: ano | F26: 12 | G26: =G25*F26 -> 2016 | H26: =H25*F26 -> 12096000 | M26: ano | N26: 12 | O26: =O25*N26 -> 3024 | P26: =P25*N26 -> 20160000 | X26: ano | Y26: 12 | Z26: =Z25*Y26 -> 4032 | AA26: =AA25*Y26 -> 24192000
E27: total costoS | G27: =G26*variables!$C$3 -> 18144000 | M27: total costoS | O27: =O26*variables!$C$3 -> 27216000 | X27: total costoS | Z27: =Z26*variables!$C$4 -> 40320000
E28: utilidad | G28: =G27/H26 -> 1.5 | M28: utilidad | O28: =O27/P26 -> 1.35 | X28: utilidad | Y28: =Z27/AA26 -> 1.6666667
E29: total | H29: =G27+H27+H28 -> 18144000 | M29: total | P29: =O27+P27+P28 -> 27216000 | X29: total | AA29: =Z27+AA27+AA28 -> 40320000
E31: total | G31: =G26+G13 -> 6624 | H31: =H26+H13 -> 36288000 | M31: total | O31: =O26+O13 -> 8400 | P31: =P26+P13 -> 48384000 | X31: total 321 | Z31: =Z26+Z13 -> 11088 | AA31: =AA26+AA13 -> 60480000 | AB31: total b777 | AC31: =AC13 -> 2304 | AD31: =AD13 -> 19584000
W33: a321 | X33: b777
F34: fuel cost | G34: =G31*variables!$C$11*variables!$C$12 -> 17884800 | N34: fuel cost | O34: =O31*variables!$C$11*variables!$C$12 -> 22680000 | V34: fuel cost | W34: =Z31*variables!$C$11*variables!$C$12 -> 29937600 | X34: =AC31*variables!$D$11*variables!$C$12 -> 12441600 | Y34: =SUM(W34:X34) -> 42379200
F35: cargo hand | H35: =H31*variables!$C$9 -> 3628800 | N35: cargo hand | P35: =P31*variables!$C$9 -> 4838400 | V35: cargo hand | W35: =AA31*variables!$C$9 -> 6048000 | X35: =AD31*variables!$C$9 -> 1958400 | Y35: =SUM(W35:X35) -> 8006400
F36: sobrevuelo | G36: =G31*variables!$C$13*variables!$C$10 -> 1159200 | N36: sobrevuelo | O36: =O31*variables!$C$13*variables!$C$10 -> 1470000 | V36: sobrevuelo | W36: =Z31*variables!$C$13*variables!$C$10 -> 1940400 | X36: =AC31*variables!$C$13*variables!$C$10 -> 403200 | Y36: =SUM(W36:X36) -> 2343600
F37: mantenimiento | G37: =G31*variables!$C$14 -> 9936000 | N37: mantenimiento | O37: =O31*variables!$C$14 -> 12600000 | V37: mantenimiento | W37: =Z31*variables!$C$14 -> 16632000 | X37: =AC31*variables!$D$14 -> 14976000 | Y37: =SUM(W37:X37) -> 31608000
W41: =400000/26 -> 15384.615
D46: avion 1 | G46: avion 2 | J46: avion 3 | M46: avion 4
B47: vuelo | C47: ruta | D47: horas | E47: kg | F47: ruta | G47: horas | H47: kg | I47: ruta | J47: horas | K47: kg | L47: ruta | M47: horas | N47: kg
B48: 1 | C48: mde-kin | D48: 2.5 | E48: 24000 | F48: mia kin | G48: 2.5 | H48: 24000 | I48: mia kin | J48: 2.5 | K48: 24000 | L48: gso eur | M48: 12 | N48: 102000
B49: 2 | C49: kin-mde | D49: 2.5 | F49: kin-mia | G49: 2.5 | I49: kin-mia | J49: 2.5 | L49: eur gso | M49: 12 | N49: 102000
B50: 3 | C50: mde- mia | D50: 3 | E50: 24000 | F50: mia kin | G50: 2.5 | H50: 24000 | I50: mia kin | J50: 2.5 | K50: 24000 | L50: eur gso | M50: 12 | N50: 102000
B51: 4 | C51: mia mde | D51: 3 | E51: 12000 | F51: kin-mia | G51: 2.5 | I51: kin-mia | J51: 2.5
C52: mde- mia | D52: 3 | E52: 24000
C53: mia mde | D53: 3 | E53: 12000
B54: total | D54: =SUM(D48:D53) -> 17 | E54: =SUM(E48:E53) -> 96000 | G54: =SUM(G48:G53) -> 10 | H54: =SUM(H48:H53) -> 48000 | J54: =SUM(J48:J53) -> 10 | K54: =SUM(K48:K53) -> 48000 | M54: =SUM(M48:M53) -> 36 | N54: =SUM(N48:N53) -> 306000
H55: dia | I55: 1 | J55: =D54+G54+J54 -> 37 | K55: =E54+H54+K54 -> 192000 | L55: 1 | M55: =M54*I55 -> 36 | N55: =N54*L55 -> 306000
H56: semana | I56: 7 | J56: =J55*I56 -> 259 | K56: =K55*I56 -> 1344000 | L56: 2 | M56: =M55*L56 -> 72 | N56: =N55*L56 -> 612000
H57: mes | I57: 4 | J57: =J56*I57 -> 1036 | K57: =K56*I57 -> 5376000 | L57: 4 | M57: =M56*L57 -> 288 | N57: =N56*L57 -> 2448000
H58: ano | I58: 12 | J58: =J57*I58 -> 12432 | K58: =K57*I58 -> 64512000 | L58: 12 | M58: =M57*L58 -> 3456 | N58: =N57*L58 -> 29376000
H59: total costoS | J59: =J58*variables!$C$3 -> 111888000 | K59: =K58*variables!$C$5 -> 193536000 | M59: =M58*variables!$D$3 -> 62208000 | N59: =N58*variables!$C$5 -> 88128000
H60: utilidad | J60: =J59/K58 -> 1.734375 | K60: =K58*variables!$C$6 -> 129024000 | M60: =M59/N58 -> 2.1176471 | N60: =N58*variables!$D$6 -> 51408000
H61: total | K61: =J59+K59+K60 -> 434448000 | N61: =M59+N59+N60 -> 201744000
B63: vuelo | C63: ruta | D63: horas | E63: kg | F63: ruta | G63: horas | H63: kg | I63: ruta | J63: horas | K63: kg
B64: 5 | C64: mde- mia | D64: 3 | E64: 24000 | F64: mde- mia | G64: 3 | H64: 24000 | I64: mde- mia | J64: 3 | K64: 24000 | L64: gso eur | M64: 12 | N64: 102000
B65: 6 | C65: mia mde | D65: 3 | E65: 12000 | F65: mia mde | G65: 3 | H65: 12000 | I65: mia mde | J65: 3 | K65: 12000 | L65: eur gso | M65: 12 | N65: 102000 | P65: =M57+M70 -> 480
P66: =20*2*30 -> 1200
B67: total | D67: =SUM(D64:D66) -> 6 | E67: =SUM(E64:E66) -> 36000 | F67: =SUM(F64:F66) -> 0 | G67: =SUM(G64:G66) -> 6 | H67: =SUM(H64:H66) -> 36000 | J67: =SUM(J64:J66) -> 6 | K67: =SUM(K64:K66) -> 36000 | M67: =SUM(M64:M66) -> 24 | N67: =SUM(N64:N66) -> 204000
H68: dia | I68: 1 | J68: =D67+G67+J67 -> 18 | K68: =E67+H67+K67 -> 108000 | L68: 1 | M68: =M67*I68 -> 24 | N68: =N67*L68 -> 204000
C69: =16*4 -> 64 | D69: =D54+G54+J54+J67+G67+D67 -> 55 | H69: semana | I69: 7 | J69: =J68*I69 -> 126 | K69: =K68*I69 -> 756000 | L69: 2 | M69: =M68*L69 -> 48 | N69: =N68*L69 -> 408000
H70: mes | I70: 4 | J70: =J69*I70 -> 504 | K70: =K69*I70 -> 3024000 | L70: 4 | M70: =M69*L70 -> 192 | N70: =N69*L70 -> 1632000
H71: ano | I71: 12 | J71: =J70*I71 -> 6048 | K71: =K70*I71 -> 36288000 | L71: 12 | M71: =M70*L71 -> 2304 | N71: =N70*L71 -> 19584000
H72: total costoS | J72: =J71*variables!$C$4 -> 60480000 | M72: =M71*variables!$D$3 -> 41472000
H73: utilidad | I73: =J72/K71 -> 1.6666667 | M73: =M72/N71 -> 2.1176471
H74: total | K74: =J72+K72+K73 -> 60480000 | N74: =M72+N72+N73 -> 41472000
H76: total 321 | J76: =J71+J58 -> 18480 | K76: =K71+K58 -> 100800000 | L76: total b777 | M76: =M58+M71 -> 5760 | N76: =N58+N71 -> 48960000
G78: a321 | H78: b777
F79: fuel cost | G79: =J76*variables!$C$11*variables!$C$12 -> 49896000 | H79: =M76*variables!$D$11*variables!$C$12 -> 31104000 | I79: =SUM(G79:H79) -> 81000000
F80: cargo hand | G80: =K76*variables!$C$9 -> 10080000 | H80: =N76*variables!$C$9 -> 4896000 | I80: =SUM(G80:H80) -> 14976000
F81: sobrevuelo | G81: =J76*variables!$C$13*variables!$C$10 -> 3234000 | H81: =M76*variables!$C$13*variables!$C$10 -> 1008000 | I81: =SUM(G81:H81) -> 4242000
F82: mantenimiento | G82: =J76*variables!$C$14 -> 27720000 | H82: =M76*variables!$D$14 -> 37440000 | I82: =SUM(G82:H82) -> 65160000
D87: avion 1 | G87: avion 2 | J87: avion 3 | M87: avion 4
B88: vuelo | C88: ruta | D88: horas | E88: kg | F88: ruta | G88: horas | H88: kg | I88: ruta | J88: horas | K88: kg | L88: ruta | M88: horas | N88: kg
B89: 1 | C89: mde-kin | D89: 2.5 | E89: 24000 | F89: mia kin | G89: 2.5 | H89: 24000 | I89: mia kin | J89: 2.5 | K89: 24000 | L89: gso eur | M89: 12 | N89: 102000
B90: 2 | C90: kin-mde | D90: 2.5 | F90: kin-mia | G90: 2.5 | I90: kin-mia | J90: 2.5 | K90: 24000 | L90: eur gso | M90: 12 | N90: 102000
B91: 3 | C91: mde- mia | D91: 3 | E91: 24000 | F91: mia kin | G91: 2.5 | H91: 24000 | I91: mia kin | J91: 2.5 | K91: 24000 | L91: eur gso | M91: 12 | N91: 102000
B92: 4 | C92: mia mde | D92: 3 | E92: 12000 | F92: kin-mia | G92: 2.5 | I92: kin-mia | J92: 2.5 | K92: 24000 | L92: eur gso | M92: 12 | N92: 102000
C93: mde- mia | D93: 3 | E93: 24000 | F93: mia kin | G93: 2.5 | I93: mde- mia | J93: 3 | K93: 24000 | L93: eur gso | M93: 12 | N93: 102000
C94: mia mde | D94: 3 | E94: 12000 | F94: kin-mia | G94: 2.5 | I94: mia mde | J94: 3 | K94: 12000
B95: total | D95: =SUM(D89:D94) -> 17 | E95: =SUM(E89:E94) -> 96000 | G95: =SUM(G89:G94) -> 15 | H95: =SUM(H89:H94) -> 48000 | J95: =SUM(J89:J94) -> 16 | K95: =SUM(K89:K94) -> 132000 | M95: =SUM(M89:M94) -> 60 | N95: =SUM(N89:N94) -> 510000
H96: dia | I96: 1 | J96: =D95+G95+J95 -> 48 | K96: =E95+H95+K95 -> 276000 | L96: 1 | M96: =M95*I96 -> 60 | N96: =N95*L96 -> 510000
H97: semana | I97: 7 | J97: =J96*I97 -> 336 | K97: =K96*I97 -> 1932000 | L97: 2 | M97: =M96*L97 -> 120 | N97: =N96*L97 -> 1020000
H98: mes | I98: 4 | J98: =J97*I98 -> 1344 | K98: =K97*I98 -> 7728000 | L98: 4 | M98: =M97*L98 -> 480 | N98: =N97*L98 -> 4080000
H99: ano | I99: 12 | J99: =J98*I99 -> 16128 | K99: =K98*I99 -> 92736000 | L99: 12 | M99: =M98*L99 -> 5760 | N99: =N98*L99 -> 48960000
H100: total costoS | J100: =J99*variables!$C$3 -> 145152000 | K100: =K99*variables!$C$5 -> 278208000 | M100: =M99*variables!$D$3 -> 103680000 | N100: =N99*variables!$C$5 -> 146880000
H101: utilidad | J101: =J100/K99 -> 1.5652174 | K101: =K99*variables!$C$6 -> 185472000 | M101: =M100/N99 -> 2.1176471 | N101: =N99*variables!$D$6 -> 85680000
H102: total | K102: =J100+K100+K101 -> 608832000 | N102: =M100+N100+N101 -> 336240000
B104: vuelo | C104: ruta | D104: horas | E104: kg | F104: ruta | G104: horas | H104: kg | I104: ruta | J104: horas | K104: kg
B105: 5 | C105: mde- mia | D105: 3 | E105: 24000 | F105: mde- mia | G105: 3 | H105: 24000 | I105: mde- mia | J105: 3 | K105: 24000 | L105: gso eur | M105: 12 | N105: 102000
B106: 6 | C106: mia mde | D106: 3 | E106: 12000 | F106: mia mde | G106: 3 | H106: 12000 | I106: mia mde | J106: 3 | K106: 12000 | L106: eur gso | M106: 12 | N106: 102000
C107: mde- mia | D107: 3 | E107: 24000 | F107: mde- mia | G107: 3 | H107: 24000 | L107: gso eur | M107: 12 | N107: 102000
C108: mia mde | D108: 3 | E108: 12000 | F108: mia mde | G108: 3 | H108: 12000 | L108: eur gso | M108: 12 | N108: 102000
B110: total | D110: =SUM(D105:D109) -> 12 | E110: =SUM(E105:E109) -> 72000 | F110: =SUM(F105:F109) -> 0 | G110: =SUM(G105:G109) -> 12 | H110: =SUM(H105:H109) -> 72000 | J110: =SUM(J105:J109) -> 6 | K110: =SUM(K105:K109) -> 36000 | M110: =SUM(M105:M109) -> 48 | N110: =SUM(N105:N109) -> 408000
H111: dia | I111: 1 | J111: =D110+G110+J110 -> 30 | K111: =E110+H110+K110 -> 180000 | L111: 1 | M111: =M110*I111 -> 48 | N111: =N110*L111 -> 408000
C112: =16*6 -> 96 | D112: =D95+G95+J95+J110+G110+D110 -> 78 | H112: semana | I112: 7 | J112: =J111*I112 -> 210 | K112: =K111*I112 -> 1260000 | L112: 2 | M112: =M111*L112 -> 96 | N112: =N111*L112 -> 816000
H113: mes | I113: 4 | J113: =J112*I113 -> 840 | K113: =K112*I113 -> 5040000 | L113: 4 | M113: =M112*L113 -> 384 | N113: =N112*L113 -> 3264000
H114: ano | I114: 12 | J114: =J113*I114 -> 10080 | K114: =K113*I114 -> 60480000 | L114: 12 | M114: =M113*L114 -> 4608 | N114: =N113*L114 -> 39168000
H115: total costoS | J115: =J114*variables!$C$4 -> 100800000 | M115: =M114*variables!$D$3 -> 82944000
H116: utilidad | I116: =J115/K114 -> 1.6666667 | M116: =M115/N114 -> 2.1176471
H117: total | K117: =J115+K115+K116 -> 100800000 | N117: =M115+N115+N116 -> 82944000
H119: total 321 | J119: =J114+J99 -> 26208 | K119: =K114+K99 -> 153216000 | L119: total b777 | M119: =M99+M114 -> 10368 | N119: =N99+N114 -> 88128000
G121: a321 | H121: b777
F122: fuel cost | G122: =J119*variables!$C$11*variables!$C$12 -> 70761600 | H122: =M119*variables!$D$11*variables!$C$12 -> 55987200 | I122: =SUM(G122:H122) -> 126748800
F123: cargo hand | G123: =K119*variables!$C$9 -> 15321600 | H123: =N119*variables!$C$9 -> 8812800 | I123: =SUM(G123:H123) -> 24134400
F124: sobrevuelo | G124: =J119*variables!$C$13*variables!$C$10 -> 4586400 | H124: =M119*variables!$C$13*variables!$C$10 -> 1814400 | I124: =SUM(G124:H124) -> 6400800
...

Sheet variables
C2: A321 | D2: B777
B3: costo hora vuelo charter indirecto | C3: 9000 | D3: 18000
B4: costo hora vuelo charter indirecto gsa | C4: 10000 | D4: 20000
B5: costo kg avg productos | C5: 3
B6: utilidad avg producto | C6: 2 | D6: 1.75
B7: costo x kg venta | C7: =SUM(C5:C6) -> 5
B8: Tax provision | C8: 0.25
B9: cargo hand | C9: 0.1
B10: sobrevuelo | C10: 0.35
B11: fuel burn | C11: 900 | D11: 1800
B12: fuel cost | C12: 3
B13: millas x hora | C13: 500
B14: mant x hora | C14: 1500 | D14: 6500
A16: b777 | B16: costo hora vuelo charter indirecto

Sheet ANALYSIS
M1: FRESH | AB1: GSA | AQ1: FRESH | BG1: FRESH
E2: Fuel b. | K2: mtt x | M2: IND CHR. F24 | N2: l1 | P2: l2 | R2: l3 | T2: l4 | V2: l5 | X2: l6 | Z2: LDG | AB2: IND CHR. GSA | AC2: l1 | AE2: l2 | AG2: l3 | AI2: l4 | AK2: l5 | AM2: l6 | AQ2: total dia | AS2: TOTAL | BD2: Cargo buy | BE2: profit | BG2: total dia | BI2: TOTAL
C3: MTOW | D3: M/HORA | E3: GLS | F3: $ | G3: HAND. | H3: OVER/F | I3: LDG FEES | J3: T/A FEES | K3: HORA | N3: F/H | O3: Cargo | P3: F/H | Q3: Cargo | R3: F/H | S3: Cargo | T3: F/H | U3: Cargo | V3: F/H | W3: Cargo | X3: F/H | Y3: Cargo | AC3: F/H | AD3: Cargo | AE3: F/H | AF3: Cargo | AG3: F/H | AH3: Cargo | AI3: F/H | AJ3: Cargo | AK3: F/H | AL3: Cargo | AM3: F/H | AN3: Cargo | AO3: LDG | AQ3: F/H | AR3: Cargo | AS3: x/W | AT3: F/H (Year) | AU3: air log $ | AV3: Maint. | AW3: T/A | AX3: FUEL GLS | AY3: FUEL $ | AZ3: O/FLIGHT | BA3: LDG FEES | BB3: Cargo (Kg) | BC3: Handling | BD3: 3 | BE3: 2 | BG3: F/H | BH3: Cargo | BI3: x/W | BJ3: F/H(Year) | BK3: air log $ | BL3: Maint. | BM3: T/A | BN3: FUEL GLS | BO3: FUEL $ | BP3: O/FLIGHT | BQ3: LDG FEES | BR3: Cargo (Kg) | BS3: Handling
A4: 1 | B4: A321 | C4: 77800 | D4: 500 | E4: 900 | F4: 3 | G4: 0.1 | H4: 0.35 | I4: =C4*0.02 -> 1556 | J4: 150 | K4: 1500 | M4: 9000 | N4: 2.5 | O4: 24500 | P4: 2.5 | R4: 3 | S4: 24500 | T4: 3 | U4: 12000 | Z4: 4 | AB4: 10000 | AQ4: =N4+P4+R4+T4+V4+X4 -> 11 | AR4: =O4+Q4+S4+U4+W4+Y4 -> 61000 | AS4: 6 | AT4: =AQ4*AS4*4*12 -> 3168 | AU4: =AT4*M4 -> 28512000 | AV4: =AT4*K4 -> 4752000 | AW4: =Z4*J4*AS4*4*12 -> 172800 | AX4: =AT4*E4 -> 2851200 | AY4: =AX4*F4 -> 8553600 | AZ4: =AT4*D4*H4 -> 554400 | BA4: =Z4*I4*AS4*4*12 -> 1792512 | BB4: =AR4*AS4*4*12 -> 17568000 | BC4: =BB4*G4 -> 1756800 | BD4: =BB4*$BD$3 -> 52704000 | BE4: =BB4*$BE$3 -> 35136000 | BG4: =AC4+AE4+AG4+AI4+AK4+AM4 -> 0 | BH4: =AD4+AF4+AH4+AJ4+AL4+AN4 -> 0 | BJ4: =BG4*BI4*4*12 -> 0 | BK4: =BJ4*AB4 -> 0 | BL4: =BJ4*K4 -> 0 | BM4: =BI4*AO4*4*12*J4 -> 0 | BN4: =BJ4*E4 -> 0 | BO4: =BN4*F4 -> 0 | BP4: =BJ4*D4*H4 -> 0 | BQ4: =BI4*AO4*I4*4*12 -> 0 | BR4: =BH4*BI4*4*12 -> 0 | BS4: =BR4*G4 -> 0
A5: 1 | B5: A321 | C5: 77800 | D5: 500 | E5: 900 | F5: 3 | G5: 0.1 | H5: 0.35 | I5: =C5*0.02 -> 1556 | J5: 150 | K5: 1500 | M5: 9000 | N5: 2.5 | O5: 24500 | P5: 2.5 | Z5: 2 | AB5: 10000 | AC5: 3 | AD5: 24500 | AE5: 3 | AF5: 12000 | AO5: 2 | AQ5: =N5+P5+R5+T5+V5+X5 -> 5 | AR5: =O5+Q5+S5+U5+W5+Y5 -> 24500 | AS5: 6 | AT5: =AQ5*AS5*4*12 -> 1440 | AU5: =AT5*M5 -> 12960000 | AV5: =AT5*K5 -> 2160000 | AW5: =Z5*J5*AS5*4*12 -> 86400 | AX5: =AT5*E5 -> 1296000 | AY5: =AX5*F5 -> 3888000 | AZ5: =AT5*D5*H5 -> 252000 | BA5: =Z5*I5*AS5*4*12 -> 896256 | BB5: =AR5*AS5*4*12 -> 7056000 | BC5: =BB5*G5 -> 705600 | BD5: =BB5*$BD$3 -> 21168000 | BE5: =BB5*$BE$3 -> 14112000 | BG5: =AC5+AE5+AG5+AI5+AK5+AM5 -> 6 | BH5: =AD5+AF5+AH5+AJ5+AL5+AN5 -> 36500 | BI5: 7 | BJ5: =BG5*BI5*4*12 -> 2016 | BK5: =BJ5*AB5 -> 20160000 | BL5: =BJ5*K5 -> 3024000 | BM5: =BI5*AO5*4*12*J5 -> 100800 | BN5: =BJ5*E5 -> 1814400 | BO5: =BN5*F5 -> 5443200 | BP5: =BJ5*D5*H5 -> 352800 | BQ5: =BI5*AO5*I5*4*12 -> 1045632 | BR5: =BH5*BI5*4*12 -> 12264000 | BS5: =BR5*G5 -> 1226400
A6: 2 | B6: A321 | C6: 77800 | D6: 500 | E6: 900 | F6: 3 | G6: 0.1 | H6: 0.35 | I6: =C6*0.02 -> 1556 | J6: 150 | K6: 1500 | M6: 9000 | AB6: 10000 | AQ6: =N6+P6+R6+T6+V6+X6 -> 0 | AR6: =O6+Q6+S6+U6+W6+Y6 -> 0 | AT6: =AQ6*AS6*4*12 -> 0 | AU6: =AT6*M6 -> 0 | AV6: =AT6*K6 -> 0 | AW6: =Z6*J6*AS6*4*12 -> 0 | AX6: =AT6*E6 -> 0 | AY6: =AX6*F6 -> 0 | AZ6: =AT6*D6*H6 -> 0 | BA6: =Z6*I6*AS6*4*12 -> 0 | BB6: =AR6*AS6*4*12 -> 0 | BC6: =BB6*G6 -> 0 | BD6: =BB6*$BD$3 -> 0 | BE6: =BB6*$BE$3 -> 0 | BG6: =AC6+AE6+AG6+AI6+AK6+AM6 -> 0 | BH6: =AE6+AG6+AI6+AK6+AM6+AO6 -> 0 | BJ6: =BG6*BI6*4*12 -> 0 | BK6: =BJ6*AB6 -> 0 | BL6: =BJ6*K6 -> 0 | BM6: =BI6*AO6*4*12*J6 -> 0 | BN6: =BJ6*E6 -> 0 | BO6: =BN6*F6 -> 0 | BP6: =BJ6*D6*H6 -> 0 | BQ6: =BI6*AO6*I6*4*12 -> 0 | BR6: =BH6*BI6*4*12 -> 0 | BS6: =BR6*G6 -> 0
A7: 3 | B7: A321 | C7: 77800 | D7: 500 | E7: 900 | F7: 3 | G7: 0.1 | H7: 0.35 | I7: =C7*0.02 -> 1556 | J7: 150 | K7: 1500 | M7: 9000 | AB7: 10000 | AQ7: =N7+P7+R7+T7+V7+X7 -> 0 | AR7: =O7+Q7+S7+U7+W7+Y7 -> 0 | AT7: =AQ7*AS7*4*12 -> 0 | AU7: =AT7*M7 -> 0 | AV7: =AT7*K7 -> 0 | AW7: =Z7*J7*AS7*4*12 -> 0 | AX7: =AT7*E7 -> 0 | AY7: =AX7*F7 -> 0 | AZ7: =AT7*D7*H7 -> 0 | BA7: =Z7*I7*AS7*4*12 -> 0 | BB7: =AR7*AS7*4*12 -> 0 | BC7: =BB7*G7 -> 0 | BD7: =BB7*$BD$3 -> 0 | BE7: =BB7*$BE$3 -> 0 | BG7: =AC7+AE7+AG7+AI7+AK7+AM7 -> 0 | BH7: =AE7+AG7+AI7+AK7+AM7+AO7 -> 0 | BJ7: =BG7*BI7*4*12 -> 0 | BK7: =BJ7*AB7 -> 0 | BL7: =BJ7*K7 -> 0 | BM7: =BI7*AO7*4*12*J7 -> 0 | BN7: =BJ7*E7 -> 0 | BO7: =BN7*F7 -> 0 | BP7: =BJ7*D7*H7 -> 0 | BQ7: =BI7*AO7*I7*4*12 -> 0 | BR7: =BH7*BI7*4*12 -> 0 | BS7: =BR7*G7 -> 0
A8: 4 | B8: A321 | C8: 77800 | D8: 500 | E8: 900 | F8: 3 | G8: 0.1 | H8: 0.35 | I8: =C8*0.02 -> 1556 | J8: 150 | K8: 1500 | M8: 9000 | AB8: 10000 | AQ8: =N8+P8+R8+T8+V8+X8 -> 0 | AR8: =O8+Q8+S8+U8+W8+Y8 -> 0 | AT8: =AQ8*AS8*4*12 -> 0 | AU8: =AT8*M8 -> 0 | AV8: =AT8*K8 -> 0 | AW8: =Z8*J8*AS8*4*12 -> 0 | AX8: =AT8*E8 -> 0 | AY8: =AX8*F8 -> 0 | AZ8: =AT8*D8*H8 -> 0 | BA8: =Z8*I8*AS8*4*12 -> 0 | BB8: =AR8*AS8*4*12 -> 0 | BC8: =BB8*G8 -> 0 | BD8: =BB8*$BD$3 -> 0 | BE8: =BB8*$BE$3 -> 0 | BG8: =AC8+AE8+AG8+AI8+AK8+AM8 -> 0 | BH8: =AE8+AG8+AI8+AK8+AM8+AO8 -> 0 | BJ8: =BG8*BI8*4*12 -> 0 | BK8: =BJ8*AB8 -> 0 | BL8: =BJ8*K8 -> 0 | BM8: =BI8*AO8*4*12*J8 -> 0 | BN8: =BJ8*E8 -> 0 | BO8: =BN8*F8 -> 0 | BP8: =BJ8*D8*H8 -> 0 | BQ8: =BI8*AO8*I8*4*12 -> 0 | BR8: =BH8*BI8*4*12 -> 0 | BS8: =BR8*G8 -> 0
A9: 3 | B9: B777 | C9: 260800 | D9: 500 | E9: 1800 | F9: 3 | G9: 0.1 | H9: 0.35 | I9: =C9*0.02 -> 5216 | J9: 350 | K9: 6500 | M9: 18000 | AB9: 20000 | AQ9: =N9+P9+R9+T9+V9+X9 -> 0 | AR9: =O9+Q9+S9+U9+W9+Y9 -> 0 | AT9: =AQ9*AS9*4*12 -> 0 | AU9: =AT9*M9 -> 0 | AV9: =AT9*K9 -> 0 | AW9: =Z9*J9*AS9*4*12 -> 0 | AX9: =AT9*E9 -> 0 | AY9: =AX9*F9 -> 0 | AZ9: =AT9*D9*H9 -> 0 | BA9: =Z9*I9*AS9*4*12 -> 0 | BB9: =AR9*AS9*4*12 -> 0 | BC9: =BB9*G9 -> 0 | BD9: =BB9*$BD$3 -> 0 | BE9: =BB9*$BE$3 -> 0 | BG9: =AC9+AE9+AG9+AI9+AK9+AM9 -> 0 | BH9: =AE9+AG9+AI9+AK9+AM9+AO9 -> 0 | BJ9: =BG9*BI9*4*12 -> 0 | BK9: =BJ9*AB9 -> 0 | BL9: =BJ9*K9 -> 0 | BM9: =BI9*AO9*4*12*J9 -> 0 | BN9: =BJ9*E9 -> 0 | BO9: =BN9*F9 -> 0 | BP9: =BJ9*D9*H9 -> 0 | BQ9: =BI9*AO9*I9*4*12 -> 0 | BR9: =BH9*BI9*4*12 -> 0 | BS9: =BR9*G9 -> 0
A10: 4 | B10: B777 | C10: 260800 | D10: 500 | E10: 1800 | F10: 3 | G10: 0.1 | H10: 0.35 | I10: =C10*0.02 -> 5216 | J10: 350 | K10: 6500 | M10: 18000 | AB10: 20000 | AQ10: =N10+P10+R10+T10+V10+X10 -> 0 | AR10: =O10+Q10+S10+U10+W10+Y10 -> 0 | AT10: =AQ10*AS10*4*12 -> 0 | AU10: =AT10*M10 -> 0 | AV10: =AT10*K10 -> 0 | AW10: =Z10*J10*AS10*4*12 -> 0 | AX10: =AT10*E10 -> 0 | AY10: =AX10*F10 -> 0 | AZ10: =AT10*D10*H10 -> 0 | BA10: =Z10*I10*AS10*4*12 -> 0 | BB10: =AR10*AS10*4*12 -> 0 | BC10: =BB10*G10 -> 0 | BD10: =BB10*$BD$3 -> 0 | BE10: =BB10*$BE$3 -> 0 | BG10: =AC10+AE10+AG10+AI10+AK10+AM10 -> 0 | BH10: =AE10+AG10+AI10+AK10+AM10+AO10 -> 0 | BJ10: =BG10*BI10*4*12 -> 0 | BK10: =BJ10*AB10 -> 0 | BL10: =BJ10*K10 -> 0 | BM10: =BI10*AO10*4*12*J10 -> 0 | BN10: =BJ10*E10 -> 0 | BO10: =BN10*F10 -> 0 | BP10: =BJ10*D10*H10 -> 0 | BQ10: =BI10*AO10*I10*4*12 -> 0 | BR10: =BH10*BI10*4*12 -> 0 | BS10: =BR10*G10 -> 0
AQ11: =SUM(AQ4:AQ10) -> 16 | AT11: =SUM(AT4:AT10) -> 4608 | AU11: =SUM(AU4:AU10) -> 41472000 | AV11: =SUM(AV4:AV10) -> 6912000 | AW11: =SUM(AW4:AW10) -> 259200 | AX11: =SUM(AX4:AX10) -> 4147200 | AY11: =SUM(AY4:AY10) -> 12441600 | AZ11: =SUM(AZ4:AZ10) -> 806400 | BA11: =SUM(BA4:BA10) -> 2688768 | ... BE11: =SUM(BE4:BE10) -> 49248000 | BG11: =SUM(BG4:BG10) -> 6 | BJ11: =SUM(BJ4:BJ10) -> 2016 | BK11: =SUM(BK4:BK10) -> 20160000 | BL11: =SUM(BL4:BL10) -> 3024000 | BM11: =SUM(BM4:BM10) -> 100800 | BN11: =SUM(BN4:BN10) -> 1814400 | BO11: =SUM(BO4:BO10) -> 5443200 | BP11: =SUM(BP4:BP10) -> 352800 | BQ11: =SUM(BQ4:BQ10) -> 1045632 | ... BS11: =SUM(BS4:BS10) -> 1226400
BE12: =BD11+BE11+AU11 -> 164592000 | BJ12: =BJ11+AT11 -> 6624 | BK12: total maint | BL12: =BL11+AV11 -> 9936000 | BN12: total fuel | BO12: =BO11+AY11 -> 17884800 | BP12: TOT. AERO. | BQ12: =BQ11+BP11+BM11+BS11+BC11+BA11+AZ11+AW11 -> 8942400
M15: FRESH | AB15: GSA | AQ15: FRESH | BG15: FRESH
E16: Fuel b. | K16: mtt x | M16: IND CHR. F24 | N16: l1 | P16: l2 | R16: l3 | T16: l4 | V16: l5 | X16: l6 | Z16: LDG | AB16: IND CHR. GSA | AC16: l1 | AE16: l2 | AG16: l3 | AI16: l4 | AK16: l5 | AM16: l6 | AQ16: total dia | AS16: TOTAL | BD16: Cargo buy | BE16: profit | BG16: total dia | BI16: TOTAL
C17: MTOW | D17: M/HORA | E17: GLS | F17: $ | G17: HAND. | H17: OVER/F | I17: LDG FEES | J17: T/A FEES | K17: HORA | N17: F/H | O17: Cargo | P17: F/H | Q17: Cargo | R17: F/H | S17: Cargo | T17: F/H | U17: Cargo | V17: F/H | W17: Cargo | X17: F/H | Y17: Cargo | AC17: F/H | AD17: Cargo | AE17: F/H | AF17: Cargo | AG17: F/H | AH17: Cargo | AI17: F/H | AJ17: Cargo | AK17: F/H | AL17: Cargo | AM17: F/H | AN17: Cargo | AO17: LDG | AQ17: F/H | AR17: Cargo | AS17: x/W | AT17: F/H | AU17: air log $ | AV17: Maint. | AW17: T/A | AX17: FUEL GLS | AY17: FUEL $ | AZ17: O/FLIGHT | BA17: LDG FEES | BB17: Cargo (Kg) | BC17: Handling | BD17: 3 | BE17: 2 | BG17: F/H | BH17: Cargo | BI17: x/W | BJ17: F/H | BK17: air log $ | BL17: Maint. | BM17: T/A | BN17: FUEL GLS | BO17: FUEL $ | BP17: O/FLIGHT | BQ17: LDG FEES | BR17: Cargo (Kg) | BS17: Handling
A18: 1 | B18: A321 | C18: 77800 | D18: 500 | E18: 900 | F18: 3 | G18: 0.1 | H18: 0.35 | I18: =C18*0.02 -> 1556 | J18: 150 | K18: 1500 | M18: 9000 | N18: 2.5 | O18: 24500 | P18: 2.5 | R18: 3 | S18: 24500 | T18: 3 | U18: 12000 | Z18: 4 | AB18: 10000 | AQ18: =N18+P18+R18+T18+V18+X18 -> 11 | AR18: =O18+Q18+S18+U18+W18+Y18 -> 61000 | AS18: 7 | AT18: =AQ18*AS18*4*12 -> 3696 | AU18: =AT18*M18 -> 33264000 | AV18: =AT18*K18 -> 5544000 | AW18: =Z18*J18*AS18*4*12 -> 201600 | AX18: =AT18*E18 -> 3326400 | AY18: =AX18*F18 -> 9979200 | AZ18: =AT18*D18*H18 -> 646800 | BA18: =Z18*I18*AS18*4*12 -> 2091264 | BB18: =AR18*AS18*4*12 -> 20496000 | BC18: =BB18*G18 -> 2049600 | BD18: =BB18*$BD$17 -> 61488000 | BE18: =BB18*$BE$17 -> 40992000 | BG18: =AC18+AE18+AG18+AI18+AK18+AM18 -> 0 | BH18: =AD18+AF18+AH18+AJ18+AL18+AN18 -> 0 | BI18: 7 | BJ18: =BG18*BI18*4*12 -> 0 | BK18: =BJ18*AB18 -> 0 | BL18: =BJ18*K18 -> 0 | BM18: =BI18*AO18*4*12*J18 -> 0 | BN18: =BJ18*E18 -> 0 | BO18: =BN18*F18 -> 0 | BP18: =BJ18*D18*H18 -> 0 | BQ18: =BI18*AO18*I18*4*12 -> 0 | BR18: =BH18*BI18*4*12 -> 0 | BS18: =BR18*G18 -> 0
A19: 1 | B19: A321 | C19: 77800 | D19: 500 | E19: 900 | F19: 3 | G19: 0.1 | H19: 0.35 | I19: =C19*0.02 -> 1556 | J19: 150 | K19: 1500 | M19: 9000 | N19: 2.5 | O19: 24500 | P19: 2.5 | R19: 3 | S19: 24500 | T19: 3 | U19: 12000 | Z19: 4 | AB19: 10000 | AC19: 3 | AD19: 24500 | AE19: 3 | AF19: 12000 | AO19: 2 | AQ19: =N19+P19+R19+T19+V19+X19 -> 11 | AR19: =O19+Q19+S19+U19+W19+Y19 -> 61000 | AS19: 7 | AT19: =AQ19*AS19*4*12 -> 3696 | AU19: =AT19*M19 -> 33264000 | AV19: =AT19*K19 -> 5544000 | AW19: =Z19*J19*AS19*4*12 -> 201600 | AX19: =AT19*E19 -> 3326400 | AY19: =AX19*F19 -> 9979200 | AZ19: =AT19*D19*H19 -> 646800 | BA19: =Z19*I19*AS19*4*12 -> 2091264 | BB19: =AR19*AS19*4*12 -> 20496000 | BC19: =BB19*G19 -> 2049600 | BD19: =BB19*$BD$17 -> 61488000 | BE19: =BB19*$BE$17 -> 40992000 | BG19: =AC19+AE19+AG19+AI19+AK19+AM19 -> 6 | BH19: =AD19+AF19+AH19+AJ19+AL19+AN19 -> 36500 | BI19: 7 | BJ19: =BG19*BI19*4*12 -> 2016 | BK19: =BJ19*AB19 -> 20160000 | BL19: =BJ19*K19 -> 3024000 | BM19: =BI19*AO19*4*12*J19 -> 100800 | BN19: =BJ19*E19 -> 1814400 | BO19: =BN19*F19 -> 5443200 | BP19: =BJ19*D19*H19 -> 352800 | BQ19: =BI19*AO19*I19*4*12 -> 1045632 | BR19: =BH19*BI19*4*12 -> 12264000 | BS19: =BR19*G19 -> 1226400
A20: 2 | B20: A321 | C20: 77800 | D20: 500 | E20: 900 | F20: 3 | G20: 0.1 | H20: 0.35 | I20: =C20*0.02 -> 1556 | J20: 150 | K20: 1500 | M20: 9000 | AB20: 10000 | AC20: 3 | AD20: 24500 | AE20: 3 | AF20: 12000 | AO20: 2 | AQ20: =N20+P20+R20+T20+V20+X20 -> 0 | AR20: =O20+Q20+S20+U20+W20+Y20 -> 0 | AT20: =AQ20*AS20*4*12 -> 0 | AU20: =AT20*M20 -> 0 | AV20: =AT20*K20 -> 0 | AW20: =Z20*J20*AS20*4*12 -> 0 | AX20: =AT20*E20 -> 0 | AY20: =AX20*F20 -> 0 | AZ20: =AT20*D20*H20 -> 0 | BA20: =Z20*I20*AS20*4*12 -> 0 | BB20: =AR20*AS20*4*12 -> 0 | BC20: =BB20*G20 -> 0 | BD20: =BB20*$BD$17 -> 0 | BE20: =BB20*$BE$17 -> 0 | BG20: =AC20+AE20+AG20+AI20+AK20+AM20 -> 6 | BH20: =AE20+AG20+AI20+AK20+AM20+AO20 -> 5 | BI20: 7 | BJ20: =BG20*BI20*4*12 -> 2016 | BK20: =BJ20*AB20 -> 20160000 | BL20: =BJ20*K20 -> 3024000 | BM20: =BI20*AO20*4*12*J20 -> 100800 | BN20: =BJ20*E20 -> 1814400 | BO20: =BN20*F20 -> 5443200 | BP20: =BJ20*D20*H20 -> 352800 | BQ20: =BI20*AO20*I20*4*12 -> 1045632 | BR20: =BH20*BI20*4*12 -> 1680 | BS20: =BR20*G20 -> 168
A21: 3 | B21: A321 | C21: 77800 | D21: 500 | E21: 900 | F21: 3 | G21: 0.1 | H21: 0.35 | I21: =C21*0.02 -> 1556 | J21: 150 | K21: 1500 | M21: 9000 | AB21: 10000 | AQ21: =N21+P21+R21+T21+V21+X21 -> 0 | AR21: =O21+Q21+S21+U21+W21+Y21 -> 0 | AT21: =AQ21*AS21*4*12 -> 0 | AU21: =AT21*M21 -> 0 | AV21: =AT21*K21 -> 0 | AW21: =Z21*J21*AS21*4*12 -> 0 | AX21: =AT21*E21 -> 0 | AY21: =AX21*F21 -> 0 | AZ21: =AT21*D21*H21 -> 0 | BA21: =Z21*I21*AS21*4*12 -> 0 | BB21: =AR21*AS21*4*12 -> 0 | BC21: =BB21*G21 -> 0 | BD21: =BB21*$BD$17 -> 0 | BE21: =BB21*$BE$17 -> 0 | BG21: =AC21+AE21+AG21+AI21+AK21+AM21 -> 0 | BH21: =AE21+AG21+AI21+AK21+AM21+AO21 -> 0 | BJ21: =BG21*BI21*4*12 -> 0 | BK21: =BJ21*AB21 -> 0 | BL21: =BJ21*K21 -> 0 | BM21: =BI21*AO21*4*12*J21 -> 0 | BN21: =BJ21*E21 -> 0 | BO21: =BN21*F21 -> 0 | BP21: =BJ21*D21*H21 -> 0 | BQ21: =BI21*AO21*I21*4*12 -> 0 | BR21: =BH21*BI21*4*12 -> 0 | BS21: =BR21*G21 -> 0
A22: 4 | B22: A321 | C22: 77800 | D22: 500 | E22: 900 | F22: 3 | G22: 0.1 | H22: 0.35 | I22: =C22*0.02 -> 1556 | J22: 150 | K22: 1500 | M22: 9000 | AB22: 10000 | AQ22: =N22+P22+R22+T22+V22+X22 -> 0 | AR22: =O22+Q22+S22+U22+W22+Y22 -> 0 | AT22: =AQ22*AS22*4*12 -> 0 | AU22: =AT22*M22 -> 0 | AV22: =AT22*K22 -> 0 | AW22: =Z22*J22*AS22*4*12 -> 0 | AX22: =AT22*E22 -> 0 | AY22: =AX22*F22 -> 0 | AZ22: =AT22*D22*H22 -> 0 | BA22: =Z22*I22*AS22*4*12 -> 0 | BB22: =AR22*AS22*4*12 -> 0 | BC22: =BB22*G22 -> 0 | BD22: =BB22*$BD$17 -> 0 | BE22: =BB22*$BE$17 -> 0 | BG22: =AC22+AE22+AG22+AI22+AK22+AM22 -> 0 | BH22: =AE22+AG22+AI22+AK22+AM22+AO22 -> 0 | BJ22: =BG22*BI22*4*12 -> 0 | BK22: =BJ22*AB22 -> 0 | BL22: =BJ22*K22 -> 0 | BM22: =BI22*AO22*4*12*J22 -> 0 | BN22: =BJ22*E22 -> 0 | BO22: =BN22*F22 -> 0 | BP22: =BJ22*D22*H22 -> 0 | BQ22: =BI22*AO22*I22*4*12 -> 0 | BR22: =BH22*BI22*4*12 -> 0 | BS22: =BR22*G22 -> 0
A23: 3 | B23: B777 | C23: 260800 | D23: 500 | E23: 1800 | F23: 3 | G23: 0.1 | H23: 0.35 | I23: =C23*0.02 -> 5216 | J23: 350 | K23: 6500 | M23: 18000 | AB23: 20000 | AQ23: =N23+P23+R23+T23+V23+X23 -> 0 | AR23: =O23+Q23+S23+U23+W23+Y23 -> 0 | AT23: =AQ23*AS23*4*12 -> 0 | AU23: =AT23*M23 -> 0 | AV23: =AT23*K23 -> 0 | AW23: =Z23*J23*AS23*4*12 -> 0 | AX23: =AT23*E23 -> 0 | AY23: =AX23*F23 -> 0 | AZ23: =AT23*D23*H23 -> 0 | BA23: =Z23*I23*AS23*4*12 -> 0 | BB23: =AR23*AS23*4*12 -> 0 | BC23: =BB23*G23 -> 0 | BD23: =BB23*$BD$17 -> 0 | BE23: =BB23*$BE$17 -> 0 | BG23: =AC23+AE23+AG23+AI23+AK23+AM23 -> 0 | BH23: =AE23+AG23+AI23+AK23+AM23+AO23 -> 0 | BJ23: =BG23*BI23*4*12 -> 0 | BK23: =BJ23*AB23 -> 0 | BL23: =BJ23*K23 -> 0 | BM23: =BI23*AO23*4*12*J23 -> 0 | BN23: =BJ23*E23 -> 0 | BO23: =BN23*F23 -> 0 | BP23: =BJ23*D23*H23 -> 0 | BQ23: =BI23*AO23*I23*4*12 -> 0 | BR23: =BH23*BI23*4*12 -> 0 | BS23: =BR23*G23 -> 0
A24: 4 | B24: B777 | C24: 260800 | D24: 500 | E24: 1800 | F24: 3 | G24: 0.1 | H24: 0.35 | I24: =C24*0.02 -> 5216 | J24: 350 | K24: 6500 | M24: 18000 | AB24: 20000 | AQ24: =N24+P24+R24+T24+V24+X24 -> 0 | AR24: =O24+Q24+S24+U24+W24+Y24 -> 0 | AT24: =AQ24*AS24*4*12 -> 0 | AU24: =AT24*M24 -> 0 | AV24: =AT24*K24 -> 0 | AW24: =Z24*J24*AS24*4*12 -> 0 | AX24: =AT24*E24 -> 0 | AY24: =AX24*F24 -> 0 | AZ24: =AT24*D24*H24 -> 0 | BA24: =Z24*I24*AS24*4*12 -> 0 | BB24: =AR24*AS24*4*12 -> 0 | BC24: =BB24*G24 -> 0 | BD24: =BB24*$BD$17 -> 0 | BE24: =BB24*$BE$17 -> 0 | BG24: =AC24+AE24+AG24+AI24+AK24+AM24 -> 0 | BH24: =AE24+AG24+AI24+AK24+AM24+AO24 -> 0 | BJ24: =BG24*BI24*4*12 -> 0 | BK24: =BJ24*AB24 -> 0 | BL24: =BJ24*K24 -> 0 | BM24: =BI24*AO24*4*12*J24 -> 0 | BN24: =BJ24*E24 -> 0 | BO24: =BN24*F24 -> 0 | BP24: =BJ24*D24*H24 -> 0 | BQ24: =BI24*AO24*I24*4*12 -> 0 | BR24: =BH24*BI24*4*12 -> 0 | BS24: =BR24*G24 -> 0
AQ25: =SUM(AQ18:AQ24) -> 22 | AT25: =SUM(AT18:AT24) -> 7392 | AU25: =SUM(AU18:AU24) -> 66528000 | AV25: =SUM(AV18:AV24) -> 11088000 | AW25: =SUM(AW18:AW24) -> 403200 | AX25: =SUM(AX18:AX24) -> 6652800 | AY25: =SUM(AY18:AY24) -> 19958400 | AZ25: =SUM(AZ18:AZ24) -> 1293600 | BA25: =SUM(BA18:BA24) -> 4182528 | ... BE25: =SUM(BE18:BE24) -> 81984000 | BG25: =SUM(BG18:BG24) -> 12 | BJ25: =SUM(BJ18:BJ24) -> 4032 | BK25: =SUM(BK18:BK24) -> 40320000 | BL25: =SUM(BL18:BL24) -> 6048000 | BM25: =SUM(BM18:BM24) -> 201600 | BN25: =SUM(BN18:BN24) -> 3628800 | BO25: =SUM(BO18:BO24) -> 10886400 | BP25: =SUM(BP18:BP24) -> 705600 | BQ25: =SUM(BQ18:BQ24) -> 2091264 | ... BS25: =SUM(BS18:BS24) -> 1226568
AU26: =AV25+AW25+AY25+AZ25+BA25+BC25 -> 41024928 | BE26: =BD25+BE25+AU25 -> 271488000 | BJ26: =BJ25+AT25 -> 11424 | BK26: total maint | BL26: =BL25+AV25 -> 17136000 | BN26: total fuel | BO26: =BO25+AY25 -> 30844800 | BP26: TOT. AERO. | BQ26: =BQ25+BP25+BM25+BS25+BC25+BA25+AZ25+AW25 -> 14203560
M30: FRESH | AB30: GSA | AQ30: FRESH | BG30: FRESH
E31: Fuel b. | K31: mtt x | M31: IND CHR. F24 | N31: l1 | P31: l2 | R31: l3 | T31: l4 | V31: l5 | X31: l6 | Z31: LDG | AB31: IND CHR. GSA | AC31: l1 | AE31: l2 | AG31: l3 | AI31: l4 | AK31: l5 | AM31: l6 | AQ31: total dia | AS31: TOTAL | BD31: Cargo buy | BE31: profit | BG31: total dia | BI31: TOTAL
C32: MTOW | D32: M/HORA | E32: GLS | F32: $ | G32: HAND. | H32: OVER/F | I32: LDG FEES | J32: T/A FEES | K32: HORA | N32: F/H | O32: Cargo | P32: F/H | Q32: Cargo | R32: F/H | S32: Cargo | T32: F/H | U32: Cargo | V32: F/H | W32: Cargo | X32: F/H | Y32: Cargo | AC32: F/H | AD32: Cargo | AE32: F/H | AF32: Cargo | AG32: F/H | AH32: Cargo | AI32: F/H | AJ32: Cargo | AK32: F/H | AL32: Cargo | AM32: F/H | AN32: Cargo | AO32: LDG | AQ32: F/H | AR32: Cargo | AS32: x/W | AT32: F/H | AU32: air log $ | AV32: Maint. | AW32: T/A | AX32: FUEL GLS | AY32: FUEL $ | AZ32: O/FLIGHT | BA32: LDG FEES | BB32: Cargo (Kg) | BC32: Handling | BD32: 3 | BE32: 2 | BG32: F/H | BH32: Cargo | BI32: x/W | BJ32: F/H | BK32: air log $ | BL32: Maint. | BM32: T/A | BN32: FUEL GLS | BO32: FUEL $ | BP32: O/FLIGHT | BQ32: LDG FEES | BR32: Cargo (Kg) | BS32: Handling
A33: 1 | B33: A321 | C33: 77800 | D33: 500 | E33: 900 | F33: 3 | G33: 0.1 | H33: 0.35 | I33: =C33*0.02 -> 1556 | J33: 150 | K33: 1500 | M33: 9000 | N33: 2.5 | O33: 24500 | P33: 2.5 | R33: 3 | S33: 24500 | T33: 3 | U33: 12000 | Z33: 4 | AB33: 10000 | AC33: 3 | AD33: 24500 | AO33: 1 | AQ33: =N33+P33+R33+T33+V33+X33 -> 11 | AR33: =O33+Q33+S33+U33+W33+Y33 -> 61000 | AS33: 6 | AT33: =AQ33*AS33*4*12 -> 3168 | AU33: =AT33*M33 -> 28512000 | AV33: =AT33*K33 -> 4752000 | AW33: =Z33*J33*AS33*4*12 -> 172800 | AX33: =AT33*E33 -> 2851200 | AY33: =AX33*F33 -> 8553600 | AZ33: =AT33*D33*H33 -> 554400 | BA33: =Z33*I33*AS33*4*12 -> 1792512 | BB33: =AR33*AS33*4*12 -> 17568000 | BC33: =BB33*G33 -> 1756800 | BD33: =BB33*$BD$32 -> 52704000 | BE33: =BB33*$BE$32 -> 35136000 | BG33: =AC33+AE33+AG33+AI33+AK33+AM33 -> 3 | BH33: =AD33+AF33+AH33+AJ33+AL33+AN33 -> 24500 | BI33: 7 | BJ33: =BG33*BI33*4*12 -> 1008 | BK33: =BJ33*AB33 -> 10080000 | BL33: =BJ33*K33 -> 1512000 | BM33: =BI33*AO33*4*12*J33 -> 50400 | BN33: =BJ33*E33 -> 907200 | BO33: =BN33*F33 -> 2721600 | BP33: =BJ33*D33*H33 -> 176400 | BQ33: =BI33*AO33*I33*4*12 -> 522816 | BR33: =BH33*BI33*4*12 -> 8232000 | BS33: =BR33*G33 -> 823200
A34: 1 | B34: A321 | C34: 77800 | D34: 500 | E34: 900 | F34: 3 | G34: 0.1 | H34: 0.35 | I34: =C34*0.02 -> 1556 | J34: 150 | K34: 1500 | M34: 9000 | N34: 2.5 | O34: 24500 | P34: 2.5 | R34: 3 | S34: 24500 | T34: 3 | U34: 12000 | Z34: 4 | AB34: 10000 | AC34: 3 | AD34: 24500 | AO34: 1 | AQ34: =N34+P34+R34+T34+V34+X34 -> 11 | AR34: =O34+Q34+S34+U34+W34+Y34 -> 61000 | AS34: 6 | AT34: =AQ34*AS34*4*12 -> 3168 | AU34: =AT34*M34 -> 28512000 | AV34: =AT34*K34 -> 4752000 | AW34: =Z34*J34*AS34*4*12 -> 172800 | AX34: =AT34*E34 -> 2851200 | AY34: =AX34*F34 -> 8553600 | AZ34: =AT34*D34*H34 -> 554400 | BA34: =Z34*I34*AS34*4*12 -> 1792512 | BB34: =AR34*AS34*4*12 -> 17568000 | BC34: =BB34*G34 -> 1756800 | BD34: =BB34*$BD$32 -> 52704000 | BE34: =BB34*$BE$32 -> 35136000 | BG34: =AC34+AE34+AG34+AI34+AK34+AM34 -> 3 | BH34: =AD34+AF34+AH34+AJ34+AL34+AN34 -> 24500 | BI34: 7 | BJ34: =BG34*BI34*4*12 -> 1008 | BK34: =BJ34*AB34 -> 10080000 | BL34: =BJ34*K34 -> 1512000 | BM34: =BI34*AO34*4*12*J34 -> 50400 | BN34: =BJ34*E34 -> 907200 | BO34: =BN34*F34 -> 2721600 | BP34: =BJ34*D34*H34 -> 176400 | BQ34: =BI34*AO34*I34*4*12 -> 522816 | BR34: =BH34*BI34*4*12 -> 8232000 | BS34: =BR34*G34 -> 823200
A35: 2 | B35: A321 | C35: 77800 | D35: 500 | E35: 900 | F35: 3 | G35: 0.1 | H35: 0.35 | I35: =C35*0.02 -> 1556 | J35: 150 | K35: 1500 | M35: 9000 | N35: 2.5 | O35: 24500 | P35: 2.5 | R35: 3 | S35: 24500 | T35: 3 | U35: 12000 | Z35: 4 | AB35: 10000 | AC35: 3 | AD35: 24500 | AO35: 1 | AQ35: =N35+P35+R35+T35+V35+X35 -> 11 | AR35: =O35+Q35+S35+U35+W35+Y35 -> 61000 | AS35: 5 | AT35: =AQ35*AS35*4*12 -> 2640 | AU35: =AT35*M35 -> 23760000 | AV35: =AT35*K35 -> 3960000 | AW35: =Z35*J35*AS35*4*12 -> 144000 | AX35: =AT35*E35 -> 2376000 | AY35: =AX35*F35 -> 7128000 | AZ35: =AT35*D35*H35 -> 462000 | BA35: =Z35*I35*AS35*4*12 -> 1493760 | BB35: =AR35*AS35*4*12 -> 14640000 | BC35: =BB35*G35 -> 1464000 | BD35: =BB35*$BD$32 -> 43920000 | BE35: =BB35*$BE$32 -> 29280000 | BG35: =AC35+AE35+AG35+AI35+AK35+AM35 -> 3 | BH35: =AE35+AG35+AI35+AK35+AM35+AO35 -> 1 | BI35: 7 | BJ35: =BG35*BI35*4*12 -> 1008 | BK35: =BJ35*AB35 -> 10080000 | BL35: =BJ35*K35 -> 1512000 | BM35: =BI35*AO35*4*12*J35 -> 50400 | BN35: =BJ35*E35 -> 907200 | BO35: =BN35*F35 -> 2721600 | BP35: =BJ35*D35*H35 -> 176400 | BQ35: =BI35*AO35*I35*4*12 -> 522816 | BR35: =BH35*BI35*4*12 -> 336 | BS35: =BR35*G35 -> 33.6
A36: 3 | B36: A321 | C36: 77800 | D36: 500 | E36: 900 | F36: 3 | G36: 0.1 | H36: 0.35 | I36: =C36*0.02 -> 1556 | J36: 150 | K36: 1500 | M36: 9000 | AB36: 10000 | AQ36: =N36+P36+R36+T36+V36+X36 -> 0 | AR36: =O36+Q36+S36+U36+W36+Y36 -> 0 | AT36: =AQ36*AS36*4*12 -> 0 | AU36: =AT36*M36 -> 0 | AV36: =AT36*K36 -> 0 | AW36: =Z36*J36*AS36*4*12 -> 0 | AX36: =AT36*E36 -> 0 | AY36: =AX36*F36 -> 0 | AZ36: =AT36*D36*H36 -> 0 | BA36: =Z36*I36*AS36*4*12 -> 0 | BB36: =AR36*AS36*4*12 -> 0 | BC36: =BB36*G36 -> 0 | BD36: =BB36*$BD$32 -> 0 | BE36: =BB36*$BE$32 -> 0 | BG36: =AC36+AE36+AG36+AI36+AK36+AM36 -> 0 | BH36: =AE36+AG36+AI36+AK36+AM36+AO36 -> 0 | BJ36: =BG36*BI36*4*12 -> 0 | BK36: =BJ36*AB36 -> 0 | BL36: =BJ36*K36 -> 0 | BM36: =BI36*AO36*4*12*J36 -> 0 | BN36: =BJ36*E36 -> 0 | BO36: =BN36*F36 -> 0 | BP36: =BJ36*D36*H36 -> 0 | BQ36: =BI36*AO36*I36*4*12 -> 0 | BR36: =BH36*BI36*4*12 -> 0 | BS36: =BR36*G36 -> 0
A37: 4 | B37: A321 | C37: 77800 | D37: 500 | E37: 900 | F37: 3 | G37: 0.1 | H37: 0.35 | I37: =C37*0.02 -> 1556 | J37: 150 | K37: 1500 | M37: 9000 | AB37: 10000 | AQ37: =N37+P37+R37+T37+V37+X37 -> 0 | AR37: =O37+Q37+S37+U37+W37+Y37 -> 0 | AT37: =AQ37*AS37*4*12 -> 0 | AU37: =AT37*M37 -> 0 | AV37: =AT37*K37 -> 0 | AW37: =Z37*J37*AS37*4*12 -> 0 | AX37: =AT37*E37 -> 0 | AY37: =AX37*F37 -> 0 | AZ37: =AT37*D37*H37 -> 0 | BA37: =Z37*I37*AS37*4*12 -> 0 | BB37: =AR37*AS37*4*12 -> 0 | BC37: =BB37*G37 -> 0 | BD37: =BB37*$BD$32 -> 0 | BE37: =BB37*$BE$32 -> 0 | BG37: =AC37+AE37+AG37+AI37+AK37+AM37 -> 0 | BH37: =AE37+AG37+AI37+AK37+AM37+AO37 -> 0 | BJ37: =BG37*BI37*4*12 -> 0 | BK37: =BJ37*AB37 -> 0 | BL37: =BJ37*K37 -> 0 | BM37: =BI37*AO37*4*12*J37 -> 0 | BN37: =BJ37*E37 -> 0 | BO37: =BN37*F37 -> 0 | BP37: =BJ37*D37*H37 -> 0 | BQ37: =BI37*AO37*I37*4*12 -> 0 | BR37: =BH37*BI37*4*12 -> 0 | BS37: =BR37*G37 -> 0
A38: 3 | B38: B777 | C38: 260800 | D38: 500 | E38: 1800 | F38: 3 | G38: 0.1 | H38: 0.35 | I38: =C38*0.02 -> 5216 | J38: 350 | K38: 5500 | M38: 18000 | N38: 13 | O38: 102000 | Z38: 1 | AB38: 20000 | AQ38: =N38+P38+R38+T38+V38+X38 -> 13 | AR38: =O38+Q38+S38+U38+W38+Y38 -> 102000 | AS38: 5 | AT38: =AQ38*AS38*4*12 -> 3120 | AU38: =AT38*M38 -> 56160000 | AV38: =AT38*K38 -> 17160000 | AW38: =Z38*J38*AS38*4*12 -> 84000 | AX38: =AT38*E38 -> 5616000 | AY38: =AX38*F38 -> 16848000 | AZ38: =AT38*D38*H38 -> 546000 | BA38: =Z38*I38*AS38*4*12 -> 1251840 | BB38: =AR38*AS38*4*12 -> 24480000 | BC38: =BB38*G38 -> 2448000 | BD38: =BB38*$BD$32 -> 73440000 | BE38: =BB38*$BE$32 -> 48960000 | BG38: =AC38+AE38+AG38+AI38+AK38+AM38 -> 0 | BH38: =AE38+AG38+AI38+AK38+AM38+AO38 -> 0 | BJ38: =BG38*BI38*4*12 -> 0 | BK38: =BJ38*AB38 -> 0 | BL38: =BJ38*K38 -> 0 | BM38: =BI38*AO38*4*12*J38 -> 0 | BN38: =BJ38*E38 -> 0 | BO38: =BN38*F38 -> 0 | BP38: =BJ38*D38*H38 -> 0 | BQ38: =BI38*AO38*I38*4*12 -> 0 | BR38: =BH38*BI38*4*12 -> 0 | BS38: =BR38*G38 -> 0
A39: 4 | B39: B777 | C39: 260800 | D39: 500 | E39: 1800 | F39: 3 | G39: 0.1 | H39: 0.35 | I39: =C39*0.02 -> 5216 | J39: 350 | K39: 5500 | M39: 18000 | AB39: 20000 | AQ39: =N39+P39+R39+T39+V39+X39 -> 0 | AR39: =O39+Q39+S39+U39+W39+Y39 -> 0 | AT39: =AQ39*AS39*4*12 -> 0 | AU39: =AT39*M39 -> 0 | AV39: =AT39*K39 -> 0 | AW39: =Z39*J39*AS39*4*12 -> 0 | AX39: =AT39*E39 -> 0 | AY39: =AX39*F39 -> 0 | AZ39: =AT39*D39*H39 -> 0 | BA39: =Z39*I39*AS39*4*12 -> 0 | BB39: =AR39*AS39*4*12 -> 0 | BC39: =BB39*G39 -> 0 | BD39: =BB39*$BD$32 -> 0 | BE39: =BB39*$BE$32 -> 0 | BG39: =AC39+AE39+AG39+AI39+AK39+AM39 -> 0 | BH39: =AE39+AG39+AI39+AK39+AM39+AO39 -> 0 | BJ39: =BG39*BI39*4*12 -> 0 | BK39: =BJ39*AB39 -> 0 | BL39: =BJ39*K39 -> 0 | BM39: =BI39*AO39*4*12*J39 -> 0 | BN39: =BJ39*E39 -> 0 | BO39: =BN39*F39 -> 0 | BP39: =BJ39*D39*H39 -> 0 | BQ39: =BI39*AO39*I39*4*12 -> 0 | BR39: =BH39*BI39*4*12 -> 0 | BS39: =BR39*G39 -> 0
AQ40: =SUM(AQ33:AQ37) -> 33 | AT40: =SUM(AT33:AT39) -> 12096 | AU40: =SUM(AU33:AU37) -> 80784000 | AV40: =SUM(AV33:AV39) -> 30624000 | AW40: =SUM(AW33:AW39) -> 573600 | AX40: =SUM(AX33:AX39) -> 13694400 | AY40: =SUM(AY33:AY39) -> 41083200 | AZ40: =SUM(AZ33:AZ39) -> 2116800 | BA40: =SUM(BA33:BA39) -> 6330624 | BB40: =SUM(BB33:BB37) -> 49776000 | BC40: =SUM(BC33:BC39) -> 7425600 | BD40: =SUM(BD33:BD37) -> 149328000 | BE40: =SUM(BE33:BE37) -> 99552000 | BG40: =SUM(BG33:BG37) -> 9 | BJ40: =SUM(BJ33:BJ39) -> 3024 | BK40: =SUM(BK33:BK39) -> 30240000 | BL40: =SUM(BL33:BL39) -> 4536000 | BM40: =SUM(BM33:BM39) -> 151200 | BN40: =SUM(BN33:BN39) -> 2721600 | BO40: =SUM(BO33:BO39) -> 8164800 | BP40: =SUM(BP33:BP39) -> 529200 | BQ40: =SUM(BQ33:BQ39) -> 1568448 | ... BS40: =SUM(BS33:BS39) -> 1646433.6
AQ41: =SUM(AQ38:AQ39) -> 13 | AU41: =SUM(AU38:AU39) -> 56160000 | BB41: =SUM(BB38:BB39) -> 24480000 | BD41: =SUM(BD38:BD39) -> 73440000 | BE41: =SUM(BE38:BE39) -> 48960000 | BG41: =SUM(BG38:BG39) -> 0 | BJ41: =BJ40+AT40 -> 15120 | BK41: total maint | BL41: =BL40+AV40 -> 35160000 | BN41: total fuel | BO41: =BO40+AY40 -> 49248000 | BP41: TOT. AERO. | BQ41: =BQ40+BP40+BM40+BS40+BC40+BA40+AZ40+AW40 -> 20341906
AU42: =SUM(AU40:AU41) -> 136944000 | BB42: =SUM(BB40:BB41) -> 74256000 | BD42: =SUM(BD40:BD41) -> 222768000 | BE42: =SUM(BE40:BE41) -> 148512000
BD43: =AU40+BD40+BE40 -> 329664000
BD44: =AU41+BD41+BE41 -> 178560000 | BE44: =BD42+BE42+AU42 -> 508224000
M45: FRESH | AB45: GSA | AQ45: FRESH | BG45: FRESH
E46: Fuel b. | K46: mtt x | M46: IND CHR. F24 | N46: l1 | P46: l2 | R46: l3 | T46: l4 | V46: l5 | X46: l6 | Z46: LDG | AB46: IND CHR. GSA | AC46: l1 | AE46: l2 | AG46: l3 | AI46: l4 | AK46: l5 | AM46: l6 | AQ46: total dia | AS46: TOTAL | BD46: Cargo buy | BE46: profit | BG46: total dia | BI46: TOTAL
C47: MTOW | D47: M/HORA | E47: GLS | F47: $ | G47: HAND. | H47: OVER/F | I47: LDG FEES | J47: T/A FEES | K47: HORA | N47: F/H | O47: Cargo | P47: F/H | Q47: Cargo | R47: F/H | S47: Cargo | T47: F/H | U47: Cargo | V47: F/H | W47: Cargo | X47: F/H | Y47: Cargo | AC47: F/H | AD47: Cargo | AE47: F/H | AF47: Cargo | AG47: F/H | AH47: Cargo | AI47: F/H | AJ47: Cargo | AK47: F/H | AL47: Cargo | AM47: F/H | AN47: Cargo | AO47: LDG | AQ47: F/H | AR47: Cargo | AS47: x/W | AT47: F/H | AU47: air log $ | AV47: Maint. | AW47: T/A | AX47: FUEL GLS | AY47: FUEL $ | AZ47: O/FLIGHT | BA47: LDG FEES | BB47: Cargo (Kg) | BC47: Handling | BD47: 3 | BE47: 2 | BG47: F/H | BH47: Cargo | BI47: x/W | BJ47: F/H | BK47: air log $ | BL47: Maint. | BM47: T/A | BN47: FUEL GLS | BO47: FUEL $ | BP47: O/FLIGHT | BQ47: LDG FEES | BR47: Cargo (Kg) | BS47: Handling
A48: 1 | B48: A321 | C48: 77800 | D48: 500 | E48: 900 | F48: 3 | G48: 0.1 | H48: 0.35 | I48: =C48*0.02 -> 1556 | J48: 150 | K48: 1500 | M48: 9000 | N48: 2.5 | O48: 24500 | P48: 2.5 | R48: 3 | S48: 24500 | T48: 3 | U48: 12000 | Z48: 4 | AB48: 10000 | AC48: 3 | AD48: 24500 | AO48: 1 | AQ48: =N48+P48+R48+T48+V48+X48 -> 11 | AR48: =O48+Q48+S48+U48+W48+Y48 -> 61000 | AS48: 7 | AT48: =AQ48*AS48*4*12 -> 3696 | AU48: =AT48*M48 -> 33264000 | AV48: =AT48*K48 -> 5544000 | AW48: =Z48*J48*AS48*4*12 -> 201600 | AX48: =AT48*E48 -> 3326400 | AY48: =AX48*F48 -> 9979200 | AZ48: =AT48*D48*H48 -> 646800 | BA48: =Z48*I48*AS48*4*12 -> 2091264 | BB48: =AR48*AS48*4*12 -> 20496000 | BC48: =BB48*G48 -> 2049600 | BD48: =BB48*$BD$47 -> 61488000 | BE48: =BB48*$BE$47 -> 40992000 | BG48: =AC48+AE48+AG48+AI48+AK48+AM48 -> 3 | BH48: =AD48+AF48+AH48+AJ48+AL48+AN48 -> 24500 | BI48: 7 | BJ48: =BG48*BI48*4*12 -> 1008 | BK48: =BJ48*AB48 -> 10080000 | BL48: =BJ48*K48 -> 1512000 | BM48: =BI48*AO48*4*12*J48 -> 50400 | BN48: =BJ48*E48 -> 907200 | BO48: =BN48*F48 -> 2721600 | BP48: =BJ48*D48*H48 -> 176400 | BQ48: =BI48*AO48*I48*4*12 -> 522816 | BR48: =BH48*BI48*4*12 -> 8232000 | BS48: =BR48*G48 -> 823200
A49: 1 | B49: A321 | C49: 77800 | D49: 500 | E49: 900 | F49: 3 | G49: 0.1 | H49: 0.35 | I49: =C49*0.02 -> 1556 | J49: 150 | K49: 1500 | M49: 9000 | N49: 2.5 | O49: 24500 | P49: 2.5 | R49: 3 | S49: 24500 | T49: 3 | U49: 12000 | Z49: 4 | AB49: 10000 | AC49: 3 | AD49: 24500 | AO49: 1 | AQ49: =N49+P49+R49+T49+V49+X49 -> 11 | AR49: =O49+Q49+S49+U49+W49+Y49 -> 61000 | AS49: 7 | AT49: =AQ49*AS49*4*12 -> 3696 | AU49: =AT49*M49 -> 33264000 | AV49: =AT49*K49 -> 5544000 | AW49: =Z49*J49*AS49*4*12 -> 201600 | AX49: =AT49*E49 -> 3326400 | AY49: =AX49*F49 -> 9979200 | AZ49: =AT49*D49*H49 -> 646800 | BA49: =Z49*I49*AS49*4*12 -> 2091264 | BB49: =AR49*AS49*4*12 -> 20496000 | BC49: =BB49*G49 -> 2049600 | BD49: =BB49*$BD$47 -> 61488000 | BE49: =BB49*$BE$47 -> 40992000 | BG49: =AC49+AE49+AG49+AI49+AK49+AM49 -> 3 | BH49: =AD49+AF49+AH49+AJ49+AL49+AN49 -> 24500 | BI49: 7 | BJ49: =BG49*BI49*4*12 -> 1008 | BK49: =BJ49*AB49 -> 10080000 | BL49: =BJ49*K49 -> 1512000 | BM49: =BI49*AO49*4*12*J49 -> 50400 | BN49: =BJ49*E49 -> 907200 | BO49: =BN49*F49 -> 2721600 | BP49: =BJ49*D49*H49 -> 176400 | BQ49: =BI49*AO49*I49*4*12 -> 522816 | BR49: =BH49*BI49*4*12 -> 8232000 | BS49: =BR49*G49 -> 823200
A50: 2 | B50: A321 | C50: 77800 | D50: 500 | E50: 900 | F50: 3 | G50: 0.1 | H50: 0.35 | I50: =C50*0.02 -> 1556 | J50: 150 | K50: 1500 | M50: 9000 | N50: 2.5 | O50: 24500 | P50: 2.5 | R50: 3 | S50: 24500 | T50: 3 | U50: 12000 | Z50: 4 | AB50: 10000 | AC50: 3 | AD50: 24500 | AO50: 1 | AQ50: =N50+P50+R50+T50+V50+X50 -> 11 | AR50: =O50+Q50+S50+U50+W50+Y50 -> 61000 | AS50: 5 | AT50: =AQ50*AS50*4*12 -> 2640 | AU50: =AT50*M50 -> 23760000 | AV50: =AT50*K50 -> 3960000 | AW50: =Z50*J50*AS50*4*12 -> 144000 | AX50: =AT50*E50 -> 2376000 | AY50: =AX50*F50 -> 7128000 | AZ50: =AT50*D50*H50 -> 462000 | BA50: =Z50*I50*AS50*4*12 -> 1493760 | BB50: =AR50*AS50*4*12 -> 14640000 | BC50: =BB50*G50 -> 1464000 | BD50: =BB50*$BD$47 -> 43920000 | BE50: =BB50*$BE$47 -> 29280000 | BG50: =AC50+AE50+AG50+AI50+AK50+AM50 -> 3 | BH50: =AE50+AG50+AI50+AK50+AM50+AO50 -> 1 | BI50: 7 | BJ50: =BG50*BI50*4*12 -> 1008 | BK50: =BJ50*AB50 -> 10080000 | BL50: =BJ50*K50 -> 1512000 | BM50: =BI50*AO50*4*12*J50 -> 50400 | BN50: =BJ50*E50 -> 907200 | BO50: =BN50*F50 -> 2721600 | BP50: =BJ50*D50*H50 -> 176400 | BQ50: =BI50*AO50*I50*4*12 -> 522816 | BR50: =BH50*BI50*4*12 -> 336 | BS50: =BR50*G50 -> 33.6
A51: 3 | B51: A321 | C51: 77800 | D51: 500 | E51: 900 | F51: 3 | G51: 0.1 | H51: 0.35 | I51: =C51*0.02 -> 1556 | J51: 150 | K51: 1500 | M51: 9000 | N51: 2.5 | O51: 24500 | P51: 2.5 | R51: 3 | S51: 24500 | T51: 3 | U51: 12000 | Z51: 4 | AB51: 10000 | AC51: 3 | AD51: 24500 | AO51: 1 | AQ51: =N51+P51+R51+T51+V51+X51 -> 11 | AR51: =O51+Q51+S51+U51+W51+Y51 -> 61000 | AS51: 5 | AT51: =AQ51*AS51*4*12 -> 2640 | AU51: =AT51*M51 -> 23760000 | AV51: =AT51*K51 -> 3960000 | AW51: =Z51*J51*AS51*4*12 -> 144000 | AX51: =AT51*E51 -> 2376000 | AY51: =AX51*F51 -> 7128000 | AZ51: =AT51*D51*H51 -> 462000 | BA51: =Z51*I51*AS51*4*12 -> 1493760 | BB51: =AR51*AS51*4*12 -> 14640000 | BC51: =BB51*G51 -> 1464000 | BD51: =BB51*$BD$47 -> 43920000 | BE51: =BB51*$BE$47 -> 29280000 | BG51: =AC51+AE51+AG51+AI51+AK51+AM51 -> 3 | BH51: =AE51+AG51+AI51+AK51+AM51+AO51 -> 1 | BI51: 7 | BJ51: =BG51*BI51*4*12 -> 1008 | BK51: =BJ51*AB51 -> 10080000 | BL51: =BJ51*K51 -> 1512000 | BM51: =BI51*AO51*4*12*J51 -> 50400 | BN51: =BJ51*E51 -> 907200 | BO51: =BN51*F51 -> 2721600 | BP51: =BJ51*D51*H51 -> 176400 | BQ51: =BI51*AO51*I51*4*12 -> 522816 | BR51: =BH51*BI51*4*12 -> 336 | BS51: =BR51*G51 -> 33.6
A52: 4 | B52: A321 | C52: 77800 | D52: 500 | E52: 900 | F52: 3 | G52: 0.1 | H52: 0.35 | I52: =C52*0.02 -> 1556 | J52: 150 | K52: 1500 | M52: 9000 | AB52: 10000 | AQ52: =N52+P52+R52+T52+V52+X52 -> 0 | AR52: =O52+Q52+S52+U52+W52+Y52 -> 0 | AT52: =AQ52*AS52*4*12 -> 0 | AU52: =AT52*M52 -> 0 | AV52: =AT52*K52 -> 0 | AW52: =Z52*J52*AS52*4*12 -> 0 | AX52: =AT52*E52 -> 0 | AY52: =AX52*F52 -> 0 | AZ52: =AT52*D52*H52 -> 0 | BA52: =Z52*I52*AS52*4*12 -> 0 | BB52: =AR52*AS52*4*12 -> 0 | BC52: =BB52*G52 -> 0 | BD52: =BB52*$BD$47 -> 0 | BE52: =BB52*$BE$47 -> 0 | BG52: =AC52+AE52+AG52+AI52+AK52+AM52 -> 0 | BH52: =AE52+AG52+AI52+AK52+AM52+AO52 -> 0 | BJ52: =BG52*BI52*4*12 -> 0 | BK52: =BJ52*AB52 -> 0 | BL52: =BJ52*K52 -> 0 | BM52: =BI52*AO52*4*12*J52 -> 0 | BN52: =BJ52*E52 -> 0 | BO52: =BN52*F52 -> 0 | BP52: =BJ52*D52*H52 -> 0 | BQ52: =BI52*AO52*I52*4*12 -> 0 | BR52: =BH52*BI52*4*12 -> 0 | BS52: =BR52*G52 -> 0
A53: 3 | B53: B777 | C53: 260800 | D53: 500 | E53: 1800 | F53: 3 | G53: 0.1 | H53: 0.35 | I53: =C53*0.02 -> 5216 | J53: 350 | K53: 5500 | M53: 18000 | N53: 13 | O53: 102000 | Z53: 1 | AB53: 20000 | AQ53: =N53+P53+R53+T53+V53+X53 -> 13 | AR53: =O53+Q53+S53+U53+W53+Y53 -> 102000 | AS53: 6 | AT53: =AQ53*AS53*4*12 -> 3744 | AU53: =AT53*M53 -> 67392000 | AV53: =AT53*K53 -> 20592000 | AW53: =Z53*J53*AS53*4*12 -> 100800 | AX53: =AT53*E53 -> 6739200 | AY53: =AX53*F53 -> 20217600 | AZ53: =AT53*D53*H53 -> 655200 | BA53: =Z53*I53*AS53*4*12 -> 1502208 | BB53: =AR53*AS53*4*12 -> 29376000 | BC53: =BB53*G53 -> 2937600 | BD53: =BB53*$BD$47 -> 88128000 | BE53: =BB53*$BE$47 -> 58752000 | BG53: =AC53+AE53+AG53+AI53+AK53+AM53 -> 0 | BH53: =AE53+AG53+AI53+AK53+AM53+AO53 -> 0 | BJ53: =BG53*BI53*4*12 -> 0 | BK53: =BJ53*AB53 -> 0 | BL53: =BJ53*K53 -> 0 | BM53: =BI53*AO53*4*12*J53 -> 0 | BN53: =BJ53*E53 -> 0 | BO53: =BN53*F53 -> 0 | BP53: =BJ53*D53*H53 -> 0 | BQ53: =BI53*AO53*I53*4*12 -> 0 | BR53: =BH53*BI53*4*12 -> 0 | BS53: =BR53*G53 -> 0
A54: 4 | B54: B777 | C54: 260800 | D54: 500 | E54: 1800 | F54: 3 | G54: 0.1 | H54: 0.35 | I54: =C54*0.02 -> 5216 | J54: 350 | K54: 5500 | M54: 18000 | N54: 13 | O54: 102000 | Z54: 1 | AB54: 20000 | AC54: 13 | AD54: 102000 | AO54: 1 | AQ54: =N54+P54+R54+T54+V54+X54 -> 13 | AR54: =O54+Q54+S54+U54+W54+Y54 -> 102000 | AS54: 3 | AT54: =AQ54*AS54*4*12 -> 1872 | AU54: =AT54*M54 -> 33696000 | AV54: =AT54*K54 -> 10296000 | AW54: =Z54*J54*AS54*4*12 -> 50400 | AX54: =AT54*E54 -> 3369600 | AY54: =AX54*F54 -> 10108800 | AZ54: =AT54*D54*H54 -> 327600 | BA54: =Z54*I54*AS54*4*12 -> 751104 | BB54: =AR54*AS54*4*12 -> 14688000 | BC54: =BB54*G54 -> 1468800 | BD54: =BB54*$BD$47 -> 44064000 | BE54: =BB54*$BE$47 -> 29376000 | BG54: =AC54+AE54+AG54+AI54+AK54+AM54 -> 13 | BH54: =AE54+AG54+AI54+AK54+AM54+AO54 -> 1 | BI54: 3 | BJ54: =BG54*BI54*4*12 -> 1872 | BK54: =BJ54*AB54 -> 37440000 | BL54: =BJ54*K54 -> 10296000 | BM54: =BI54*AO54*4*12*J54 -> 50400 | BN54: =BJ54*E54 -> 3369600 | BO54: =BN54*F54 -> 10108800 | BP54: =BJ54*D54*H54 -> 327600 | BQ54: =BI54*AO54*I54*4*12 -> 751104 | BR54: =BH54*BI54*4*12 -> 144 | BS54: =BR54*G54 -> 14.4
AQ55: =SUM(AQ48:AQ52) -> 44 | AT55: =SUM(AT48:AT54) -> 18288 | AU55: =SUM(AU48:AU52) -> 114048000 | AV55: =SUM(AV48:AV54) -> 49896000 | AW55: =SUM(AW48:AW54) -> 842400 | AX55: =SUM(AX48:AX54) -> 21513600 | AY55: =SUM(AY48:AY54) -> 64540800 | AZ55: =SUM(AZ48:AZ54) -> 3200400 | BA55: =SUM(BA48:BA54) -> 9423360 | BB55: =SUM(BB48:BB52) -> 70272000 | BC55: =SUM(BC48:BC54) -> 11433600 | BD55: =SUM(BD48:BD52) -> 210816000 | BE55: =SUM(BE48:BE52) -> 140544000 | BG55: =SUM(BG48:BG52) -> 12 | BJ55: =SUM(BJ48:BJ54) -> 5904 | BK55: =SUM(BK48:BK54) -> 77760000 | BL55: =SUM(BL48:BL54) -> 16344000 | BM55: =SUM(BM48:BM54) -> 252000 | BN55: =SUM(BN48:BN54) -> 6998400 | BO55: =SUM(BO48:BO54) -> 20995200 | BP55: =SUM(BP48:BP54) -> 1033200 | BQ55: =SUM(BQ48:BQ54) -> 2842368 | ... BS55: =SUM(BS48:BS54) -> 1646481.6
AQ56: =SUM(AQ53:AQ54) -> 26 | AU56: =SUM(AU53:AU54) -> 101088000 | BB56: =SUM(BB53:BB54) -> 44064000 | BD56: =SUM(BD53:BD54) -> 132192000 | BE56: =SUM(BE53:BE54) -> 88128000 | BG56: =SUM(BG53:BG54) -> 13 | BJ56: =BJ55+AT55 -> 24192 | BK56: total maint | BL56: =BL55+AV55 -> 66240000 | BN56: total fuel | BO56: =BO55+AY55 -> 85536000 | BP56: TOT. AERO. | BQ56: =BQ55+BP55+BM55+BS55+BC55+BA55+AZ55+AW55 -> 30673810
AU57: =SUM(AU55:AU56) -> 215136000 | BB57: =SUM(BB55:BB56) -> 114336000 | BD57: =SUM(BD55:BD56) -> 343008000 | BE57: =SUM(BE55:BE56) -> 228672000
BD58: =AU55+BD55+BE55 -> 465408000
BD59: =AU56+BD56+BE56 -> 321408000 | BE59: =BD57+BE57+AU57 -> 786816000
M62: FRESH | AB62: GSA | AQ62: FRESH | BG62: FRESH
E63: Fuel b. | K63: mtt x | M63: IND CHR. F24 | N63: l1 | P63: l2 | R63: l3 | T63: l4 | V63: l5 | X63: l6 | Z63: LDG | AB63: IND CHR. GSA | AC63: l1 | AE63: l2 | AG63: l3 | AI63: l4 | AK63: l5 | AM63: l6 | AQ63: total dia | AS63: TOTAL | BD63: Cargo buy | BE63: profit | BG63: total dia | BI63: TOTAL
C64: MTOW | D64: M/HORA | E64: GLS | F64: $ | G64: HAND. | H64: OVER/F | I64: LDG FEES | J64: T/A FEES | K64: HORA | N64: F/H | O64: Cargo | P64: F/H | Q64: Cargo | R64: F/H | S64: Cargo | T64: F/H | U64: Cargo | V64: F/H | W64: Cargo | X64: F/H | Y64: Cargo | AC64: F/H | AD64: Cargo | AE64: F/H | AF64: Cargo | AG64: F/H | AH64: Cargo | AI64: F/H | AJ64: Cargo | AK64: F/H | AL64: Cargo | AM64: F/H | AN64: Cargo | AO64: LDG | AQ64: F/H | AR64: Cargo | AS64: x/W | AT64: F/H | AU64: air log $ | AV64: Maint. | AW64: T/A | AX64: FUEL GLS | AY64: FUEL $ | AZ64: O/FLIGHT | BA64: LDG FEES | BB64: Cargo (Kg) | BC64: Handling | BD64: 3 | BE64: 2 | BG64: F/H | BH64: Cargo | BI64: x/W | BJ64: F/H | BK64: air log $ | BL64: Maint. | BM64: T/A | BN64: FUEL GLS | BO64: FUEL $ | BP64: O/FLIGHT | BQ64: LDG FEES | BR64: Cargo (Kg) | BS64: Handling
A65: 1 | B65: A321 | C65: 77800 | D65: 500 | E65: 900 | F65: 3 | G65: 0.1 | H65: 0.35 | I65: =C65*0.02 -> 1556 | J65: 150 | K65: 1500 | M65: 9000 | N65: 2.5 | O65: 24500 | P65: 2.5 | R65: 3 | S65: 24500 | T65: 3 | U65: 12000 | Z65: 4 | AB65: 10000 | AC65: 3 | AD65: 24500 | AO65: 1 | AQ65: =N65+P65+R65+T65+V65+X65 -> 11 | AR65: =O65+Q65+S65+U65+W65+Y65 -> 61000 | AS65: 7 | AT65: =AQ65*AS65*4*12 -> 3696 | AU65: =AT65*M65 -> 33264000 | AV65: =AT65*K65 -> 5544000 | AW65: =Z65*J65*AS65*4*12 -> 201600 | AX65: =AT65*E65 -> 3326400 | AY65: =AX65*F65 -> 9979200 | AZ65: =AT65*D65*H65 -> 646800 | BA65: =Z65*I65*AS65*4*12 -> 2091264 | BB65: =AR65*AS65*4*12 -> 20496000 | BC65: =BB65*G65 -> 2049600 | BD65: =BB65*$BD$47 -> 61488000 | BE65: =BB65*$BE$47 -> 40992000 | BG65: =AC65+AE65+AG65+AI65+AK65+AM65 -> 3 | BH65: =AD65+AF65+AH65+AJ65+AL65+AN65 -> 24500 | BI65: 7 | BJ65: =BG65*BI65*4*12 -> 1008 | BK65: =BJ65*AB65 -> 10080000 | BL65: =BJ65*K65 -> 1512000 | BM65: =BI65*AO65*4*12*J65 -> 50400 | BN65: =BJ65*E65 -> 907200 | BO65: =BN65*F65 -> 2721600 | BP65: =BJ65*D65*H65 -> 176400 | BQ65: =BI65*AO65*I65*4*12 -> 522816 | BR65: =BH65*BI65*4*12 -> 8232000 | BS65: =BR65*G65 -> 823200
A66: 1 | B66: A321 | C66: 77800 | D66: 500 | E66: 900 | F66: 3 | G66: 0.1 | H66: 0.35 | I66: =C66*0.02 -> 1556 | J66: 150 | K66: 1500 | M66: 9000 | N66: 2.5 | O66: 24500 | P66: 2.5 | R66: 3 | S66: 24500 | T66: 3 | U66: 12000 | Z66: 4 | AB66: 10000 | AC66: 3 | AD66: 24500 | AO66: 1 | AQ66: =N66+P66+R66+T66+V66+X66 -> 11 | AR66: =O66+Q66+S66+U66+W66+Y66 -> 61000 | AS66: 7 | AT66: =AQ66*AS66*4*12 -> 3696 | AU66: =AT66*M66 -> 33264000 | AV66: =AT66*K66 -> 5544000 | AW66: =Z66*J66*AS66*4*12 -> 201600 | AX66: =AT66*E66 -> 3326400 | AY66: =AX66*F66 -> 9979200 | AZ66: =AT66*D66*H66 -> 646800 | BA66: =Z66*I66*AS66*4*12 -> 2091264 | BB66: =AR66*AS66*4*12 -> 20496000 | BC66: =BB66*G66 -> 2049600 | BD66: =BB66*$BD$47 -> 61488000 | BE66: =BB66*$BE$47 -> 40992000 | BG66: =AC66+AE66+AG66+AI66+AK66+AM66 -> 3 | BH66: =AD66+AF66+AH66+AJ66+AL66+AN66 -> 24500 | BI66: 7 | BJ66: =BG66*BI66*4*12 -> 1008 | BK66: =BJ66*AB66 -> 10080000 | BL66: =BJ66*K66 -> 1512000 | BM66: =BI66*AO66*4*12*J66 -> 50400 | BN66: =BJ66*E66 -> 907200 | BO66: =BN66*F66 -> 2721600 | BP66: =BJ66*D66*H66 -> 176400 | BQ66: =BI66*AO66*I66*4*12 -> 522816 | BR66: =BH66*BI66*4*12 -> 8232000 | BS66: =BR66*G66 -> 823200
A67: 2 | B67: A321 | C67: 77800 | D67: 500 | E67: 900 | F67: 3 | G67: 0.1 | H67: 0.35 | I67: =C67*0.02 -> 1556 | J67: 150 | K67: 1500 | M67: 9000 | N67: 2.5 | O67: 24500 | P67: 2.5 | R67: 3 | S67: 24500 | T67: 3 | U67: 12000 | Z67: 4 | AB67: 10000 | AC67: 3 | AD67: 24500 | AO67: 1 | AQ67: =N67+P67+R67+T67+V67+X67 -> 11 | AR67: =O67+Q67+S67+U67+W67+Y67 -> 61000 | AS67: 6 | AT67: =AQ67*AS67*4*12 -> 3168 | AU67: =AT67*M67 -> 28512000 | AV67: =AT67*K67 -> 4752000 | AW67: =Z67*J67*AS67*4*12 -> 172800 | AX67: =AT67*E67 -> 2851200 | AY67: =AX67*F67 -> 8553600 | AZ67: =AT67*D67*H67 -> 554400 | BA67: =Z67*I67*AS67*4*12 -> 1792512 | BB67: =AR67*AS67*4*12 -> 17568000 | BC67: =BB67*G67 -> 1756800 | BD67: =BB67*$BD$47 -> 52704000 | BE67: =BB67*$BE$47 -> 35136000 | BG67: =AC67+AE67+AG67+AI67+AK67+AM67 -> 3 | BH67: =AE67+AG67+AI67+AK67+AM67+AO67 -> 1 | BI67: 7 | BJ67: =BG67*BI67*4*12 -> 1008 | BK67: =BJ67*AB67 -> 10080000 | BL67: =BJ67*K67 -> 1512000 | BM67: =BI67*AO67*4*12*J67 -> 50400 | BN67: =BJ67*E67 -> 907200 | BO67: =BN67*F67 -> 2721600 | BP67: =BJ67*D67*H67 -> 176400 | BQ67: =BI67*AO67*I67*4*12 -> 522816 | BR67: =BH67*BI67*4*12 -> 336 | BS67: =BR67*G67 -> 33.6
A68: 3 | B68: A321 | C68: 77800 | D68: 500 | E68: 900 | F68: 3 | G68: 0.1 | H68: 0.35 | I68: =C68*0.02 -> 1556 | J68: 150 | K68: 1500 | M68: 9000 | N68: 2.5 | O68: 24500 | P68: 2.5 | R68: 3 | S68: 24500 | T68: 3 | U68: 12000 | Z68: 4 | AB68: 10000 | AC68: 3 | AD68: 24500 | AO68: 1 | AQ68: =N68+P68+R68+T68+V68+X68 -> 11 | AR68: =O68+Q68+S68+U68+W68+Y68 -> 61000 | AS68: 6 | AT68: =AQ68*AS68*4*12 -> 3168 | AU68: =AT68*M68 -> 28512000 | AV68: =AT68*K68 -> 4752000 | AW68: =Z68*J68*AS68*4*12 -> 172800 | AX68: =AT68*E68 -> 2851200 | AY68: =AX68*F68 -> 8553600 | AZ68: =AT68*D68*H68 -> 554400 | BA68: =Z68*I68*AS68*4*12 -> 1792512 | BB68: =AR68*AS68*4*12 -> 17568000 | BC68: =BB68*G68 -> 1756800 | BD68: =BB68*$BD$47 -> 52704000 | BE68: =BB68*$BE$47 -> 35136000 | BG68: =AC68+AE68+AG68+AI68+AK68+AM68 -> 3 | BH68: =AE68+AG68+AI68+AK68+AM68+AO68 -> 1 | BI68: 7 | BJ68: =BG68*BI68*4*12 -> 1008 | BK68: =BJ68*AB68 -> 10080000 | BL68: =BJ68*K68 -> 1512000 | BM68: =BI68*AO68*4*12*J68 -> 50400 | BN68: =BJ68*E68 -> 907200 | BO68: =BN68*F68 -> 2721600 | BP68: =BJ68*D68*H68 -> 176400 | BQ68: =BI68*AO68*I68*4*12 -> 522816 | BR68: =BH68*BI68*4*12 -> 336 | BS68: =BR68*G68 -> 33.6
A69: 4 | B69: A321 | C69: 77800 | D69: 500 | E69: 900 | F69: 3 | G69: 0.1 | H69: 0.35 | I69: =C69*0.02 -> 1556 | J69: 150 | K69: 1500 | M69: 9000 | N69: 2.5 | O69: 24500 | P69: 2.5 | R69: 3 | S69: 24500 | T69: 3 | U69: 12000 | Z69: 4 | AB69: 10000 | AC69: 3 | AD69: 24500 | AO69: 1 | AQ69: =N69+P69+R69+T69+V69+X69 -> 11 | AR69: =O69+Q69+S69+U69+W69+Y69 -> 61000 | AS69: 6 | AT69: =AQ69*AS69*4*12 -> 3168 | AU69: =AT69*M69 -> 28512000 | AV69: =AT69*K69 -> 4752000 | AW69: =Z69*J69*AS69*4*12 -> 172800 | AX69: =AT69*E69 -> 2851200 | AY69: =AX69*F69 -> 8553600 | AZ69: =AT69*D69*H69 -> 554400 | BA69: =Z69*I69*AS69*4*12 -> 1792512 | BB69: =AR69*AS69*4*12 -> 17568000 | BC69: =BB69*G69 -> 1756800 | BD69: =BB69*$BD$47 -> 52704000 | BE69: =BB69*$BE$47 -> 35136000 | BG69: =AC69+AE69+AG69+AI69+AK69+AM69 -> 3 | BH69: =AE69+AG69+AI69+AK69+AM69+AO69 -> 1 | BJ69: =BG69*BI69*4*12 -> 0 | BK69: =BJ69*AB69 -> 0 | BL69: =BJ69*K69 -> 0 | BM69: =BI69*AO69*4*12*J69 -> 0 | BN69: =BJ69*E69 -> 0 | BO69: =BN69*F69 -> 0 | BP69: =BJ69*D69*H69 -> 0 | BQ69: =BI69*AO69*I69*4*12 -> 0 | BR69: =BH69*BI69*4*12 -> 0 | BS69: =BR69*G69 -> 0
A70: 3 | B70: B777 | C70: 260800 | D70: 500 | E70: 1800 | F70: 3 | G70: 0.1 | H70: 0.35 | I70: =C70*0.02 -> 5216 | J70: 350 | K70: 5500 | M70: 18000 | N70: 13 | O70: 102000 | Z70: 1 | AB70: 20000 | AQ70: =N70+P70+R70+T70+V70+X70 -> 13 | AR70: =O70+Q70+S70+U70+W70+Y70 -> 102000 | AS70: 7 | AT70: =AQ70*AS70*4*12 -> 4368 | AU70: =AT70*M70 -> 78624000 | AV70: =AT70*K70 -> 24024000 | AW70: =Z70*J70*AS70*4*12 -> 117600 | AX70: =AT70*E70 -> 7862400 | AY70: =AX70*F70 -> 23587200 | AZ70: =AT70*D70*H70 -> 764400 | BA70: =Z70*I70*AS70*4*12 -> 1752576 | BB70: =AR70*AS70*4*12 -> 34272000 | BC70: =BB70*G70 -> 3427200 | BD70: =BB70*$BD$47 -> 102816000 | BE70: =BB70*$BE$47 -> 68544000 | BG70: =AC70+AE70+AG70+AI70+AK70+AM70 -> 0 | BH70: =AE70+AG70+AI70+AK70+AM70+AO70 -> 0 | BJ70: =BG70*BI70*4*12 -> 0 | BK70: =BJ70*AB70 -> 0 | BL70: =BJ70*K70 -> 0 | BM70: =BI70*AO70*4*12*J70 -> 0 | BN70: =BJ70*E70 -> 0 | BO70: =BN70*F70 -> 0 | BP70: =BJ70*D70*H70 -> 0 | BQ70: =BI70*AO70*I70*4*12 -> 0 | BR70: =BH70*BI70*4*12 -> 0 | BS70: =BR70*G70 -> 0
A71: 4 | B71: B777 | C71: 260800 | D71: 500 | E71: 1800 | F71: 3 | G71: 0.1 | H71: 0.35 | I71: =C71*0.02 -> 5216 | J71: 350 | K71: 5500 | M71: 18000 | N71: 13 | O71: 102000 | Z71: 1 | AB71: 20000 | AC71: 13 | AD71: 102000 | AO71: 1 | AQ71: =N71+P71+R71+T71+V71+X71 -> 13 | AR71: =O71+Q71+S71+U71+W71+Y71 -> 102000 | AS71: 3 | AT71: =AQ71*AS71*4*12 -> 1872 | AU71: =AT71*M71 -> 33696000 | AV71: =AT71*K71 -> 10296000 | AW71: =Z71*J71*AS71*4*12 -> 50400 | AX71: =AT71*E71 -> 3369600 | AY71: =AX71*F71 -> 10108800 | AZ71: =AT71*D71*H71 -> 327600 | BA71: =Z71*I71*AS71*4*12 -> 751104 | BB71: =AR71*AS71*4*12 -> 14688000 | BC71: =BB71*G71 -> 1468800 | BD71: =BB71*$BD$47 -> 44064000 | BE71: =BB71*$BE$47 -> 29376000 | BG71: =AC71+AE71+AG71+AI71+AK71+AM71 -> 13 | BH71: =AE71+AG71+AI71+AK71+AM71+AO71 -> 1 | BI71: 3 | BJ71: =BG71*BI71*4*12 -> 1872 | BK71: =BJ71*AB71 -> 37440000 | BL71: =BJ71*K71 -> 10296000 | BM71: =BI71*AO71*4*12*J71 -> 50400 | BN71: =BJ71*E71 -> 3369600 | BO71: =BN71*F71 -> 10108800 | BP71: =BJ71*D71*H71 -> 327600 | BQ71: =BI71*AO71*I71*4*12 -> 751104 | BR71: =BH71*BI71*4*12 -> 144 | BS71: =BR71*G71 -> 14.4
AQ72: =SUM(AQ65:AQ69) -> 55 | AT72: =SUM(AT65:AT71) -> 23136 | AU72: =SUM(AU65:AU69) -> 152064000 | AV72: =SUM(AV65:AV71) -> 59664000 | AW72: =SUM(AW65:AW71) -> 1089600 | AX72: =SUM(AX65:AX71) -> 26438400 | AY72: =SUM(AY65:AY71) -> 79315200 | AZ72: =SUM(AZ65:AZ71) -> 4048800 | BA72: =SUM(BA65:BA71) -> 12063744 | BB72: =SUM(BB65:BB69) -> 93696000 | BC72: =SUM(BC65:BC71) -> 14265600 | BD72: =SUM(BD65:BD69) -> 281088000 | BE72: =SUM(BE65:BE69) -> 187392000 | BG72: =SUM(BG65:BG69) -> 15 | BJ72: =SUM(BJ65:BJ71) -> 5904 | BK72: =SUM(BK65:BK71) -> 77760000 | BL72: =SUM(BL65:BL71) -> 16344000 | BM72: =SUM(BM65:BM71) -> 252000 | BN72: =SUM(BN65:BN71) -> 6998400 | BO72: =SUM(BO65:BO71) -> 20995200 | BP72: =SUM(BP65:BP71) -> 1033200 | BQ72: =SUM(BQ65:BQ71) -> 2842368 | ... BS72: =SUM(BS65:BS71) -> 1646481.6
AQ73: =SUM(AQ70:AQ71) -> 26 | AU73: =SUM(AU70:AU71) -> 112320000 | BB73: =SUM(BB70:BB71) -> 48960000 | BD73: =SUM(BD70:BD71) -> 146880000 | BE73: =SUM(BE70:BE71) -> 97920000 | BG73: =SUM(BG70:BG71) -> 13 | BJ73: =BJ72+AT72 -> 29040 | BK73: total maint | BL73: =BL72+AV72 -> 76008000 | BN73: total fuel | BO73: =BO72+AY72 -> 100310400 | BP73: TOT. AERO. | BQ73: =BQ72+BP72+BM72+BS72+BC72+BA72+AZ72+AW72 -> 37241794
AU74: =SUM(AU72:AU73) -> 264384000 | BB74: =SUM(BB72:BB73) -> 142656000 | BD74: =SUM(BD72:BD73) -> 427968000 | BE74: =SUM(BE72:BE73) -> 285312000
BD75: =AU72+BD72+BE72 -> 620544000
BD76: =AU73+BD73+BE73 -> 357120000 | BE76: =BD74+BE74+AU74 -> 977664000
AV85: Americas | AW85: Europe / Asia | AY85: Continental | AZ85: Global
AU86: Year 1 | AV86: =BB11 -> 24624000 | AY86: =BB86*BC86*BA86 -> 89425000 | AZ86: =BD86*BE86*BA86 -> 0 | BA86: 365 | BB86: =5*24500 -> 122500 | BC86: 2 | BD86: 102000
AU87: Year 2 | AV87: =BB25 -> 40992000 | AY87: =BB87*BC87*BA87 -> 134137500 | AZ87: =BD87*BE87*BA87 -> 0 | BA87: 365 | BB87: =5*24500 -> 122500 | BC87: 3 | BD87: 102000
AU88: Year 3 | AV88: =BB40 -> 49776000 | AW88: =BB41 -> 24480000 | AY88: =BB88*BC88*BA88 -> 134137500 | AZ88: =BD88*BE88*BA88 -> 37230000 | BA88: 365 | BB88: =5*24500 -> 122500 | BC88: 3 | BD88: 102000 | BE88: 1
AU89: Year 4 | AV89: =BB55 -> 70272000 | AW89: =BB56 -> 44064000 | AY89: =BB89*BC89*BA89 -> 178850000 | AZ89: =BD89*BE89*BA89 -> 74460000 | BA89: 365 | BB89: =5*24500 -> 122500 | BC89: 4 | BD89: 102000 | BE89: 2
AU90: Year 5 | AV90: =BB72 -> 93696000 | AW90: =BB73 -> 48960000 | AY90: =BB90*BC90*BA90 -> 223562500 | AZ90: =BD90*BE90*BA90 -> 74460000 | BA90: 365 | BB90: =5*24500 -> 122500 | BC90: 5 | BD90: 102000 | BE90: 2

Sheet Income FRESH24
A1: FRESH 24
A2: Statements of Operations (Unaudited)
B3: YEAR 1 | C3: YEAR 2 | D3: YEAR 3 | E3: YEAR 4 | F3: YEAR 5
A4: Revenues:
A5: Direct Product Sales Americas | B5: =ANALYSIS!BE12 -> 164592000 | C5: =ANALYSIS!BE26 -> 271488000 | D5: =ANALYSIS!BD43 -> 329664000 | E5: =ANALYSIS!BD58 -> 465408000 | F5: =ANALYSIS!BD75 -> 620544000
A6: Direct Product Sales Eurasia | D6: =ANALYSIS!BD44 -> 178560000 | E6: =ANALYSIS!BD59 -> 321408000 | F6: =ANALYSIS!BD76 -> 357120000
A7: OtherServices
A9: Total revenue | B9: =SUM(B5:B8) -> 164592000 | C9: =SUM(C5:C8) -> 271488000 | D9: =SUM(D5:D8) -> 508224000 | E9: =SUM(E5:E8) -> 786816000 | F9: =SUM(F5:F8) -> 977664000
A11: Operating expenses:
A12: Air logistic | B12: =ANALYSIS!AU11 -> 41472000 | C12: =ANALYSIS!AU25 -> 66528000 | D12: =ANALYSIS!AU42 -> 136944000 | E12: =ANALYSIS!AU57 -> 215136000 | F12: =ANALYSIS!AU74 -> 264384000
A13: Sales & marketing | B13: 1200000 | C13: 1400000 | D13: 2200000 | E13: 3000000 | F13: 4000000
A14: products | B14: =ANALYSIS!BD11 -> 73872000 | C14: =ANALYSIS!BD25 -> 122976000 | D14: =ANALYSIS!BD42 -> 222768000 | E14: =ANALYSIS!BD57 -> 343008000 | F14: =ANALYSIS!BD74 -> 427968000
A15: Other expenses* | B15: 2200000 | C15: 2500000 | D15: 2750000 | E15: 3000000 | F15: 6000000
A16: Total operating expenses | B16: =SUM(B12:B15) -> 118744000 | C16: =SUM(C12:C15) -> 193404000 | D16: =SUM(D12:D15) -> 364662000 | E16: =SUM(E12:E15) -> 564144000 | F16: =SUM(F12:F15) -> 702352000
A18: Operating income/(loss) | B18: =B9-B16 -> 45848000 | C18: =C9-C16 -> 78084000 | D18: =D9-D16 -> 143562000 | E18: =E9-E16 -> 222672000 | F18: =F9-F16 -> 275312000
A19: Operating margin | B19: =B18/B9 -> 0.27855546 | C19: =C18/C9 -> 0.28761492 | D19: =D18/D9 -> 0.28247781 | E19: =E18/E9 -> 0.2830039 | F19: =F18/F9 -> 0.28160186
A20: Non-operating expense (income):
A21: Admin payroll | B21: 1800000 | C21: 2000000 | D21: 2800000 | E21: 3500000 | F21: 4000000
A22: Admin expenses | B22: 2500000 | C22: 2750000 | D22: 4250000 | E22: 4750000 | F22: 5250000
A23: Total non-operating expenses | B23: =SUM(B21:B22) -> 4300000 | C23: =SUM(C21:C22) -> 4750000 | D23: =SUM(D21:D22) -> 7050000 | E23: =SUM(E21:E22) -> 8250000 | F23: =SUM(F21:F22) -> 9250000
A25: EBITDA | B25: =B18-B23 -> 41548000 | C25: =C18-C23 -> 73334000 | D25: =D18-D23 -> 136512000 | E25: =E18-E23 -> 214422000 | F25: =F18-F23 -> 266062000
A26: EBITDA margin | B26: =B25/B9 -> 0.25243025 | C26: =C25/C9 -> 0.27011875 | D26: =D25/D9 -> 0.26860597 | E26: =E25/E9 -> 0.27251861 | F26: =F25/F9 -> 0.27214053
A27: Loan interest | B27: ='loan 1 FRESH24'!E18*-1 -> 2574728.1 | C27: ='loan 1 FRESH24'!E30*-1 -> 2420901.4 | D27: ='loan 1 FRESH24'!E42*-1 -> 2247565.6 | E27: ='loan 1 FRESH24'!E54*-1 -> 2052246.5 | F27: ='loan 1 FRESH24'!E66*-1 -> 1832156
A28: Depreciation | B28: 450000 | C28: 475000 | D28: 650000 | E28: 850000 | F28: 1000000
A29: Tax provision (25%) | B29: =B25*variables!$C$8 -> 10387000 | C29: =C25*variables!$C$8 -> 18333500 | D29: =D25*variables!$C$8 -> 34128000 | E29: =E25*variables!$C$8 -> 53605500 | F29: =F25*variables!$C$8 -> 66515500
A30: Net income/(loss) | B30: =B25-B29-B28-B27 -> 28136272 | C30: =C25-C29-C28-C27 -> 52104599 | D30: =D25-D29-D28-D27 -> 99486434 | E30: =E25-E29-E28-E27 -> 1.5791425e+08 | F30: =F25-F29-F28-F27 -> 1.9671434e+08
A31: Net income margin | B31: =B30/B9 -> 0.17094556 | C31: =C30/C9 -> 0.19192229 | D31: =D30/D9 -> 0.19575312 | E31: =E30/E9 -> 0.20070036 | F31: =F30/F9 -> 0.20120854

Sheet Cash flow FRESH24
A1: FRESH24 cash flow operations
B2: YEAR 1 | C2: YEAR 2 | D2: YEAR 3 | E2: YEAR 4 | F2: YEAR 5
A3: Beginning cash balance | C3: =B44 -> 29873367 | D3: =C44 -> 77586234 | E3: =D44 -> 1.754751e+08 | F3: =E44 -> 3.2768711e+08
A5: Cash flow from operating activities
A7: Net Income (from Income Statement) | B7: ='Income FRESH24'!B30 -> 28136272 | C7: ='Income FRESH24'!C30 -> 52104599 | D7: ='Income FRESH24'!D30 -> 99486434 | E7: ='Income FRESH24'!E30 -> 1.5791425e+08 | F7: ='Income FRESH24'!F30 -> 1.9671434e+08
A9: Adjustments for Non-Cash Items
A11: Depreciation & Amortization | B11: ='Income FRESH24'!B28 -> 450000 | C11: ='Income FRESH24'!C28 -> 475000 | D11: ='Income FRESH24'!D28 -> 650000 | E11: ='Income FRESH24'!E28 -> 850000 | F11: ='Income FRESH24'!F28 -> 1000000
A12: Provisions (if applicable)
A13: Losses / (-) Gains on Asset Disposal
A15: Adjustments for Working Capital Changes
A17: Increase in Accounts Receivable
A18: Decrease in Accounts Receivable
A19: Increase in Inventory (if applicable)
A20: Decrease in Inventory (if applicable)
A21: Increase in Accounts Payable
A22: Decrease in Accounts Payable
A23: Changes in Other Current Assets
A24: Changes in Other Current Liabilities
A26: Net Cash from Operating Activities | B26: =B7+B11+B12+B13-B17+B18-B19+B20+B21-B22-B23+B24 -> 28586272 | C26: =C3+C7+C11+C12+C13-C17+C18-C19+C20+C21-C22-C23+C24 -> 82452966 | D26: =D3+D7+D11+D12+D13-D17+D18-D19+D20+D21-D22-D23+D24 -> 1.7772267e+08 | E26: =E3+E7+E11+E12+E13-E17+E18-E19+E20+E21-E22-E23+E24 -> 3.3423936e+08 | F26: =F3+F7+F11+F12+F13-F17+F18-F19+F20+F21-F22-F23+F24 -> 5.2540145e+08
A28: Cash flow from investing activities
A30: Capital Expenditures (CapEx) | B30: -19500000 | C30: -3500000 | E30: -4500000
A32: Net Cash Flow from Investing Activities | B32: =B30 -> -19500000 | C32: =C30 -> -3500000 | D32: =D30 -> 0 | E32: =E30 -> -4500000 | F32: =F30 -> 0
A34: Cash flow from Financing Activities
A36: Debt Issuance | B36: 22000000
A37: Debt Repayments (Principal) | B37: ='loan 1 FRESH24'!F18*-1 -> -1212905 | C37: ='loan 1 FRESH24'!F30*-1 -> -1366731.7 | D37: ='loan 1 FRESH24'!E42 -> -2247565.6 | E37: ='loan 1 FRESH24'!E54 -> -2052246.5 | F37: ='loan 1 FRESH24'!E66 -> -1832156
A38: Interest Payments
A39: Equity Contributions
A40: Dividends Paid (-)
A42: Net Cash Flow from Financing Activities | B42: =SUM(B36:B41) -> 20787095 | C42: =SUM(C36:C41) -> -1366731.7 | D42: =SUM(D36:D41) -> -2247565.6 | E42: =SUM(E36:E41) -> -2052246.5 | F42: =SUM(F36:F41) -> -1832156
A44: Net Cash Flow | B44: =B26+B32+B42 -> 29873367 | C44: =C26+C32+C42 -> 77586234 | D44: =D26+D32+D42 -> 1.754751e+08 | E44: =E26+E32+E42 -> 3.2768711e+08 | F44: =F26+F32+F42 -> 5.235693e+08

Sheet loan 1 FRESH24
A1: loan amount | B1: 22000000
A2: Loan term | B2: 120
A3: Annual rate | B3: 0.12
A4: Monthly payment | B4: =PMT(B3/12,B2,-(B1)) -> 315636.09
A6: 0 | B6: payment | C6: interest | D6: remaining
A7: 1 | B7: =$B$4 -> 315636.09 | C7: =IPMT($B$3/12,A7,$B$2,($B$1)) -> -220000 | D7: =B7+C7 -> 95636.086
A8: 2 | B8: =$B$4 -> 315636.09 | C8: =IPMT($B$3/12,A8,$B$2,($B$1)) -> -219043.64 | D8: =B8+C8 -> 96592.447
A9: 3 | B9: =$B$4 -> 315636.09 | C9: =IPMT($B$3/12,A9,$B$2,($B$1)) -> -218077.71 | D9: =B9+C9 -> 97558.372
A10: 4 | B10: =$B$4 -> 315636.09 | C10: =IPMT($B$3/12,A10,$B$2,($B$1)) -> -217102.13 | D10: =B10+C10 -> 98533.956
A11: 5 | B11: =$B$4 -> 315636.09 | C11: =IPMT($B$3/12,A11,$B$2,($B$1)) -> -216116.79 | D11: =B11+C11 -> 99519.295
A12: 6 | B12: =$B$4 -> 315636.09 | C12: =IPMT($B$3/12,A12,$B$2,($B$1)) -> -215121.6 | D12: =B12+C12 -> 100514.49
A13: 7 | B13: =$B$4 -> 315636.09 | C13: =IPMT($B$3/12,A13,$B$2,($B$1)) -> -214116.45 | D13: =B13+C13 -> 101519.63
A14: 8 | B14: =$B$4 -> 315636.09 | C14: =IPMT($B$3/12,A14,$B$2,($B$1)) -> -213101.26 | D14: =B14+C14 -> 102534.83
A15: 9 | B15: =$B$4 -> 315636.09 | C15: =IPMT($B$3/12,A15,$B$2,($B$1)) -> -212075.91 | D15: =B15+C15 -> 103560.18
A16: 10 | B16: =$B$4 -> 315636.09 | C16: =IPMT($B$3/12,A16,$B$2,($B$1)) -> -211040.31 | D16: =B16+C16 -> 104595.78
A17: 11 | B17: =$B$4 -> 315636.09 | C17: =IPMT($B$3/12,A17,$B$2,($B$1)) -> -209994.35 | D17: =B17+C17 -> 105641.74
A18: 12 | B18: =$B$4 -> 315636.09 | C18: =IPMT($B$3/12,A18,$B$2,($B$1)) -> -208937.93 | D18: =B18+C18 -> 106698.15 | E18: =SUM(C7:C18) -> -2574728.1 | F18: =SUM(D7:D18) -> 1212905 | G18: =SUM(B7:B18) -> 3787633
A19: 13 | B19: =$B$4 -> 315636.09 | C19: =IPMT($B$3/12,A19,$B$2,($B$1)) -> -207870.95 | D19: =B19+C19 -> 107765.14
A20: 14 | B20: =$B$4 -> 315636.09 | C20: =IPMT($B$3/12,A20,$B$2,($B$1)) -> -206793.3 | D20: =B20+C20 -> 108842.79
A21: 15 | B21: =$B$4 -> 315636.09 | C21: =IPMT($B$3/12,A21,$B$2,($B$1)) -> -205704.87 | D21: =B21+C21 -> 109931.22
A22: 16 | B22: =$B$4 -> 315636.09 | C22: =IPMT($B$3/12,A22,$B$2,($B$1)) -> -204605.56 | D22: =B22+C22 -> 111030.53
A23: 17 | B23: =$B$4 -> 315636.09 | C23: =IPMT($B$3/12,A23,$B$2,($B$1)) -> -203495.25 | D23: =B23+C23 -> 112140.83
A24: 18 | B24: =$B$4 -> 315636.09 | C24: =IPMT($B$3/12,A24,$B$2,($B$1)) -> -202373.85 | D24: =B24+C24 -> 113262.24
A25: 19 | B25: =$B$4 -> 315636.09 | C25: =IPMT($B$3/12,A25,$B$2,($B$1)) -> -201241.22 | D25: =B25+C25 -> 114394.86
A26: 20 | B26: =$B$4 -> 315636.09 | C26: =IPMT($B$3/12,A26,$B$2,($B$1)) -> -200097.27 | D26: =B26+C26 -> 115538.81
A27: 21 | B27: =$B$4 -> 315636.09 | C27: =IPMT($B$3/12,A27,$B$2,($B$1)) -> -198941.89 | D27: =B27+C27 -> 116694.2
A28: 22 | B28: =$B$4 -> 315636.09 | C28: =IPMT($B$3/12,A28,$B$2,($B$1)) -> -197774.94 | D28: =B28+C28 -> 117861.14
A29: 23 | B29: =$B$4 -> 315636.09 | C29: =IPMT($B$3/12,A29,$B$2,($B$1)) -> -196596.33 | D29: =B29+C29 -> 119039.75
A30: 24 | B30: =$B$4 -> 315636.09 | C30: =IPMT($B$3/12,A30,$B$2,($B$1)) -> -195405.94 | D30: =B30+C30 -> 120230.15 | E30: =SUM(C19:C30) -> -2420901.4 | F30: =SUM(D19:D30) -> 1366731.7 | G30: =F30-E30 -> 3787633
A31: 25 | B31: =$B$4 -> 315636.09 | C31: =IPMT($B$3/12,A31,$B$2,($B$1)) -> -194203.63 | D31: =B31+C31 -> 121432.45
A32: 26 | B32: =$B$4 -> 315636.09 | C32: =IPMT($B$3/12,A32,$B$2,($B$1)) -> -192989.31 | D32: =B32+C32 -> 122646.78
A33: 27 | B33: =$B$4 -> 315636.09 | C33: =IPMT($B$3/12,A33,$B$2,($B$1)) -> -191762.84 | D33: =B33+C33 -> 123873.24
A34: 28 | B34: =$B$4 -> 315636.09 | C34: =IPMT($B$3/12,A34,$B$2,($B$1)) -> -190524.11 | D34: =B34+C34 -> 125111.98
A35: 29 | B35: =$B$4 -> 315636.09 | C35: =IPMT($B$3/12,A35,$B$2,($B$1)) -> -189272.99 | D35: =B35+C35 -> 126363.1
A36: 30 | B36: =$B$4 -> 315636.09 | C36: =IPMT($B$3/12,A36,$B$2,($B$1)) -> -188009.36 | D36: =B36+C36 -> 127626.73
A37: 31 | B37: =$B$4 -> 315636.09 | C37: =IPMT($B$3/12,A37,$B$2,($B$1)) -> -186733.09 | D37: =B37+C37 -> 128903
A38: 32 | B38: =$B$4 -> 315636.09 | C38: =IPMT($B$3/12,A38,$B$2,($B$1)) -> -185444.06 | D38: =B38+C38 -> 130192.03
A39: 33 | B39: =$B$4 -> 315636.09 | C39: =IPMT($B$3/12,A39,$B$2,($B$1)) -> -184142.14 | D39: =B39+C39 -> 131493.95
A40: 34 | B40: =$B$4 -> 315636.09 | C40: =IPMT($B$3/12,A40,$B$2,($B$1)) -> -182827.2 | D40: =B40+C40 -> 132808.89
A41: 35 | B41: =$B$4 -> 315636.09 | C41: =IPMT($B$3/12,A41,$B$2,($B$1)) -> -181499.11 | D41: =B41+C41 -> 134136.97
A42: 36 | B42: =$B$4 -> 315636.09 | C42: =IPMT($B$3/12,A42,$B$2,($B$1)) -> -180157.74 | D42: =B42+C42 -> 135478.34 | E42: =SUM(C31:C42) -> -2247565.6 | F42: =SUM(D31:D42) -> 1540067.4 | G42: =F42-E42 -> 3787633
A43: 37 | B43: =$B$4 -> 315636.09 | C43: =IPMT($B$3/12,A43,$B$2,($B$1)) -> -178802.96 | D43: =B43+C43 -> 136833.13
A44: 38 | B44: =$B$4 -> 315636.09 | C44: =IPMT($B$3/12,A44,$B$2,($B$1)) -> -177434.63 | D44: =B44+C44 -> 138201.46
A45: 39 | B45: =$B$4 -> 315636.09 | C45: =IPMT($B$3/12,A45,$B$2,($B$1)) -> -176052.61 | D45: =B45+C45 -> 139583.47
A46: 40 | B46: =$B$4 -> 315636.09 | C46: =IPMT($B$3/12,A46,$B$2,($B$1)) -> -174656.78 | D46: =B46+C46 -> 140979.31
A47: 41 | B47: =$B$4 -> 315636.09 | C47: =IPMT($B$3/12,A47,$B$2,($B$1)) -> -173246.99 | D47: =B47+C47 -> 142389.1
A48: 42 | B48: =$B$4 -> 315636.09 | C48: =IPMT($B$3/12,A48,$B$2,($B$1)) -> -171823.09 | D48: =B48+C48 -> 143812.99
A49: 43 | B49: =$B$4 -> 315636.09 | C49: =IPMT($B$3/12,A49,$B$2,($B$1)) -> -170384.96 | D49: =B49+C49 -> 145251.12
A50: 44 | B50: =$B$4 -> 315636.09 | C50: =IPMT($B$3/12,A50,$B$2,($B$1)) -> -168932.45 | D50: =B50+C50 -> 146703.63
A51: 45 | B51: =$B$4 -> 315636.09 | C51: =IPMT($B$3/12,A51,$B$2,($B$1)) -> -167465.42 | D51: =B51+C51 -> 148170.67
A52: 46 | B52: =$B$4 -> 315636.09 | C52: =IPMT($B$3/12,A52,$B$2,($B$1)) -> -165983.71 | D52: =B52+C52 -> 149652.38
A53: 47 | B53: =$B$4 -> 315636.09 | C53: =IPMT($B$3/12,A53,$B$2,($B$1)) -> -164487.19 | D53: =B53+C53 -> 151148.9
A54: 48 | B54: =$B$4 -> 315636.09 | C54: =IPMT($B$3/12,A54,$B$2,($B$1)) -> -162975.7 | D54: =B54+C54 -> 152660.39 | E54: =SUM(C43:C54) -> -2052246.5 | F54: =SUM(D43:D54) -> 1735386.5
A55: 49 | B55: =$B$4 -> 315636.09 | C55: =IPMT($B$3/12,A55,$B$2,($B$1)) -> -161449.09 | D55: =B55+C55 -> 154186.99
A56: 50 | B56: =$B$4 -> 315636.09 | C56: =IPMT($B$3/12,A56,$B$2,($B$1)) -> -159907.22 | D56: =B56+C56 -> 155728.86
A57: 51 | B57: =$B$4 -> 315636.09 | C57: =IPMT($B$3/12,A57,$B$2,($B$1)) -> -158349.94 | D57: =B57+C57 -> 157286.15
A58: 52 | B58: =$B$4 -> 315636.09 | C58: =IPMT($B$3/12,A58,$B$2,($B$1)) -> -156777.07 | D58: =B58+C58 -> 158859.01
A59: 53 | B59: =$B$4 -> 315636.09 | C59: =IPMT($B$3/12,A59,$B$2,($B$1)) -> -155188.48 | D59: =B59+C59 -> 160447.6
A60: 54 | B60: =$B$4 -> 315636.09 | C60: =IPMT($B$3/12,A60,$B$2,($B$1)) -> -153584.01 | D60: =B60+C60 -> 162052.08
A61: 55 | B61: =$B$4 -> 315636.09 | C61: =IPMT($B$3/12,A61,$B$2,($B$1)) -> -151963.49 | D61: =B61+C61 -> 163672.6
A62: 56 | B62: =$B$4 -> 315636.09 | C62: =IPMT($B$3/12,A62,$B$2,($B$1)) -> -150326.76 | D62: =B62+C62 -> 165309.33
A63: 57 | B63: =$B$4 -> 315636.09 | C63: =IPMT($B$3/12,A63,$B$2,($B$1)) -> -148673.67 | D63: =B63+C63 -> 166962.42
A64: 58 | B64: =$B$4 -> 315636.09 | C64: =IPMT($B$3/12,A64,$B$2,($B$1)) -> -147004.04 | D64: =B64+C64 -> 168632.04
A65: 59 | B65: =$B$4 -> 315636.09 | C65: =IPMT($B$3/12,A65,$B$2,($B$1)) -> -145317.72 | D65: =B65+C65 -> 170318.36
A66: 60 | B66: =$B$4 -> 315636.09 | C66: =IPMT($B$3/12,A66,$B$2,($B$1)) -> -143614.54 | D66: =B66+C66 -> 172021.55 | E66: =SUM(C55:C66) -> -1832156 | F66: =SUM(D55:D66) -> 1955477
C67: =SUM(C7:C66) -> -11127598 | D67: =SUM(D7:D66) -> 7810567.6 | E67: =SUM(E66,E54,E42,E30,E18) -> -11127598 | F67: =SUM(F66,F54,F42,F30,F18) -> 7810567.6

Sheet Income MAJESTIC
A1: MAJESTIC AIR CARGO
A2: Statements of Operations (Unaudited)
B3: YEAR 1 | C3: YEAR 2 | D3: YEAR 3 | E3: YEAR 4 | F3: YEAR 5
A4: Revenues:
A5: Indirect Charter Majestic | B5: =ANALYSIS!AU11 -> 41472000 | C5: =ANALYSIS!AU25 -> 66528000 | D5: =ANALYSIS!AU42 -> 136944000 | E5: =ANALYSIS!AU57 -> 215136000 | F5: =ANALYSIS!AU74 -> 264384000
A6: Indirect charter GSA | B6: =ANALYSIS!BK11 -> 20160000 | C6: =ANALYSIS!BK25 -> 40320000 | D6: =ANALYSIS!BK40 -> 30240000 | E6: =ANALYSIS!BK55 -> 77760000 | F6: =ANALYSIS!BK72 -> 77760000
A7: Direct Charter
A9: Total revenue | B9: =SUM(B5:B8) -> 61632000 | C9: =SUM(C5:C8) -> 106848000 | D9: =SUM(D5:D8) -> 167184000 | E9: =SUM(E5:E8) -> 292896000 | F9: =SUM(F5:F8) -> 342144000
A11: Operating expenses:
A12: Fuel | B12: =ANALYSIS!BO12 -> 17884800 | C12: =ANALYSIS!BO26 -> 30844800 | D12: =ANALYSIS!BO41 -> 49248000 | E12: =ANALYSIS!BO56 -> 85536000 | F12: =ANALYSIS!BO73 -> 100310400
A13: Maintenance | B13: =ANALYSIS!BL12 -> 9936000 | C13: =ANALYSIS!BL26 -> 17136000 | D13: =ANALYSIS!BL41 -> 35160000 | E13: =ANALYSIS!BL56 -> 66240000 | F13: =ANALYSIS!BL73 -> 76008000
A14: Aeronautical | B14: =ANALYSIS!BQ26 -> 14203560 | C14: =ANALYSIS!BQ26 -> 14203560 | D14: =ANALYSIS!BQ41 -> 20341906 | E14: =ANALYSIS!BQ56 -> 30673810 | F14: =ANALYSIS!BQ73 -> 37241794
A15: Staff / Crew | B15: 2850000 | C15: 3450000 | D15: 4450000 | E15: 5750000 | F15: 7000000
A16: Lease / Rent | B16: 450000 | C16: 475000 | D16: 525000 | E16: 600000 | F16: 850000
A17: Training | B17: 450000 | C17: 550000 | D17: 650000 | E17: 950000 | F17: 1250000
A18: Insurance | B18: 600000 | C18: 900000 | D18: 1350000 | E18: 2100000 | F18: 2450000
A19: Other | B19: 527000 | C19: 650000 | D19: 850000 | E19: 1575000 | F19: 2575000
A21: Other expenses*
A22: Total operating expenses | B22: =SUM(B12:B21) -> 46901360 | C22: =SUM(C12:C21) -> 68209360 | D22: =SUM(D12:D21) -> 1.1257491e+08 | E22: =SUM(E12:E21) -> 1.9342481e+08 | F22: =SUM(F12:F21) -> 2.2768519e+08
A24: Operating income/(loss) | B24: =B9-B22 -> 14730640 | C24: =C9-C22 -> 38638640 | D24: =D9-D22 -> 54609094 | E24: =E9-E22 -> 99471190 | F24: =F9-F22 -> 1.1445881e+08
A25: Operating margin | B25: =B24/B9 -> 0.23900961 | C25: =C24/C9 -> 0.36162249 | D25: =D24/D9 -> 0.32664067 | E25: =E24/E9 -> 0.33961266 | F25: =F24/F9 -> 0.33453402
A26: Non-operating expense (income):
A27: Admin payroll | B27: 1500000 | C27: 1750000 | D27: 2250000 | E27: 2750000 | F27: 3500000
A28: Admin expenses | B28: 1000000 | C28: 1400000 | D28: 1800000 | E28: 2200000 | F28: 2850000
A29: Total non-operating expenses | B29: =SUM(B27:B28) -> 2500000 | C29: =SUM(C27:C28) -> 3150000 | D29: =SUM(D27:D28) -> 4050000 | E29: =SUM(E27:E28) -> 4950000 | F29: =SUM(F27:F28) -> 6350000
A31: EBITDA | B31: =B24-B29 -> 12230640 | C31: =C24-C29 -> 35488640 | D31: =D24-D29 -> 50559094 | E31: =E24-E29 -> 94521190 | F31: =F24-F29 -> 1.0810881e+08
A32: EBITDA margin | B32: =B31/B9 -> 0.19844626 | C32: =C31/C9 -> 0.33214136 | D32: =D31/D9 -> 0.30241587 | E32: =E31/E9 -> 0.32271247 | F32: =F31/F9 -> 0.31597458
A33: Loan interest | B33: ='loan 1Majestic'!E18*-1 -> 4908200.6 | C33: =('loan 1Majestic'!E30+'loan 1Majestic'!K18)*-1 -> 6792484 | D33: =('loan 1Majestic'!E42+'loan 1Majestic'!K30+'loan 1Majestic'!Q18)*-1 -> 10105260 | E33: =('loan 1Majestic'!E54+'loan 1Majestic'!K42+'loan 1Majestic'!Q30+'loan 1Majestic'!W18)*-1 -> 14005339 | F33: =('loan 1Majestic'!E66+'loan 1Majestic'!K54+'loan 1Majestic'!Q42+'loan 1Majestic'!W30+'loan 1Majestic'!AC18)*-1 -> 14805460
A34: Depreciation | B34: 255000 | C34: 550000 | D34: 750000 | E34: 1000000 | F34: 1250000
A35: Tax provision (25%) | B35: =B31*variables!$C$8 -> 3057660 | C35: =C31*variables!$C$8 -> 8872160 | D35: =D31*variables!$C$8 -> 12639774 | E35: =E31*variables!$C$8 -> 23630298 | F35: =F31*variables!$C$8 -> 27027202
A36: Net income/(loss) | B36: =B31-B35-B34-B33 -> 4009779.4 | C36: =C31-C35-C34-C33 -> 19273996 | D36: =D31-D35-D34-D33 -> 27064060 | E36: =E31-E35-E34-E33 -> 55885554 | F36: =F31-F35-F34-F33 -> 65026144
A37: Net income margin | B37: =B36/B9 -> 0.065060024 | C37: =C36/C9 -> 0.18038705 | D37: =D36/D9 -> 0.16188188 | E37: =E36/E9 -> 0.19080341 | F37: =F36/F9 -> 0.1900549

Sheet Cash flow MAJESTIC
A1: MAJESTIC AIR CARGO cash flow operations
B2: YEAR 1 | C2: YEAR 2 | D2: YEAR 3 | E2: YEAR 4 | F2: YEAR 5
A3: Beginning cash balance | C3: =B44 -> 3234788.7 | D3: =C44 -> 21403757 | E3: =D44 -> 46223773 | F3: =E44 -> 97997340
A5: Cash flow from operating activities
A7: Net Income (from Income Statement) | B7: ='Income MAJESTIC'!B36 -> 4009779.4 | C7: ='Income MAJESTIC'!C36 -> 19273996 | D7: ='Income MAJESTIC'!D36 -> 27064060 | E7: ='Income MAJESTIC'!E36 -> 55885554 | F7: ='Income MAJESTIC'!F36 -> 65026144
A9: Adjustments for Non-Cash Items
A11: Depreciation & Amortization | B11: ='Income MAJESTIC'!B34 -> 255000 | C11: ='Income MAJESTIC'!C34 -> 550000 | D11: ='Income MAJESTIC'!D34 -> 750000 | E11: ='Income MAJESTIC'!E34 -> 1000000 | F11: ='Income MAJESTIC'!F34 -> 1250000
A12: Provisions (if applicable)
A13: Losses / (-) Gains on Asset Disposal
A15: Adjustments for Working Capital Changes
A17: Increase in Accounts Receivable
A18: Decrease in Accounts Receivable
A19: Increase in Inventory (if applicable)
A20: Decrease in Inventory (if applicable)
A21: Increase in Accounts Payable
A22: Decrease in Accounts Payable
A23: Changes in Other Current Assets
A24: Changes in Other Current Liabilities
A26: Net Cash from Operating Activities | B26: =B7+B11+B12+B13-B17+B18-B19+B20+B21-B22-B23+B24 -> 4264779.4 | C26: =C3+C7+C11+C12+C13-C17+C18-C19+C20+C21-C22-C23+C24 -> 23058785 | D26: =D3+D7+D11+D12+D13-D17+D18-D19+D20+D21-D22-D23+D24 -> 49217818 | E26: =E3+E7+E11+E12+E13-E17+E18-E19+E20+E21-E22-E23+E24 -> 1.0310933e+08 | F26: =F3+F7+F11+F12+F13-F17+F18-F19+F20+F21-F22-F23+F24 -> 1.6427348e+08
A28: Cash flow from investing activities
A30: Capital Expenditures (CapEx) | B30: ='loan 1Majestic'!C1*-1 -> -55000000 | C30: ='loan 1Majestic'!I1*-1 -> -25000000 | D30: ='loan 1Majestic'!O1*-1 -> -50000000 | E30: ='loan 1Majestic'!U1*-1 -> -70000000 | F30: ='loan 1Majestic'!AA1*-1 -> -20000000 | H30: =SUM(B30:G30) -> -220000000
A32: Net Cash Flow from Investing Activities | B32: =B30 -> -55000000 | C32: =C30 -> -25000000 | D32: =D30 -> -50000000 | E32: =E30 -> -70000000 | F32: =F30 -> -20000000
A34: Cash flow from Financing Activities
A36: Debt Issuance | B36: ='loan 1Majestic'!C1 -> 55000000 | C36: ='loan 1Majestic'!I1 -> 25000000 | D36: ='loan 1Majestic'!O1 -> 50000000 | E36: ='loan 1Majestic'!U1 -> 70000000 | F36: ='loan 1Majestic'!AA1 -> 20000000
A37: Debt Repayments (Principal) | B37: ='loan 1Majestic'!E19*-1 -> -1029990.7 | C37: =('loan 1Majestic'!E31+'loan 1Majestic'!K19)*-1 -> -1655027.5 | D37: =('loan 1Majestic'!E43+'loan 1Majestic'!K31+'loan 1Majestic'!Q19)*-1 -> -2994044.7 | E37: =('loan 1Majestic'!E55+'loan 1Majestic'!K43+'loan 1Majestic'!Q31+'loan 1Majestic'!W19)*-1 -> -5111987.4 | F37: =('loan 1Majestic'!E67+'loan 1Majestic'!K55+'loan 1Majestic'!Q43+'loan 1Majestic'!W31+'loan 1Majestic'!AC19)*-1 -> -6031300.1
A38: Interest Payments
A39: Equity Contributions
A40: Dividends Paid (-)
A42: Net Cash Flow from Financing Activities | B42: =SUM(B36:B41) -> 53970009 | C42: =SUM(C36:C41) -> 23344973 | D42: =SUM(D36:D41) -> 47005955 | E42: =SUM(E36:E41) -> 64888013 | F42: =SUM(F36:F41) -> 13968700
A44: Net Cash Flow | B44: =B26+B32+B42 -> 3234788.7 | C44: =C26+C32+C42 -> 21403757 | D44: =D26+D32+D42 -> 46223773 | E44: =E26+E32+E42 -> 97997340 | F44: =F26+F32+F42 -> 1.5824218e+08

Sheet loan 1Majestic
B1: loan amount | C1: 55000000 | H1: loan amount | I1: 25000000 | N1: loan amount | O1: 50000000 | T1: loan amount | U1: 70000000 | Z1: loan amount | AA1: 20000000 | AF1: loan amount | AG1: 40000000
B2: Loan term | C2: 240 | H2: Loan term | I2: 240 | N2: Loan term | O2: 240 | T2: Loan term | U2: 240 | Z2: Loan term | AA2: 240 | AF2: Loan term | AG2: 96
B3: Annual rate | C3: 0.09 | H3: Annual rate | I3: 0.08 | N3: Annual rate | O3: 0.07 | T3: Annual rate | U3: 0.06 | Z3: Annual rate | AA3: 0.06 | AF3: Annual rate | AG3: 0.09
B4: Monthly payment | C4: =PMT(C3/12,C2,-(C1)) -> 494849.28 | H4: Monthly payment | I4: =PMT(I3/12,I2,-(I1)) -> 209110.02 | N4: Monthly payment | O4: =PMT(O3/12,O2,-(O1)) -> 387649.47 | T4: Monthly payment | U4: =PMT(U3/12,U2,-(U1)) -> 501501.74 | Z4: Monthly payment | AA4: =PMT(AA3/12,AA2,-(AA1)) -> 143286.21 | AF4: Monthly payment | AG4: =PMT(AG3/12,AG2,-(AG1)) -> 586008.13
A6: 0 | B6: payment | C6: interest | D6: remaining | G6: 0 | H6: payment | I6: interest | J6: remaining | M6: 0 | N6: payment | O6: interest | P6: remaining | S6: 0 | T6: payment | U6: interest | V6: remaining | Y6: 0 | Z6: payment | AA6: interest | AB6: remaining | AE6: 0 | AF6: payment | AG6: interest | AH6: remaining
A7: 1 | B7: =$C$4 -> 494849.28 | C7: =IPMT($C$3/12,A7,$C$2,($C$1)) -> -412500 | D7: =B7+C7 -> 82349.276 | G7: 1 | H7: =$I$4 -> 209110.02 | I7: =IPMT($I$3/12,G7,$I$2,($I$1)) -> -166666.67 | J7: =H7+I7 -> 42443.351 | M7: 1 | N7: =$O$4 -> 387649.47 | O7: =IPMT($O$3/12,M7,$O$2,($O$1)) -> -291666.67 | P7: =N7+O7 -> 95982.801 | S7: 1 | T7: =$U$4 -> 501501.74 | U7: =IPMT($U$3/12,S7,$U$2,($U$1)) -> -350000 | V7: =T7+U7 -> 151501.74 | Y7: 1 | Z7: =$AA$4 -> 143286.21 | AA7: =IPMT($AA$3/12,Y7,$AA$2,($AA$1)) -> -100000 | AB7: =Z7+AA7 -> 43286.212 | AE7: 1 | AF7: =$AG$4 -> 586008.13 | AG7: =IPMT($AG$3/12,AE7,$AG$2,($AG$1)) -> -300000 | AH7: =AF7+AG7 -> 286008.13
A8: 2 | B8: =$C$4 -> 494849.28 | C8: =IPMT($C$3/12,A8,$C$2,($C$1)) -> -411882.38 | D8: =B8+C8 -> 82966.895 | G8: 2 | H8: =$I$4 -> 209110.02 | I8: =IPMT($I$3/12,G8,$I$2,($I$1)) -> -166383.71 | J8: =H8+I8 -> 42726.306 | M8: 2 | N8: =$O$4 -> 387649.47 | O8: =IPMT($O$3/12,G8,$O$2,($O$1)) -> -291106.77 | P8: =N8+O8 -> 96542.701 | S8: 2 | T8: =$U$4 -> 501501.74 | U8: =IPMT($U$3/12,S8,$U$2,($U$1)) -> -349242.49 | V8: =T8+U8 -> 152259.25 | Y8: 2 | Z8: =$AA$4 -> 143286.21 | AA8: =IPMT($AA$3/12,Y8,$AA$2,($AA$1)) -> -99783.569 | AB8: =Z8+AA8 -> 43502.643 | AE8: 2 | AF8: =$AG$4 -> 586008.13 | AG8: =IPMT($AG$3/12,AE8,$AG$2,($AG$1)) -> -297854.94 | AH8: =AF8+AG8 -> 288153.19
A9: 3 | B9: =$C$4 -> 494849.28 | C9: =IPMT($C$3/12,A9,$C$2,($C$1)) -> -411260.13 | D9: =B9+C9 -> 83589.147 | G9: 3 | H9: =$I$4 -> 209110.02 | I9: =IPMT($I$3/12,G9,$I$2,($I$1)) -> -166098.87 | J9: =H9+I9 -> 43011.148 | M9: 3 | N9: =$O$4 -> 387649.47 | O9: =IPMT($O$3/12,G9,$O$2,($O$1)) -> -290543.6 | P9: =N9+O9 -> 97105.867 | S9: 3 | T9: =$U$4 -> 501501.74 | U9: =IPMT($U$3/12,S9,$U$2,($U$1)) -> -348481.2 | V9: =T9+U9 -> 153020.55 | Y9: 3 | Z9: =$AA$4 -> 143286.21 | AA9: =IPMT($AA$3/12,Y9,$AA$2,($AA$1)) -> -99566.056 | AB9: =Z9+AA9 -> 43720.156 | AE9: 3 | AF9: =$AG$4 -> 586008.13 | AG9: =IPMT($AG$3/12,AE9,$AG$2,($AG$1)) -> -295693.79 | AH9: =AF9+AG9 -> 290314.34
A10: 4 | B10: =$C$4 -> 494849.28 | C10: =IPMT($C$3/12,A10,$C$2,($C$1)) -> -410633.21 | D10: =B10+C10 -> 84216.066 | G10: 4 | H10: =$I$4 -> 209110.02 | I10: =IPMT($I$3/12,G10,$I$2,($I$1)) -> -165812.13 | J10: =H10+I10 -> 43297.889 | M10: 4 | N10: =$O$4 -> 387649.47 | O10: =IPMT($O$3/12,G10,$O$2,($O$1)) -> -289977.15 | P10: =N10+O10 -> 97672.317 | S10: 4 | T10: =$U$4 -> 501501.74 | U10: =IPMT($U$3/12,S10,$U$2,($U$1)) -> -347716.09 | V10: =T10+U10 -> 153785.65 | Y10: 4 | Z10: =$AA$4 -> 143286.21 | AA10: =IPMT($AA$3/12,Y10,$AA$2,($AA$1)) -> -99347.455 | AB10: =Z10+AA10 -> 43938.757 | AE10: 4 | AF10: =$AG$4 -> 586008.13 | AG10: =IPMT($AG$3/12,AE10,$AG$2,($AG$1)) -> -293516.43 | AH10: =AF10+AG10 -> 292491.7
A11: 5 | B11: =$C$4 -> 494849.28 | C11: =IPMT($C$3/12,A11,$C$2,($C$1)) -> -410001.59 | D11: =B11+C11 -> 84847.686 | G11: 5 | H11: =$I$4 -> 209110.02 | I11: =IPMT($I$3/12,G11,$I$2,($I$1)) -> -165523.48 | J11: =H11+I11 -> 43586.542 | M11: 5 | N11: =$O$4 -> 387649.47 | O11: =IPMT($O$3/12,G11,$O$2,($O$1)) -> -289407.4 | P11: =N11+O11 -> 98242.073 | S11: 5 | T11: =$U$4 -> 501501.74 | U11: =IPMT($U$3/12,S11,$U$2,($U$1)) -> -346947.16 | V11: =T11+U11 -> 154554.58 | Y11: 5 | Z11: =$AA$4 -> 143286.21 | AA11: =IPMT($AA$3/12,Y11,$AA$2,($AA$1)) -> -99127.761 | AB11: =Z11+AA11 -> 44158.451 | AE11: 5 | AF11: =$AG$4 -> 586008.13 | AG11: =IPMT($AG$3/12,AE11,$AG$2,($AG$1)) -> -291322.74 | AH11: =AF11+AG11 -> 294685.39
A12: 6 | B12: =$C$4 -> 494849.28 | C12: =IPMT($C$3/12,A12,$C$2,($C$1)) -> -409365.23 | D12: =B12+C12 -> 85484.044 | G12: 6 | H12: =$I$4 -> 209110.02 | I12: =IPMT($I$3/12,G12,$I$2,($I$1)) -> -165232.9 | J12: =H12+I12 -> 43877.119 | M12: 6 | N12: =$O$4 -> 387649.47 | O12: =IPMT($O$3/12,G12,$O$2,($O$1)) -> -288834.32 | P12: =N12+O12 -> 98815.151 | S12: 6 | T12: =$U$4 -> 501501.74 | U12: =IPMT($U$3/12,S12,$U$2,($U$1)) -> -346174.39 | V12: =T12+U12 -> 155327.35 | Y12: 6 | Z12: =$AA$4 -> 143286.21 | AA12: =IPMT($AA$3/12,Y12,$AA$2,($AA$1)) -> -98906.969 | AB12: =Z12+AA12 -> 44379.243 | AE12: 6 | AF12: =$AG$4 -> 586008.13 | AG12: =IPMT($AG$3/12,AE12,$AG$2,($AG$1)) -> -289112.6 | AH12: =AF12+AG12 -> 296895.53
A13: 7 | B13: =$C$4 -> 494849.28 | C13: =IPMT($C$3/12,A13,$C$2,($C$1)) -> -408724.1 | D13: =B13+C13 -> 86125.174 | G13: 7 | H13: =$I$4 -> 209110.02 | I13: =IPMT($I$3/12,G13,$I$2,($I$1)) -> -164940.38 | J13: =H13+I13 -> 44169.633 | M13: 7 | N13: =$O$4 -> 387649.47 | O13: =IPMT($O$3/12,G13,$O$2,($O$1)) -> -288257.89 | P13: =N13+O13 -> 99391.573 | S13: 7 | T13: =$U$4 -> 501501.74 | U13: =IPMT($U$3/12,S13,$U$2,($U$1)) -> -345397.75 | V13: =T13+U13 -> 156103.99 | Y13: 7 | Z13: =$AA$4 -> 143286.21 | AA13: =IPMT($AA$3/12,Y13,$AA$2,($AA$1)) -> -98685.073 | AB13: =Z13+AA13 -> 44601.139 | AE13: 7 | AF13: =$AG$4 -> 586008.13 | AG13: =IPMT($AG$3/12,AE13,$AG$2,($AG$1)) -> -286885.89 | AH13: =AF13+AG13 -> 299122.24
A14: 8 | B14: =$C$4 -> 494849.28 | C14: =IPMT($C$3/12,A14,$C$2,($C$1)) -> -408078.16 | D14: =B14+C14 -> 86771.113 | G14: 8 | H14: =$I$4 -> 209110.02 | I14: =IPMT($I$3/12,G14,$I$2,($I$1)) -> -164645.92 | J14: =H14+I14 -> 44464.097 | M14: 8 | N14: =$O$4 -> 387649.47 | O14: =IPMT($O$3/12,G14,$O$2,($O$1)) -> -287678.11 | P14: =N14+O14 -> 99971.357 | S14: 8 | T14: =$U$4 -> 501501.74 | U14: =IPMT($U$3/12,S14,$U$2,($U$1)) -> -344617.23 | V14: =T14+U14 -> 156884.51 | Y14: 8 | Z14: =$AA$4 -> 143286.21 | AA14: =IPMT($AA$3/12,Y14,$AA$2,($AA$1)) -> -98462.067 | AB14: =Z14+AA14 -> 44824.145 | AE14: 8 | AF14: =$AG$4 -> 586008.13 | AG14: =IPMT($AG$3/12,AE14,$AG$2,($AG$1)) -> -284642.47 | AH14: =AF14+AG14 -> 301365.66
A15: 9 | B15: =$C$4 -> 494849.28 | C15: =IPMT($C$3/12,A15,$C$2,($C$1)) -> -407427.38 | D15: =B15+C15 -> 87421.896 | G15: 9 | H15: =$I$4 -> 209110.02 | I15: =IPMT($I$3/12,G15,$I$2,($I$1)) -> -164349.49 | J15: =H15+I15 -> 44760.524 | M15: 9 | N15: =$O$4 -> 387649.47 | O15: =IPMT($O$3/12,G15,$O$2,($O$1)) -> -287094.94 | P15: =N15+O15 -> 100554.52 | S15: 9 | T15: =$U$4 -> 501501.74 | U15: =IPMT($U$3/12,S15,$U$2,($U$1)) -> -343832.81 | V15: =T15+U15 -> 157668.93 | Y15: 9 | Z15: =$AA$4 -> 143286.21 | AA15: =IPMT($AA$3/12,Y15,$AA$2,($AA$1)) -> -98237.946 | AB15: =Z15+AA15 -> 45048.265 | AE15: 9 | AF15: =$AG$4 -> 586008.13 | AG15: =IPMT($AG$3/12,AE15,$AG$2,($AG$1)) -> -282382.23 | AH15: =AF15+AG15 -> 303625.9
A16: 10 | B16: =$C$4 -> 494849.28 | C16: =IPMT($C$3/12,A16,$C$2,($C$1)) -> -406771.72 | D16: =B16+C16 -> 88077.56 | G16: 10 | H16: =$I$4 -> 209110.02 | I16: =IPMT($I$3/12,G16,$I$2,($I$1)) -> -164051.09 | J16: =H16+I16 -> 45058.928 | M16: 10 | N16: =$O$4 -> 387649.47 | O16: =IPMT($O$3/12,G16,$O$2,($O$1)) -> -286508.38 | P16: =N16+O16 -> 101141.09 | S16: 10 | T16: =$U$4 -> 501501.74 | U16: =IPMT($U$3/12,S16,$U$2,($U$1)) -> -343044.47 | V16: =T16+U16 -> 158457.27 | Y16: 10 | Z16: =$AA$4 -> 143286.21 | AA16: =IPMT($AA$3/12,Y16,$AA$2,($AA$1)) -> -98012.705 | AB16: =Z16+AA16 -> 45273.507 | AE16: 10 | AF16: =$AG$4 -> 586008.13 | AG16: =IPMT($AG$3/12,AE16,$AG$2,($AG$1)) -> -280105.03 | AH16: =AF16+AG16 -> 305903.1
A17: 11 | B17: =$C$4 -> 494849.28 | C17: =IPMT($C$3/12,A17,$C$2,($C$1)) -> -406111.13 | D17: =B17+C17 -> 88738.142 | G17: 11 | H17: =$I$4 -> 209110.02 | I17: =IPMT($I$3/12,G17,$I$2,($I$1)) -> -163750.7 | J17: =H17+I17 -> 45359.321 | M17: 11 | N17: =$O$4 -> 387649.47 | O17: =IPMT($O$3/12,G17,$O$2,($O$1)) -> -285918.39 | P17: =N17+O17 -> 101731.08 | S17: 11 | T17: =$U$4 -> 501501.74 | U17: =IPMT($U$3/12,S17,$U$2,($U$1)) -> -342252.18 | V17: =T17+U17 -> 159249.56 | Y17: 11 | Z17: =$AA$4 -> 143286.21 | AA17: =IPMT($AA$3/12,Y17,$AA$2,($AA$1)) -> -97786.337 | AB17: =Z17+AA17 -> 45499.874 | AE17: 11 | AF17: =$AG$4 -> 586008.13 | AG17: =IPMT($AG$3/12,AE17,$AG$2,($AG$1)) -> -277810.76 | AH17: =AF17+AG17 -> 308197.37
A18: 12 | B18: =$C$4 -> 494849.28 | C18: =IPMT($C$3/12,A18,$C$2,($C$1)) -> -405445.6 | D18: =B18+C18 -> 89403.678 | E18: =SUM(C7:C18) -> -4908200.6 | G18: 12 | H18: =$I$4 -> 209110.02 | I18: =IPMT($I$3/12,G18,$I$2,($I$1)) -> -163448.3 | J18: =H18+I18 -> 45661.716 | K18: =SUM(I7:I18) -> -1980903.6 | M18: 12 | N18: =$O$4 -> 387649.47 | O18: =IPMT($O$3/12,G18,$O$2,($O$1)) -> -285324.96 | P18: =N18+O18 -> 102324.51 | Q18: =SUM(O7:O18) -> -3462318.6 | S18: 12 | T18: =$U$4 -> 501501.74 | U18: =IPMT($U$3/12,S18,$U$2,($U$1)) -> -341455.93 | V18: =T18+U18 -> 160045.81 | W18: =SUM(U7:U18) -> -4149161.7 | Y18: 12 | Z18: =$AA$4 -> 143286.21 | AA18: =IPMT($AA$3/12,Y18,$AA$2,($AA$1)) -> -97558.838 | AB18: =Z18+AA18 -> 45727.374 | AC18: =SUM(AA7:AA18) -> -1185474.8 | AE18: 12 | AF18: =$AG$4 -> 586008.13 | AG18: =IPMT($AG$3/12,AE18,$AG$2,($AG$1)) -> -275499.28 | AH18: =AF18+AG18 -> 310508.85 | AI18: =SUM(AG7:AG18) -> -3454826.2
A19: 13 | B19: =$C$4 -> 494849.28 | C19: =IPMT($C$3/12,A19,$C$2,($C$1)) -> -404775.07 | D19: =B19+C19 -> 90074.206 | E19: =SUM(D7:D18) -> 1029990.7 | G19: 13 | H19: =$I$4 -> 209110.02 | I19: =IPMT($I$3/12,G19,$I$2,($I$1)) -> -163143.89 | J19: =H19+I19 -> 45966.128 | K19: =SUM(J7:J18) -> 528416.57 | M19: 13 | N19: =$O$4 -> 387649.47 | O19: =IPMT($O$3/12,G19,$O$2,($O$1)) -> -284728.06 | P19: =N19+O19 -> 102921.41 | Q19: =SUM(P7:P18) -> 1189475 | S19: 13 | T19: =$U$4 -> 501501.74 | U19: =IPMT($U$3/12,S19,$U$2,($U$1)) -> -340655.7 | V19: =T19+U19 -> 160846.04 | W19: =SUM(V7:V18) -> 1868859.2 | Y19: 13 | Z19: =$AA$4 -> 143286.21 | AA19: =IPMT($AA$3/12,Y19,$AA$2,($AA$1)) -> -97330.201 | AB19: =Z19+AA19 -> 45956.011 | AC19: =SUM(AB7:AB18) -> 533959.76 | AE19: 13 | AF19: =$AG$4 -> 586008.13 | AG19: =IPMT($AG$3/12,AE19,$AG$2,($AG$1)) -> -273170.46 | AH19: =AF19+AG19 -> 312837.67 | AI19: =SUM(AH7:AH18) -> 3577271.4
A20: 14 | B20: =$C$4 -> 494849.28 | C20: =IPMT($C$3/12,A20,$C$2,($C$1)) -> -404099.51 | D20: =B20+C20 -> 90749.762 | E20: =SUM(B7:B18) -> 5938191.3 | G20: 14 | H20: =$I$4 -> 209110.02 | I20: =IPMT($I$3/12,G20,$I$2,($I$1)) -> -162837.45 | J20: =H20+I20 -> 46272.569 | K20: =SUM(H7:H18) -> 2509320.2 | M20: 14 | N20: =$O$4 -> 387649.47 | O20: =IPMT($O$3/12,G20,$O$2,($O$1)) -> -284127.69 | P20: =N20+O20 -> 103521.78 | S20: 14 | T20: =$U$4 -> 501501.74 | U20: =IPMT($U$3/12,S20,$U$2,($U$1)) -> -339851.47 | V20: =T20+U20 -> 161650.27 | Y20: 14 | Z20: =$AA$4 -> 143286.21 | AA20: =IPMT($AA$3/12,Y20,$AA$2,($AA$1)) -> -97100.421 | AB20: =Z20+AA20 -> 46185.791 | AE20: 14 | AF20: =$AG$4 -> 586008.13 | AG20: =IPMT($AG$3/12,AE20,$AG$2,($AG$1)) -> -270824.18 | AH20: =AF20+AG20 -> 315183.95
A21: 15 | B21: =$C$4 -> 494849.28 | C21: =IPMT($C$3/12,A21,$C$2,($C$1)) -> -403418.89 | D21: =B21+C21 -> 91430.386 | G21: 15 | H21: =$I$4 -> 209110.02 | I21: =IPMT($I$3/12,G21,$I$2,($I$1)) -> -162528.96 | J21: =H21+I21 -> 46581.052 | M21: 15 | N21: =$O$4 -> 387649.47 | O21: =IPMT($O$3/12,G21,$O$2,($O$1)) -> -283523.81 | P21: =N21+O21 -> 104125.66 | S21: 15 | T21: =$U$4 -> 501501.74 | U21: =IPMT($U$3/12,S21,$U$2,($U$1)) -> -339043.22 | V21: =T21+U21 -> 162458.52 | Y21: 15 | Z21: =$AA$4 -> 143286.21 | AA21: =IPMT($AA$3/12,Y21,$AA$2,($AA$1)) -> -96869.492 | AB21: =Z21+AA21 -> 46416.72 | AE21: 15 | AF21: =$AG$4 -> 586008.13 | AG21: =IPMT($AG$3/12,AE21,$AG$2,($AG$1)) -> -268460.3 | AH21: =AF21+AG21 -> 317547.83
A22: 16 | B22: =$C$4 -> 494849.28 | C22: =IPMT($C$3/12,A22,$C$2,($C$1)) -> -402733.16 | D22: =B22+C22 -> 92116.113 | G22: 16 | H22: =$I$4 -> 209110.02 | I22: =IPMT($I$3/12,G22,$I$2,($I$1)) -> -162218.42 | J22: =H22+I22 -> 46891.593 | M22: 16 | N22: =$O$4 -> 387649.47 | O22: =IPMT($O$3/12,G22,$O$2,($O$1)) -> -282916.41 | P22: =N22+O22 -> 104733.06 | S22: 16 | T22: =$U$4 -> 501501.74 | U22: =IPMT($U$3/12,S22,$U$2,($U$1)) -> -338230.93 | V22: =T22+U22 -> 163270.81 | Y22: 16 | Z22: =$AA$4 -> 143286.21 | AA22: =IPMT($AA$3/12,Y22,$AA$2,($AA$1)) -> -96637.409 | AB22: =Z22+AA22 -> 46648.803 | AE22: 16 | AF22: =$AG$4 -> 586008.13 | AG22: =IPMT($AG$3/12,AE22,$AG$2,($AG$1)) -> -266078.69 | AH22: =AF22+AG22 -> 319929.44
A23: 17 | B23: =$C$4 -> 494849.28 | C23: =IPMT($C$3/12,A23,$C$2,($C$1)) -> -402042.29 | D23: =B23+C23 -> 92806.984 | G23: 17 | H23: =$I$4 -> 209110.02 | I23: =IPMT($I$3/12,G23,$I$2,($I$1)) -> -161905.81 | J23: =H23+I23 -> 47204.203 | M23: 17 | N23: =$O$4 -> 387649.47 | O23: =IPMT($O$3/12,G23,$O$2,($O$1)) -> -282305.47 | P23: =N23+O23 -> 105344 | S23: 17 | T23: =$U$4 -> 501501.74 | U23: =IPMT($U$3/12,S23,$U$2,($U$1)) -> -337414.58 | V23: =T23+U23 -> 164087.16 | Y23: 17 | Z23: =$AA$4 -> 143286.21 | AA23: =IPMT($AA$3/12,Y23,$AA$2,($AA$1)) -> -96404.165 | AB23: =Z23+AA23 -> 46882.047 | AE23: 17 | AF23: =$AG$4 -> 586008.13 | AG23: =IPMT($AG$3/12,AE23,$AG$2,($AG$1)) -> -263679.22 | AH23: =AF23+AG23 -> 322328.91
A24: 18 | B24: =$C$4 -> 494849.28 | C24: =IPMT($C$3/12,A24,$C$2,($C$1)) -> -401346.24 | D24: =B24+C24 -> 93503.037 | G24: 18 | H24: =$I$4 -> 209110.02 | I24: =IPMT($I$3/12,G24,$I$2,($I$1)) -> -161591.12 | J24: =H24+I24 -> 47518.898 | M24: 18 | N24: =$O$4 -> 387649.47 | O24: =IPMT($O$3/12,G24,$O$2,($O$1)) -> -281690.96 | P24: =N24+O24 -> 105958.51 | S24: 18 | T24: =$U$4 -> 501501.74 | U24: =IPMT($U$3/12,S24,$U$2,($U$1)) -> -336594.14 | V24: =T24+U24 -> 164907.6 | Y24: 18 | Z24: =$AA$4 -> 143286.21 | AA24: =IPMT($AA$3/12,Y24,$AA$2,($AA$1)) -> -96169.754 | AB24: =Z24+AA24 -> 47116.457 | AE24: 18 | AF24: =$AG$4 -> 586008.13 | AG24: =IPMT($AG$3/12,AE24,$AG$2,($AG$1)) -> -261261.76 | AH24: =AF24+AG24 -> 324746.37
A25: 19 | B25: =$C$4 -> 494849.28 | C25: =IPMT($C$3/12,A25,$C$2,($C$1)) -> -400644.97 | D25: =B25+C25 -> 94204.309 | G25: 19 | H25: =$I$4 -> 209110.02 | I25: =IPMT($I$3/12,G25,$I$2,($I$1)) -> -161274.33 | J25: =H25+I25 -> 47835.691 | M25: 19 | N25: =$O$4 -> 387649.47 | O25: =IPMT($O$3/12,G25,$O$2,($O$1)) -> -281072.87 | P25: =N25+O25 -> 106576.6 | S25: 19 | T25: =$U$4 -> 501501.74 | U25: =IPMT($U$3/12,S25,$U$2,($U$1)) -> -335769.6 | V25: =T25+U25 -> 165732.14 | Y25: 19 | Z25: =$AA$4 -> 143286.21 | AA25: =IPMT($AA$3/12,Y25,$AA$2,($AA$1)) -> -95934.172 | AB25: =Z25+AA25 -> 47352.04 | AE25: 19 | AF25: =$AG$4 -> 586008.13 | AG25: =IPMT($AG$3/12,AE25,$AG$2,($AG$1)) -> -258826.16 | AH25: =AF25+AG25 -> 327181.97
A26: 20 | B26: =$C$4 -> 494849.28 | C26: =IPMT($C$3/12,A26,$C$2,($C$1)) -> -399938.43 | D26: =B26+C26 -> 94910.842 | G26: 20 | H26: =$I$4 -> 209110.02 | I26: =IPMT($I$3/12,G26,$I$2,($I$1)) -> -160955.42 | J26: =H26+I26 -> 48154.595 | M26: 20 | N26: =$O$4 -> 387649.47 | O26: =IPMT($O$3/12,G26,$O$2,($O$1)) -> -280451.17 | P26: =N26+O26 -> 107198.29 | S26: 20 | T26: =$U$4 -> 501501.74 | U26: =IPMT($U$3/12,S26,$U$2,($U$1)) -> -334940.94 | V26: =T26+U26 -> 166560.8 | Y26: 20 | Z26: =$AA$4 -> 143286.21 | AA26: =IPMT($AA$3/12,Y26,$AA$2,($AA$1)) -> -95697.412 | AB26: =Z26+AA26 -> 47588.8 | AE26: 20 | AF26: =$AG$4 -> 586008.13 | AG26: =IPMT($AG$3/12,AE26,$AG$2,($AG$1)) -> -256372.29 | AH26: =AF26+AG26 -> 329635.84
A27: 21 | B27: =$C$4 -> 494849.28 | C27: =IPMT($C$3/12,A27,$C$2,($C$1)) -> -399226.6 | D27: =B27+C27 -> 95622.673 | G27: 21 | H27: =$I$4 -> 209110.02 | I27: =IPMT($I$3/12,G27,$I$2,($I$1)) -> -160634.39 | J27: =H27+I27 -> 48475.626 | M27: 21 | N27: =$O$4 -> 387649.47 | O27: =IPMT($O$3/12,G27,$O$2,($O$1)) -> -279825.85 | P27: =N27+O27 -> 107823.62 | S27: 21 | T27: =$U$4 -> 501501.74 | U27: =IPMT($U$3/12,S27,$U$2,($U$1)) -> -334108.14 | V27: =T27+U27 -> 167393.6 | Y27: 21 | Z27: =$AA$4 -> 143286.21 | AA27: =IPMT($AA$3/12,Y27,$AA$2,($AA$1)) -> -95459.468 | AB27: =Z27+AA27 -> 47826.744 | AE27: 21 | AF27: =$AG$4 -> 586008.13 | AG27: =IPMT($AG$3/12,AE27,$AG$2,($AG$1)) -> -253900.02 | AH27: =AF27+AG27 -> 332108.11
A28: 22 | B28: =$C$4 -> 494849.28 | C28: =IPMT($C$3/12,A28,$C$2,($C$1)) -> -398509.43 | D28: =B28+C28 -> 96339.843 | G28: 22 | H28: =$I$4 -> 209110.02 | I28: =IPMT($I$3/12,G28,$I$2,($I$1)) -> -160311.22 | J28: =H28+I28 -> 48798.797 | M28: 22 | N28: =$O$4 -> 387649.47 | O28: =IPMT($O$3/12,G28,$O$2,($O$1)) -> -279196.88 | P28: =N28+O28 -> 108452.59 | S28: 22 | T28: =$U$4 -> 501501.74 | U28: =IPMT($U$3/12,S28,$U$2,($U$1)) -> -333271.17 | V28: =T28+U28 -> 168230.57 | Y28: 22 | Z28: =$AA$4 -> 143286.21 | AA28: =IPMT($AA$3/12,Y28,$AA$2,($AA$1)) -> -95220.334 | AB28: =Z28+AA28 -> 48065.878 | AE28: 22 | AF28: =$AG$4 -> 586008.13 | AG28: =IPMT($AG$3/12,AE28,$AG$2,($AG$1)) -> -251409.21 | AH28: =AF28+AG28 -> 334598.92
A29: 23 | B29: =$C$4 -> 494849.28 | C29: =IPMT($C$3/12,A29,$C$2,($C$1)) -> -397786.88 | D29: =B29+C29 -> 97062.392 | G29: 23 | H29: =$I$4 -> 209110.02 | I29: =IPMT($I$3/12,G29,$I$2,($I$1)) -> -159985.9 | J29: =H29+I29 -> 49124.122 | M29: 23 | N29: =$O$4 -> 387649.47 | O29: =IPMT($O$3/12,G29,$O$2,($O$1)) -> -278564.24 | P29: =N29+O29 -> 109085.23 | S29: 23 | T29: =$U$4 -> 501501.74 | U29: =IPMT($U$3/12,S29,$U$2,($U$1)) -> -332430.02 | V29: =T29+U29 -> 169071.72 | Y29: 23 | Z29: =$AA$4 -> 143286.21 | AA29: =IPMT($AA$3/12,Y29,$AA$2,($AA$1)) -> -94980.005 | AB29: =Z29+AA29 -> 48306.207 | AE29: 23 | AF29: =$AG$4 -> 586008.13 | AG29: =IPMT($AG$3/12,AE29,$AG$2,($AG$1)) -> -248899.72 | AH29: =AF29+AG29 -> 337108.41
A30: 24 | B30: =$C$4 -> 494849.28 | C30: =IPMT($C$3/12,A30,$C$2,($C$1)) -> -397058.92 | D30: =B30+C30 -> 97790.36 | E30: =SUM(C19:C30) -> -4811580.4 | G30: 24 | H30: =$I$4 -> 209110.02 | I30: =IPMT($I$3/12,G30,$I$2,($I$1)) -> -159658.4 | J30: =H30+I30 -> 49451.616 | K30: =SUM(I19:I30) -> -1937045.3 | M30: 24 | N30: =$O$4 -> 387649.47 | O30: =IPMT($O$3/12,G30,$O$2,($O$1)) -> -277927.91 | P30: =N30+O30 -> 109721.56 | Q30: =SUM(O19:O30) -> -3376331.3 | S30: 24 | T30: =$U$4 -> 501501.74 | U30: =IPMT($U$3/12,S30,$U$2,($U$1)) -> -331584.66 | V30: =T30+U30 -> 169917.08 | W30: =SUM(U19:U30) -> -4033894.6 | Y30: 24 | Z30: =$AA$4 -> 143286.21 | AA30: =IPMT($AA$3/12,Y30,$AA$2,($AA$1)) -> -94738.474 | AB30: =Z30+AA30 -> 48547.738 | AC30: =SUM(AA19:AA30) -> -1152541.3 | AE30: 24 | AF30: =$AG$4 -> 586008.13 | AG30: =IPMT($AG$3/12,AE30,$AG$2,($AG$1)) -> -246371.41 | AH30: =AF30+AG30 -> 339636.72 | AI30: =SUM(AG19:AG30) -> -3119253.4
A31: 25 | B31: =$C$4 -> 494849.28 | C31: =IPMT($C$3/12,A31,$C$2,($C$1)) -> -396325.49 | D31: =B31+C31 -> 98523.788 | E31: =SUM(D19:D30) -> 1126610.9 | G31: 25 | H31: =$I$4 -> 209110.02 | I31: =IPMT($I$3/12,G31,$I$2,($I$1)) -> -159328.72 | J31: =H31+I31 -> 49781.294 | K31: =SUM(J19:J30) -> 572274.89 | M31: 25 | N31: =$O$4 -> 387649.47 | O31: =IPMT($O$3/12,G31,$O$2,($O$1)) -> -277287.87 | P31: =N31+O31 -> 110361.6 | Q31: =SUM(P19:P30) -> 1275462.3 | S31: 25 | T31: =$U$4 -> 501501.74 | U31: =IPMT($U$3/12,S31,$U$2,($U$1)) -> -330735.07 | V31: =T31+U31 -> 170766.67 | W31: =SUM(V19:V30) -> 1984126.3 | Y31: 25 | Z31: =$AA$4 -> 143286.21 | AA31: =IPMT($AA$3/12,Y31,$AA$2,($AA$1)) -> -94495.735 | AB31: =Z31+AA31 -> 48790.477 | AC31: =SUM(AB19:AB30) -> 566893.23 | AE31: 25 | AF31: =$AG$4 -> 586008.13 | AG31: =IPMT($AG$3/12,AE31,$AG$2,($AG$1)) -> -243824.13 | AH31: =AF31+AG31 -> 342184 | AI31: =SUM(AH19:AH30) -> 3912844.1
A32: 26 | B32: =$C$4 -> 494849.28 | C32: =IPMT($C$3/12,A32,$C$2,($C$1)) -> -395586.56 | D32: =B32+C32 -> 99262.716 | E32: =E31-E30 -> 5938191.3 | G32: 26 | H32: =$I$4 -> 209110.02 | I32: =IPMT($I$3/12,G32,$I$2,($I$1)) -> -158996.85 | J32: =H32+I32 -> 50113.169 | K32: =K31-K30 -> 2509320.2 | M32: 26 | N32: =$O$4 -> 387649.47 | O32: =IPMT($O$3/12,G32,$O$2,($O$1)) -> -276644.09 | P32: =N32+O32 -> 111005.38 | S32: 26 | T32: =$U$4 -> 501501.74 | U32: =IPMT($U$3/12,S32,$U$2,($U$1)) -> -329881.24 | V32: =T32+U32 -> 171620.5 | Y32: 26 | Z32: =$AA$4 -> 143286.21 | AA32: =IPMT($AA$3/12,Y32,$AA$2,($AA$1)) -> -94251.783 | AB32: =Z32+AA32 -> 49034.429 | AE32: 26 | AF32: =$AG$4 -> 586008.13 | AG32: =IPMT($AG$3/12,AE32,$AG$2,($AG$1)) -> -241257.75 | AH32: =AF32+AG32 -> 344750.38
A33: 27 | B33: =$C$4 -> 494849.28 | C33: =IPMT($C$3/12,A33,$C$2,($C$1)) -> -394842.09 | D33: =B33+C33 -> 100007.19 | G33: 27 | H33: =$I$4 -> 209110.02 | I33: =IPMT($I$3/12,G33,$I$2,($I$1)) -> -158662.76 | J33: =H33+I33 -> 50447.257 | M33: 27 | N33: =$O$4 -> 387649.47 | O33: =IPMT($O$3/12,G33,$O$2,($O$1)) -> -275996.56 | P33: =N33+O33 -> 111652.91 | S33: 27 | T33: =$U$4 -> 501501.74 | U33: =IPMT($U$3/12,S33,$U$2,($U$1)) -> -329023.14 | V33: =T33+U33 -> 172478.6 | Y33: 27 | Z33: =$AA$4 -> 143286.21 | AA33: =IPMT($AA$3/12,Y33,$AA$2,($AA$1)) -> -94006.61 | AB33: =Z33+AA33 -> 49279.601 | AE33: 27 | AF33: =$AG$4 -> 586008.13 | AG33: =IPMT($AG$3/12,AE33,$AG$2,($AG$1)) -> -238672.13 | AH33: =AF33+AG33 -> 347336.01
A34: 28 | B34: =$C$4 -> 494849.28 | C34: =IPMT($C$3/12,A34,$C$2,($C$1)) -> -394092.04 | D34: =B34+C34 -> 100757.24 | G34: 28 | H34: =$I$4 -> 209110.02 | I34: =IPMT($I$3/12,G34,$I$2,($I$1)) -> -158326.45 | J34: =H34+I34 -> 50783.572 | M34: 28 | N34: =$O$4 -> 387649.47 | O34: =IPMT($O$3/12,G34,$O$2,($O$1)) -> -275345.25 | P34: =N34+O34 -> 112304.22 | S34: 28 | T34: =$U$4 -> 501501.74 | U34: =IPMT($U$3/12,S34,$U$2,($U$1)) -> -328160.74 | V34: =T34+U34 -> 173341 | Y34: 28 | Z34: =$AA$4 -> 143286.21 | AA34: =IPMT($AA$3/12,Y34,$AA$2,($AA$1)) -> -93760.212 | AB34: =Z34+AA34 -> 49525.999 | AE34: 28 | AF34: =$AG$4 -> 586008.13 | AG34: =IPMT($AG$3/12,AE34,$AG$2,($AG$1)) -> -236067.11 | AH34: =AF34+AG34 -> 349941.03
A35: 29 | B35: =$C$4 -> 494849.28 | C35: =IPMT($C$3/12,A35,$C$2,($C$1)) -> -393336.36 | D35: =B35+C35 -> 101512.92 | G35: 29 | H35: =$I$4 -> 209110.02 | I35: =IPMT($I$3/12,G35,$I$2,($I$1)) -> -157987.89 | J35: =H35+I35 -> 51122.129 | M35: 29 | N35: =$O$4 -> 387649.47 | O35: =IPMT($O$3/12,G35,$O$2,($O$1)) -> -274690.14 | P35: =N35+O35 -> 112959.33 | S35: 29 | T35: =$U$4 -> 501501.74 | U35: =IPMT($U$3/12,S35,$U$2,($U$1)) -> -327294.04 | V35: =T35+U35 -> 174207.7 | Y35: 29 | Z35: =$AA$4 -> 143286.21 | AA35: =IPMT($AA$3/12,Y35,$AA$2,($AA$1)) -> -93512.582 | AB35: =Z35+AA35 -> 49773.629 | AE35: 29 | AF35: =$AG$4 -> 586008.13 | AG35: =IPMT($AG$3/12,AE35,$AG$2,($AG$1)) -> -233442.55 | AH35: =AF35+AG35 -> 352565.58
A36: 30 | B36: =$C$4 -> 494849.28 | C36: =IPMT($C$3/12,A36,$C$2,($C$1)) -> -392575.01 | D36: =B36+C36 -> 102274.27 | G36: 30 | H36: =$I$4 -> 209110.02 | I36: =IPMT($I$3/12,G36,$I$2,($I$1)) -> -157647.07 | J36: =H36+I36 -> 51462.943 | M36: 30 | N36: =$O$4 -> 387649.47 | O36: =IPMT($O$3/12,G36,$O$2,($O$1)) -> -274031.21 | P36: =N36+O36 -> 113618.26 | S36: 30 | T36: =$U$4 -> 501501.74 | U36: =IPMT($U$3/12,S36,$U$2,($U$1)) -> -326423 | V36: =T36+U36 -> 175078.74 | Y36: 30 | Z36: =$AA$4 -> 143286.21 | AA36: =IPMT($AA$3/12,Y36,$AA$2,($AA$1)) -> -93263.714 | AB36: =Z36+AA36 -> 50022.497 | AE36: 30 | AF36: =$AG$4 -> 586008.13 | AG36: =IPMT($AG$3/12,AE36,$AG$2,($AG$1)) -> -230798.31 | AH36: =AF36+AG36 -> 355209.82
A37: 31 | B37: =$C$4 -> 494849.28 | C37: =IPMT($C$3/12,A37,$C$2,($C$1)) -> -391807.95 | D37: =B37+C37 -> 103041.32 | G37: 31 | H37: =$I$4 -> 209110.02 | I37: =IPMT($I$3/12,G37,$I$2,($I$1)) -> -157303.99 | J37: =H37+I37 -> 51806.029 | M37: 31 | N37: =$O$4 -> 387649.47 | O37: =IPMT($O$3/12,G37,$O$2,($O$1)) -> -273368.44 | P37: =N37+O37 -> 114281.03 | S37: 31 | T37: =$U$4 -> 501501.74 | U37: =IPMT($U$3/12,S37,$U$2,($U$1)) -> -325547.61 | V37: =T37+U37 -> 175954.13 | Y37: 31 | Z37: =$AA$4 -> 143286.21 | AA37: =IPMT($AA$3/12,Y37,$AA$2,($AA$1)) -> -93013.602 | AB37: =Z37+AA37 -> 50272.61 | AE37: 31 | AF37: =$AG$4 -> 586008.13 | AG37: =IPMT($AG$3/12,AE37,$AG$2,($AG$1)) -> -228134.23 | AH37: =AF37+AG37 -> 357873.9
A38: 32 | B38: =$C$4 -> 494849.28 | C38: =IPMT($C$3/12,A38,$C$2,($C$1)) -> -391035.14 | D38: =B38+C38 -> 103814.13 | G38: 32 | H38: =$I$4 -> 209110.02 | I38: =IPMT($I$3/12,G38,$I$2,($I$1)) -> -156958.61 | J38: =H38+I38 -> 52151.403 | M38: 32 | N38: =$O$4 -> 387649.47 | O38: =IPMT($O$3/12,G38,$O$2,($O$1)) -> -272701.8 | P38: =N38+O38 -> 114947.67 | S38: 32 | T38: =$U$4 -> 501501.74 | U38: =IPMT($U$3/12,S38,$U$2,($U$1)) -> -324667.84 | V38: =T38+U38 -> 176833.91 | Y38: 32 | Z38: =$AA$4 -> 143286.21 | AA38: =IPMT($AA$3/12,Y38,$AA$2,($AA$1)) -> -92762.239 | AB38: =Z38+AA38 -> 50523.973 | AE38: 32 | AF38: =$AG$4 -> 586008.13 | AG38: =IPMT($AG$3/12,AE38,$AG$2,($AG$1)) -> -225450.18 | AH38: =AF38+AG38 -> 360557.95
A39: 33 | B39: =$C$4 -> 494849.28 | C39: =IPMT($C$3/12,A39,$C$2,($C$1)) -> -390256.54 | D39: =B39+C39 -> 104592.74 | G39: 33 | H39: =$I$4 -> 209110.02 | I39: =IPMT($I$3/12,G39,$I$2,($I$1)) -> -156610.94 | J39: =H39+I39 -> 52499.079 | M39: 33 | N39: =$O$4 -> 387649.47 | O39: =IPMT($O$3/12,G39,$O$2,($O$1)) -> -272031.27 | P39: =N39+O39 -> 115618.2 | S39: 33 | T39: =$U$4 -> 501501.74 | U39: =IPMT($U$3/12,S39,$U$2,($U$1)) -> -323783.67 | V39: =T39+U39 -> 177718.07 | Y39: 33 | Z39: =$AA$4 -> 143286.21 | AA39: =IPMT($AA$3/12,Y39,$AA$2,($AA$1)) -> -92509.619 | AB39: =Z39+AA39 -> 50776.593 | AE39: 33 | AF39: =$AG$4 -> 586008.13 | AG39: =IPMT($AG$3/12,AE39,$AG$2,($AG$1)) -> -222745.99 | AH39: =AF39+AG39 -> 363262.14
A40: 34 | B40: =$C$4 -> 494849.28 | C40: =IPMT($C$3/12,A40,$C$2,($C$1)) -> -389472.09 | D40: =B40+C40 -> 105377.18 | G40: 34 | H40: =$I$4 -> 209110.02 | I40: =IPMT($I$3/12,G40,$I$2,($I$1)) -> -156260.94 | J40: =H40+I40 -> 52849.073 | M40: 34 | N40: =$O$4 -> 387649.47 | O40: =IPMT($O$3/12,G40,$O$2,($O$1)) -> -271356.83 | P40: =N40+O40 -> 116292.64 | S40: 34 | T40: =$U$4 -> 501501.74 | U40: =IPMT($U$3/12,S40,$U$2,($U$1)) -> -322895.08 | V40: =T40+U40 -> 178606.67 | Y40: 34 | Z40: =$AA$4 -> 143286.21 | AA40: =IPMT($AA$3/12,Y40,$AA$2,($AA$1)) -> -92255.736 | AB40: =Z40+AA40 -> 51030.476 | AE40: 34 | AF40: =$AG$4 -> 586008.13 | AG40: =IPMT($AG$3/12,AE40,$AG$2,($AG$1)) -> -220021.53 | AH40: =AF40+AG40 -> 365986.6
A41: 35 | B41: =$C$4 -> 494849.28 | C41: =IPMT($C$3/12,A41,$C$2,($C$1)) -> -388681.76 | D41: =B41+C41 -> 106167.51 | G41: 35 | H41: =$I$4 -> 209110.02 | I41: =IPMT($I$3/12,G41,$I$2,($I$1)) -> -155908.62 | J41: =H41+I41 -> 53201.4 | M41: 35 | N41: =$O$4 -> 387649.47 | O41: =IPMT($O$3/12,G41,$O$2,($O$1)) -> -270678.46 | P41: =N41+O41 -> 116971.01 | S41: 35 | T41: =$U$4 -> 501501.74 | U41: =IPMT($U$3/12,S41,$U$2,($U$1)) -> -322002.04 | V41: =T41+U41 -> 179499.7 | Y41: 35 | Z41: =$AA$4 -> 143286.21 | AA41: =IPMT($AA$3/12,Y41,$AA$2,($AA$1)) -> -92000.584 | AB41: =Z41+AA41 -> 51285.628 | AE41: 35 | AF41: =$AG$4 -> 586008.13 | AG41: =IPMT($AG$3/12,AE41,$AG$2,($AG$1)) -> -217276.63 | AH41: =AF41+AG41 -> 368731.5
A42: 36 | B42: =$C$4 -> 494849.28 | C42: =IPMT($C$3/12,A42,$C$2,($C$1)) -> -387885.51 | D42: =B42+C42 -> 106963.77 | E42: =SUM(C31:C42) -> -4705896.5 | G42: 36 | H42: =$I$4 -> 209110.02 | I42: =IPMT($I$3/12,G42,$I$2,($I$1)) -> -155553.94 | J42: =H42+I42 -> 53556.076 | K42: =SUM(I31:I42) -> -1889546.8 | M42: 36 | N42: =$O$4 -> 387649.47 | O42: =IPMT($O$3/12,G42,$O$2,($O$1)) -> -269996.13 | P42: =N42+O42 -> 117653.34 | Q42: =SUM(O31:O42) -> -3284128 | S42: 36 | T42: =$U$4 -> 501501.74 | U42: =IPMT($U$3/12,S42,$U$2,($U$1)) -> -321104.54 | V42: =T42+U42 -> 180397.2 | W42: =SUM(U31:U42) -> -3911518 | Y42: 36 | Z42: =$AA$4 -> 143286.21 | AA42: =IPMT($AA$3/12,Y42,$AA$2,($AA$1)) -> -91744.155 | AB42: =Z42+AA42 -> 51542.056 | AC42: =SUM(AA31:AA42) -> -1117576.6 | AE42: 36 | AF42: =$AG$4 -> 586008.13 | AG42: =IPMT($AG$3/12,AE42,$AG$2,($AG$1)) -> -214511.14 | AH42: =AF42+AG42 -> 371496.99 | AI42: =SUM(AG31:AG42) -> -2752201.7
A43: 37 | B43: =$C$4 -> 494849.28 | C43: =IPMT($C$3/12,A43,$C$2,($C$1)) -> -387083.28 | D43: =B43+C43 -> 107766 | E43: =SUM(D31:D42) -> 1232294.8 | G43: 37 | H43: =$I$4 -> 209110.02 | I43: =IPMT($I$3/12,G43,$I$2,($I$1)) -> -155196.9 | J43: =H43+I43 -> 53913.117 | K43: =SUM(J31:J42) -> 619773.42 | M43: 37 | N43: =$O$4 -> 387649.47 | O43: =IPMT($O$3/12,G43,$O$2,($O$1)) -> -269309.82 | P43: =N43+O43 -> 118339.65 | Q43: =SUM(P31:P42) -> 1367665.6 | S43: 37 | T43: =$U$4 -> 501501.74 | U43: =IPMT($U$3/12,S43,$U$2,($U$1)) -> -320202.56 | V43: =T43+U43 -> 181299.18 | W43: =SUM(V31:V42) -> 2106502.9 | Y43: 37 | Z43: =$AA$4 -> 143286.21 | AA43: =IPMT($AA$3/12,Y43,$AA$2,($AA$1)) -> -91486.445 | AB43: =Z43+AA43 -> 51799.767 | AC43: =SUM(AB31:AB42) -> 601857.97 | AE43: 37 | AF43: =$AG$4 -> 586008.13 | AG43: =IPMT($AG$3/12,AE43,$AG$2,($AG$1)) -> -211724.91 | AH43: =AF43+AG43 -> 374283.22 | AI43: =SUM(AH31:AH42) -> 4279895.9
A44: 38 | B44: =$C$4 -> 494849.28 | C44: =IPMT($C$3/12,A44,$C$2,($C$1)) -> -386275.03 | D44: =B44+C44 -> 108574.24 | E44: =E43-E42 -> 5938191.3 | G44: 38 | H44: =$I$4 -> 209110.02 | I44: =IPMT($I$3/12,G44,$I$2,($I$1)) -> -154837.48 | J44: =H44+I44 -> 54272.537 | K44: =K43-K42 -> 2509320.2 | M44: 38 | N44: =$O$4 -> 387649.47 | O44: =IPMT($O$3/12,G44,$O$2,($O$1)) -> -268619.5 | P44: =N44+O44 -> 119029.97 | S44: 38 | T44: =$U$4 -> 501501.74 | U44: =IPMT($U$3/12,S44,$U$2,($U$1)) -> -319296.06 | V44: =T44+U44 -> 182205.68 | Y44: 38 | Z44: =$AA$4 -> 143286.21 | AA44: =IPMT($AA$3/12,Y44,$AA$2,($AA$1)) -> -91227.446 | AB44: =Z44+AA44 -> 52058.765 | AE44: 38 | AF44: =$AG$4 -> 586008.13 | AG44: =IPMT($AG$3/12,AE44,$AG$2,($AG$1)) -> -208917.79 | AH44: =AF44+AG44 -> 377090.34
A45: 39 | B45: =$C$4 -> 494849.28 | C45: =IPMT($C$3/12,A45,$C$2,($C$1)) -> -385460.73 | D45: =B45+C45 -> 109388.55 | G45: 39 | H45: =$I$4 -> 209110.02 | I45: =IPMT($I$3/12,G45,$I$2,($I$1)) -> -154475.66 | J45: =H45+I45 -> 54634.354 | M45: 39 | N45: =$O$4 -> 387649.47 | O45: =IPMT($O$3/12,G45,$O$2,($O$1)) -> -267925.16 | P45: =N45+O45 -> 119724.31 | S45: 39 | T45: =$U$4 -> 501501.74 | U45: =IPMT($U$3/12,S45,$U$2,($U$1)) -> -318385.03 | V45: =T45+U45 -> 183116.71 | Y45: 39 | Z45: =$AA$4 -> 143286.21 | AA45: =IPMT($AA$3/12,Y45,$AA$2,($AA$1)) -> -90967.153 | AB45: =Z45+AA45 -> 52319.059 | AE45: 39 | AF45: =$AG$4 -> 586008.13 | AG45: =IPMT($AG$3/12,AE45,$AG$2,($AG$1)) -> -206089.61 | AH45: =AF45+AG45 -> 379918.52
A46: 40 | B46: =$C$4 -> 494849.28 | C46: =IPMT($C$3/12,A46,$C$2,($C$1)) -> -384640.31 | D46: =B46+C46 -> 110208.96 | G46: 40 | H46: =$I$4 -> 209110.02 | I46: =IPMT($I$3/12,G46,$I$2,($I$1)) -> -154111.43 | J46: =H46+I46 -> 54998.583 | M46: 40 | N46: =$O$4 -> 387649.47 | O46: =IPMT($O$3/12,G46,$O$2,($O$1)) -> -267226.77 | P46: =N46+O46 -> 120422.7 | S46: 40 | T46: =$U$4 -> 501501.74 | U46: =IPMT($U$3/12,S46,$U$2,($U$1)) -> -317469.45 | V46: =T46+U46 -> 184032.29 | Y46: 40 | Z46: =$AA$4 -> 143286.21 | AA46: =IPMT($AA$3/12,Y46,$AA$2,($AA$1)) -> -90705.557 | AB46: =Z46+AA46 -> 52580.654 | AE46: 40 | AF46: =$AG$4 -> 586008.13 | AG46: =IPMT($AG$3/12,AE46,$AG$2,($AG$1)) -> -203240.22 | AH46: =AF46+AG46 -> 382767.91
A47: 41 | B47: =$C$4 -> 494849.28 | C47: =IPMT($C$3/12,A47,$C$2,($C$1)) -> -383813.74 | D47: =B47+C47 -> 111035.53 | G47: 41 | H47: =$I$4 -> 209110.02 | I47: =IPMT($I$3/12,G47,$I$2,($I$1)) -> -153744.78 | J47: =H47+I47 -> 55365.24 | M47: 41 | N47: =$O$4 -> 387649.47 | O47: =IPMT($O$3/12,G47,$O$2,($O$1)) -> -266524.3 | P47: =N47+O47 -> 121125.17 | S47: 41 | T47: =$U$4 -> 501501.74 | U47: =IPMT($U$3/12,S47,$U$2,($U$1)) -> -316549.29 | V47: =T47+U47 -> 184952.45 | Y47: 41 | Z47: =$AA$4 -> 143286.21 | AA47: =IPMT($AA$3/12,Y47,$AA$2,($AA$1)) -> -90442.654 | AB47: =Z47+AA47 -> 52843.558 | AE47: 41 | AF47: =$AG$4 -> 586008.13 | AG47: =IPMT($AG$3/12,AE47,$AG$2,($AG$1)) -> -200369.46 | AH47: =AF47+AG47 -> 385638.67
A48: 42 | B48: =$C$4 -> 494849.28 | C48: =IPMT($C$3/12,A48,$C$2,($C$1)) -> -382980.98 | D48: =B48+C48 -> 111868.3 | G48: 42 | H48: =$I$4 -> 209110.02 | I48: =IPMT($I$3/12,G48,$I$2,($I$1)) -> -153375.68 | J48: =H48+I48 -> 55734.342 | M48: 42 | N48: =$O$4 -> 387649.47 | O48: =IPMT($O$3/12,G48,$O$2,($O$1)) -> -265817.74 | P48: =N48+O48 -> 121831.73 | S48: 42 | T48: =$U$4 -> 501501.74 | U48: =IPMT($U$3/12,S48,$U$2,($U$1)) -> -315624.53 | V48: =T48+U48 -> 185877.21 | Y48: 42 | Z48: =$AA$4 -> 143286.21 | AA48: =IPMT($AA$3/12,Y48,$AA$2,($AA$1)) -> -90178.436 | AB48: =Z48+AA48 -> 53107.776 | AE48: 42 | AF48: =$AG$4 -> 586008.13 | AG48: =IPMT($AG$3/12,AE48,$AG$2,($AG$1)) -> -197477.17 | AH48: =AF48+AG48 -> 388530.96
A49: 43 | B49: =$C$4 -> 494849.28 | C49: =IPMT($C$3/12,A49,$C$2,($C$1)) -> -382141.97 | D49: =B49+C49 -> 112707.31 | G49: 43 | H49: =$I$4 -> 209110.02 | I49: =IPMT($I$3/12,G49,$I$2,($I$1)) -> -153004.11 | J49: =H49+I49 -> 56105.904 | M49: 43 | N49: =$O$4 -> 387649.47 | O49: =IPMT($O$3/12,G49,$O$2,($O$1)) -> -265107.05 | P49: =N49+O49 -> 122542.41 | S49: 43 | T49: =$U$4 -> 501501.74 | U49: =IPMT($U$3/12,S49,$U$2,($U$1)) -> -314695.14 | V49: =T49+U49 -> 186806.6 | Y49: 43 | Z49: =$AA$4 -> 143286.21 | AA49: =IPMT($AA$3/12,Y49,$AA$2,($AA$1)) -> -89912.897 | AB49: =Z49+AA49 -> 53373.314 | AE49: 43 | AF49: =$AG$4 -> 586008.13 | AG49: =IPMT($AG$3/12,AE49,$AG$2,($AG$1)) -> -194563.19 | AH49: =AF49+AG49 -> 391444.94
A50: 44 | B50: =$C$4 -> 494849.28 | C50: =IPMT($C$3/12,A50,$C$2,($C$1)) -> -381296.66 | D50: =B50+C50 -> 113552.62 | G50: 44 | H50: =$I$4 -> 209110.02 | I50: =IPMT($I$3/12,G50,$I$2,($I$1)) -> -152630.07 | J50: =H50+I50 -> 56479.944 | M50: 44 | N50: =$O$4 -> 387649.47 | O50: =IPMT($O$3/12,G50,$O$2,($O$1)) -> -264392.22 | P50: =N50+O50 -> 123257.24 | S50: 44 | T50: =$U$4 -> 501501.74 | U50: =IPMT($U$3/12,S50,$U$2,($U$1)) -> -313761.11 | V50: =T50+U50 -> 187740.63 | Y50: 44 | Z50: =$AA$4 -> 143286.21 | AA50: =IPMT($AA$3/12,Y50,$AA$2,($AA$1)) -> -89646.031 | AB50: =Z50+AA50 -> 53640.181 | AE50: 44 | AF50: =$AG$4 -> 586008.13 | AG50: =IPMT($AG$3/12,AE50,$AG$2,($AG$1)) -> -191627.36 | AH50: =AF50+AG50 -> 394380.78
A51: 45 | B51: =$C$4 -> 494849.28 | C51: =IPMT($C$3/12,A51,$C$2,($C$1)) -> -380445.02 | D51: =B51+C51 -> 114404.26 | G51: 45 | H51: =$I$4 -> 209110.02 | I51: =IPMT($I$3/12,G51,$I$2,($I$1)) -> -152253.54 | J51: =H51+I51 -> 56856.477 | M51: 45 | N51: =$O$4 -> 387649.47 | O51: =IPMT($O$3/12,G51,$O$2,($O$1)) -> -263673.22 | P51: =N51+O51 -> 123976.25 | S51: 45 | T51: =$U$4 -> 501501.74 | U51: =IPMT($U$3/12,S51,$U$2,($U$1)) -> -312822.4 | V51: =T51+U51 -> 188679.34 | Y51: 45 | Z51: =$AA$4 -> 143286.21 | AA51: =IPMT($AA$3/12,Y51,$AA$2,($AA$1)) -> -89377.83 | AB51: =Z51+AA51 -> 53908.382 | AE51: 45 | AF51: =$AG$4 -> 586008.13 | AG51: =IPMT($AG$3/12,AE51,$AG$2,($AG$1)) -> -188669.5 | AH51: =AF51+AG51 -> 397338.63
A52: 46 | B52: =$C$4 -> 494849.28 | C52: =IPMT($C$3/12,A52,$C$2,($C$1)) -> -379586.98 | D52: =B52+C52 -> 115262.29 | G52: 46 | H52: =$I$4 -> 209110.02 | I52: =IPMT($I$3/12,G52,$I$2,($I$1)) -> -151874.5 | J52: =H52+I52 -> 57235.52 | M52: 46 | N52: =$O$4 -> 387649.47 | O52: =IPMT($O$3/12,G52,$O$2,($O$1)) -> -262950.03 | P52: =N52+O52 -> 124699.44 | S52: 46 | T52: =$U$4 -> 501501.74 | U52: =IPMT($U$3/12,S52,$U$2,($U$1)) -> -311879.01 | V52: =T52+U52 -> 189622.73 | Y52: 46 | Z52: =$AA$4 -> 143286.21 | AA52: =IPMT($AA$3/12,Y52,$AA$2,($AA$1)) -> -89108.288 | AB52: =Z52+AA52 -> 54177.924 | AE52: 46 | AF52: =$AG$4 -> 586008.13 | AG52: =IPMT($AG$3/12,AE52,$AG$2,($AG$1)) -> -185689.46 | AH52: =AF52+AG52 -> 400318.67
A53: 47 | B53: =$C$4 -> 494849.28 | C53: =IPMT($C$3/12,A53,$C$2,($C$1)) -> -378722.52 | D53: =B53+C53 -> 116126.76 | G53: 47 | H53: =$I$4 -> 209110.02 | I53: =IPMT($I$3/12,G53,$I$2,($I$1)) -> -151492.93 | J53: =H53+I53 -> 57617.09 | M53: 47 | N53: =$O$4 -> 387649.47 | O53: =IPMT($O$3/12,G53,$O$2,($O$1)) -> -262222.61 | P53: =N53+O53 -> 125426.85 | S53: 47 | T53: =$U$4 -> 501501.74 | U53: =IPMT($U$3/12,S53,$U$2,($U$1)) -> -310930.89 | V53: =T53+U53 -> 190570.85 | Y53: 47 | Z53: =$AA$4 -> 143286.21 | AA53: =IPMT($AA$3/12,Y53,$AA$2,($AA$1)) -> -88837.398 | AB53: =Z53+AA53 -> 54448.813 | AE53: 47 | AF53: =$AG$4 -> 586008.13 | AG53: =IPMT($AG$3/12,AE53,$AG$2,($AG$1)) -> -182687.07 | AH53: =AF53+AG53 -> 403321.06
A54: 48 | B54: =$C$4 -> 494849.28 | C54: =IPMT($C$3/12,A54,$C$2,($C$1)) -> -377851.57 | D54: =B54+C54 -> 116997.71 | E54: =SUM(C43:C54) -> -4590298.8 | G54: 48 | H54: =$I$4 -> 209110.02 | I54: =IPMT($I$3/12,G54,$I$2,($I$1)) -> -151108.81 | J54: =H54+I54 -> 58001.204 | K54: =SUM(I43:I54) -> -1838105.9 | M54: 48 | N54: =$O$4 -> 387649.47 | O54: =IPMT($O$3/12,G54,$O$2,($O$1)) -> -261490.96 | P54: =N54+O54 -> 126158.51 | Q54: =SUM(O43:O54) -> -3185259.4 | S54: 48 | T54: =$U$4 -> 501501.74 | U54: =IPMT($U$3/12,S54,$U$2,($U$1)) -> -309978.04 | V54: =T54+U54 -> 191523.7 | W54: =SUM(U43:U54) -> -3781593.5 | Y54: 48 | Z54: =$AA$4 -> 143286.21 | AA54: =IPMT($AA$3/12,Y54,$AA$2,($AA$1)) -> -88565.154 | AB54: =Z54+AA54 -> 54721.057 | AC54: =SUM(AA43:AA54) -> -1080455.3 | AE54: 48 | AF54: =$AG$4 -> 586008.13 | AG54: =IPMT($AG$3/12,AE54,$AG$2,($AG$1)) -> -179662.16 | AH54: =AF54+AG54 -> 406345.97 | AI54: =SUM(AG43:AG54) -> -2350717.9
A55: 49 | B55: =$C$4 -> 494849.28 | C55: =IPMT($C$3/12,A55,$C$2,($C$1)) -> -376974.08 | D55: =B55+C55 -> 117875.19 | E55: =SUM(D43:D54) -> 1347892.5 | G55: 49 | H55: =$I$4 -> 209110.02 | I55: =IPMT($I$3/12,G55,$I$2,($I$1)) -> -150722.14 | J55: =H55+I55 -> 58387.879 | K55: =SUM(J43:J54) -> 671214.31 | M55: 49 | N55: =$O$4 -> 387649.47 | O55: =IPMT($O$3/12,G55,$O$2,($O$1)) -> -260755.03 | P55: =N55+O55 -> 126894.43 | Q55: =SUM(P43:P54) -> 1466534.2 | S55: 49 | T55: =$U$4 -> 501501.74 | U55: =IPMT($U$3/12,S55,$U$2,($U$1)) -> -309020.42 | V55: =T55+U55 -> 192481.32 | W55: =SUM(V43:V54) -> 2236427.4 | Y55: 49 | Z55: =$AA$4 -> 143286.21 | AA55: =IPMT($AA$3/12,Y55,$AA$2,($AA$1)) -> -88291.549 | AB55: =Z55+AA55 -> 54994.663 | AC55: =SUM(AB43:AB54) -> 638979.25 | AE55: 49 | AF55: =$AG$4 -> 586008.13 | AG55: =IPMT($AG$3/12,AE55,$AG$2,($AG$1)) -> -176614.57 | AH55: =AF55+AG55 -> 409393.56 | AI55: =SUM(AH43:AH54) -> 4681379.7
A56: 50 | B56: =$C$4 -> 494849.28 | C56: =IPMT($C$3/12,A56,$C$2,($C$1)) -> -376090.02 | D56: =B56+C56 -> 118759.26 | G56: 50 | H56: =$I$4 -> 209110.02 | I56: =IPMT($I$3/12,G56,$I$2,($I$1)) -> -150332.89 | J56: =H56+I56 -> 58777.131 | M56: 50 | N56: =$O$4 -> 387649.47 | O56: =IPMT($O$3/12,G56,$O$2,($O$1)) -> -260014.82 | P56: =N56+O56 -> 127634.65 | S56: 50 | T56: =$U$4 -> 501501.74 | U56: =IPMT($U$3/12,S56,$U$2,($U$1)) -> -308058.01 | V56: =T56+U56 -> 193443.73 | Y56: 50 | Z56: =$AA$4 -> 143286.21 | AA56: =IPMT($AA$3/12,Y56,$AA$2,($AA$1)) -> -88016.576 | AB56: =Z56+AA56 -> 55269.636 | AE56: 50 | AF56: =$AG$4 -> 586008.13 | AG56: =IPMT($AG$3/12,AE56,$AG$2,($AG$1)) -> -173544.12 | AH56: =AF56+AG56 -> 412464.02
A57: 51 | B57: =$C$4 -> 494849.28 | C57: =IPMT($C$3/12,A57,$C$2,($C$1)) -> -375199.32 | D57: =B57+C57 -> 119649.95 | G57: 51 | H57: =$I$4 -> 209110.02 | I57: =IPMT($I$3/12,G57,$I$2,($I$1)) -> -149941.04 | J57: =H57+I57 -> 59168.979 | M57: 51 | N57: =$O$4 -> 387649.47 | O57: =IPMT($O$3/12,G57,$O$2,($O$1)) -> -259270.28 | P57: =N57+O57 -> 128379.19 | S57: 51 | T57: =$U$4 -> 501501.74 | U57: =IPMT($U$3/12,S57,$U$2,($U$1)) -> -307090.8 | V57: =T57+U57 -> 194410.94 | Y57: 51 | Z57: =$AA$4 -> 143286.21 | AA57: =IPMT($AA$3/12,Y57,$AA$2,($AA$1)) -> -87740.227 | AB57: =Z57+AA57 -> 55545.984 | AE57: 51 | AF57: =$AG$4 -> 586008.13 | AG57: =IPMT($AG$3/12,AE57,$AG$2,($AG$1)) -> -170450.64 | AH57: =AF57+AG57 -> 415557.5
A58: 52 | B58: =$C$4 -> 494849.28 | C58: =IPMT($C$3/12,A58,$C$2,($C$1)) -> -374301.95 | D58: =B58+C58 -> 120547.33 | G58: 52 | H58: =$I$4 -> 209110.02 | I58: =IPMT($I$3/12,G58,$I$2,($I$1)) -> -149546.58 | J58: =H58+I58 -> 59563.439 | M58: 52 | N58: =$O$4 -> 387649.47 | O58: =IPMT($O$3/12,G58,$O$2,($O$1)) -> -258521.4 | P58: =N58+O58 -> 129128.07 | S58: 52 | T58: =$U$4 -> 501501.74 | U58: =IPMT($U$3/12,S58,$U$2,($U$1)) -> -306118.74 | V58: =T58+U58 -> 195383 | Y58: 52 | Z58: =$AA$4 -> 143286.21 | AA58: =IPMT($AA$3/12,Y58,$AA$2,($AA$1)) -> -87462.497 | AB58: =Z58+AA58 -> 55823.714 | AE58: 52 | AF58: =$AG$4 -> 586008.13 | AG58: =IPMT($AG$3/12,AE58,$AG$2,($AG$1)) -> -167333.95 | AH58: =AF58+AG58 -> 418674.18
A59: 53 | B59: =$C$4 -> 494849.28 | C59: =IPMT($C$3/12,A59,$C$2,($C$1)) -> -373397.85 | D59: =B59+C59 -> 121451.43 | G59: 53 | H59: =$I$4 -> 209110.02 | I59: =IPMT($I$3/12,G59,$I$2,($I$1)) -> -149149.49 | J59: =H59+I59 -> 59960.528 | M59: 53 | N59: =$O$4 -> 387649.47 | O59: =IPMT($O$3/12,G59,$O$2,($O$1)) -> -257768.15 | P59: =N59+O59 -> 129881.31 | S59: 53 | T59: =$U$4 -> 501501.74 | U59: =IPMT($U$3/12,S59,$U$2,($U$1)) -> -305141.83 | V59: =T59+U59 -> 196359.91 | Y59: 53 | Z59: =$AA$4 -> 143286.21 | AA59: =IPMT($AA$3/12,Y59,$AA$2,($AA$1)) -> -87183.379 | AB59: =Z59+AA59 -> 56102.833 | AE59: 53 | AF59: =$AG$4 -> 586008.13 | AG59: =IPMT($AG$3/12,AE59,$AG$2,($AG$1)) -> -164193.9 | AH59: =AF59+AG59 -> 421814.23
A60: 54 | B60: =$C$4 -> 494849.28 | C60: =IPMT($C$3/12,A60,$C$2,($C$1)) -> -372486.96 | D60: =B60+C60 -> 122362.32 | G60: 54 | H60: =$I$4 -> 209110.02 | I60: =IPMT($I$3/12,G60,$I$2,($I$1)) -> -148749.75 | J60: =H60+I60 -> 60360.265 | M60: 54 | N60: =$O$4 -> 387649.47 | O60: =IPMT($O$3/12,G60,$O$2,($O$1)) -> -257010.51 | P60: =N60+O60 -> 130638.95 | S60: 54 | T60: =$U$4 -> 501501.74 | U60: =IPMT($U$3/12,S60,$U$2,($U$1)) -> -304160.03 | V60: =T60+U60 -> 197341.71 | Y60: 54 | Z60: =$AA$4 -> 143286.21 | AA60: =IPMT($AA$3/12,Y60,$AA$2,($AA$1)) -> -86902.865 | AB60: =Z60+AA60 -> 56383.347 | AE60: 54 | AF60: =$AG$4 -> 586008.13 | AG60: =IPMT($AG$3/12,AE60,$AG$2,($AG$1)) -> -161030.29 | AH60: =AF60+AG60 -> 424977.84
A61: 55 | B61: =$C$4 -> 494849.28 | C61: =IPMT($C$3/12,A61,$C$2,($C$1)) -> -371569.24 | D61: =B61+C61 -> 123280.03 | G61: 55 | H61: =$I$4 -> 209110.02 | I61: =IPMT($I$3/12,G61,$I$2,($I$1)) -> -148347.35 | J61: =H61+I61 -> 60762.667 | M61: 55 | N61: =$O$4 -> 387649.47 | O61: =IPMT($O$3/12,G61,$O$2,($O$1)) -> -256248.45 | P61: =N61+O61 -> 131401.01 | S61: 55 | T61: =$U$4 -> 501501.74 | U61: =IPMT($U$3/12,S61,$U$2,($U$1)) -> -303173.32 | V61: =T61+U61 -> 198328.42 | Y61: 55 | Z61: =$AA$4 -> 143286.21 | AA61: =IPMT($AA$3/12,Y61,$AA$2,($AA$1)) -> -86620.948 | AB61: =Z61+AA61 -> 56665.264 | AE61: 55 | AF61: =$AG$4 -> 586008.13 | AG61: =IPMT($AG$3/12,AE61,$AG$2,($AG$1)) -> -157842.96 | AH61: =AF61+AG61 -> 428165.17
A62: 56 | B62: =$C$4 -> 494849.28 | C62: =IPMT($C$3/12,A62,$C$2,($C$1)) -> -370644.64 | D62: =B62+C62 -> 124204.63 | G62: 56 | H62: =$I$4 -> 209110.02 | I62: =IPMT($I$3/12,G62,$I$2,($I$1)) -> -147942.27 | J62: =H62+I62 -> 61167.751 | M62: 56 | N62: =$O$4 -> 387649.47 | O62: =IPMT($O$3/12,G62,$O$2,($O$1)) -> -255481.95 | P62: =N62+O62 -> 132167.52 | S62: 56 | T62: =$U$4 -> 501501.74 | U62: =IPMT($U$3/12,S62,$U$2,($U$1)) -> -302181.68 | V62: =T62+U62 -> 199320.06 | Y62: 56 | Z62: =$AA$4 -> 143286.21 | AA62: =IPMT($AA$3/12,Y62,$AA$2,($AA$1)) -> -86337.622 | AB62: =Z62+AA62 -> 56948.59 | AE62: 56 | AF62: =$AG$4 -> 586008.13 | AG62: =IPMT($AG$3/12,AE62,$AG$2,($AG$1)) -> -154631.72 | AH62: =AF62+AG62 -> 431376.41
A63: 57 | B63: =$C$4 -> 494849.28 | C63: =IPMT($C$3/12,A63,$C$2,($C$1)) -> -369713.11 | D63: =B63+C63 -> 125136.17 | G63: 57 | H63: =$I$4 -> 209110.02 | I63: =IPMT($I$3/12,G63,$I$2,($I$1)) -> -147534.48 | J63: =H63+I63 -> 61575.536 | M63: 57 | N63: =$O$4 -> 387649.47 | O63: =IPMT($O$3/12,G63,$O$2,($O$1)) -> -254710.97 | P63: =N63+O63 -> 132938.5 | S63: 57 | T63: =$U$4 -> 501501.74 | U63: =IPMT($U$3/12,S63,$U$2,($U$1)) -> -301185.08 | V63: =T63+U63 -> 200316.67 | Y63: 57 | Z63: =$AA$4 -> 143286.21 | AA63: =IPMT($AA$3/12,Y63,$AA$2,($AA$1)) -> -86052.879 | AB63: =Z63+AA63 -> 57233.333 | AE63: 57 | AF63: =$AG$4 -> 586008.13 | AG63: =IPMT($AG$3/12,AE63,$AG$2,($AG$1)) -> -151396.4 | AH63: =AF63+AG63 -> 434611.74
A64: 58 | B64: =$C$4 -> 494849.28 | C64: =IPMT($C$3/12,A64,$C$2,($C$1)) -> -368774.59 | D64: =B64+C64 -> 126074.69 | G64: 58 | H64: =$I$4 -> 209110.02 | I64: =IPMT($I$3/12,G64,$I$2,($I$1)) -> -147123.98 | J64: =H64+I64 -> 61986.04 | M64: 58 | N64: =$O$4 -> 387649.47 | O64: =IPMT($O$3/12,G64,$O$2,($O$1)) -> -253935.5 | P64: =N64+O64 -> 133713.97 | S64: 58 | T64: =$U$4 -> 501501.74 | U64: =IPMT($U$3/12,S64,$U$2,($U$1)) -> -300183.49 | V64: =T64+U64 -> 201318.25 | Y64: 58 | Z64: =$AA$4 -> 143286.21 | AA64: =IPMT($AA$3/12,Y64,$AA$2,($AA$1)) -> -85766.712 | AB64: =Z64+AA64 -> 57519.5 | AE64: 58 | AF64: =$AG$4 -> 586008.13 | AG64: =IPMT($AG$3/12,AE64,$AG$2,($AG$1)) -> -148136.81 | AH64: =AF64+AG64 -> 437871.32
A65: 59 | B65: =$C$4 -> 494849.28 | C65: =IPMT($C$3/12,A65,$C$2,($C$1)) -> -367829.03 | D65: =B65+C65 -> 127020.25 | G65: 59 | H65: =$I$4 -> 209110.02 | I65: =IPMT($I$3/12,G65,$I$2,($I$1)) -> -146710.74 | J65: =H65+I65 -> 62399.28 | M65: 59 | N65: =$O$4 -> 387649.47 | O65: =IPMT($O$3/12,G65,$O$2,($O$1)) -> -253155.5 | P65: =N65+O65 -> 134493.97 | S65: 59 | T65: =$U$4 -> 501501.74 | U65: =IPMT($U$3/12,S65,$U$2,($U$1)) -> -299176.9 | V65: =T65+U65 -> 202324.84 | Y65: 59 | Z65: =$AA$4 -> 143286.21 | AA65: =IPMT($AA$3/12,Y65,$AA$2,($AA$1)) -> -85479.115 | AB65: =Z65+AA65 -> 57807.097 | AE65: 59 | AF65: =$AG$4 -> 586008.13 | AG65: =IPMT($AG$3/12,AE65,$AG$2,($AG$1)) -> -144852.77 | AH65: =AF65+AG65 -> 441155.36
A66: 60 | B66: =$C$4 -> 494849.28 | C66: =IPMT($C$3/12,A66,$C$2,($C$1)) -> -366876.37 | D66: =B66+C66 -> 127972.9 | E66: =SUM(C55:C66) -> -4463857.2 | G66: 60 | H66: =$I$4 -> 209110.02 | I66: =IPMT($I$3/12,G66,$I$2,($I$1)) -> -146294.74 | J66: =H66+I66 -> 62815.275 | K66: =SUM(I55:I66) -> -1782395.4 | M66: 60 | N66: =$O$4 -> 387649.47 | O66: =IPMT($O$3/12,G66,$O$2,($O$1)) -> -252370.95 | P66: =N66+O66 -> 135278.52 | Q66: =SUM(O55:O66) -> -3079243.5 | S66: 60 | T66: =$U$4 -> 501501.74 | U66: =IPMT($U$3/12,S66,$U$2,($U$1)) -> -298165.28 | V66: =T66+U66 -> 203336.46 | W66: =SUM(U55:U66) -> -3643655.6 | Y66: 60 | Z66: =$AA$4 -> 143286.21 | AA66: =IPMT($AA$3/12,Y66,$AA$2,($AA$1)) -> -85190.079 | AB66: =Z66+AA66 -> 58096.133 | AC66: =SUM(AA55:AA66) -> -1041044.4 | AE66: 60 | AF66: =$AG$4 -> 586008.13 | AG66: =IPMT($AG$3/12,AE66,$AG$2,($AG$1)) -> -141544.11 | AH66: =AF66+AG66 -> 444464.02 | AI66: =SUM(AG55:AG66) -> -1911572.2
E67: =SUM(D55:D66) -> 1474334.1 | K67: =SUM(J55:J66) -> 726924.77 | Q67: =SUM(P55:P66) -> 1572550.1 | W67: =SUM(V55:V66) -> 2374365.3 | AC67: =SUM(AB55:AB66) -> 678390.09 | AI67: =SUM(AH55:AH66) -> 5120525.4
C68: =SUM(C7:C66) -> -23479833 | D68: =SUM(D7:D66) -> 6211123 | E68: =SUM(E66,E54,E42,E30,E18) -> -23479833
E69: =SUM(E67,E55,E43,E31,E19) -> 6211123
